Workbook
Name activity_cost: [1]マスタ!$F$4
Name Career_Track: '[2]Career Track '!$A$2:$A$7
Name Cost_Center: '[2]Cost Center'!$A$2:$A$628
Name Deployed_to_Entity: '[2]Deployed-to Entity'!$A$2:$A$69
Name Level: [2]Level!$A$3:$A$13
Name Organization_Unit: '[2]Organization Unit'!$A$2:$A$630
Name SV: '[3]99_List'!$H$4:$H$10
Name アサインチーム: #REF!
Name サービス: #REF!
Name サービステーブル: #REF!
Name サービス一覧: #REF!
Name サービス管理番号: #REF!
Name チームラベリング: [4]List!$F$3:$H$47
Name チームラベリング設定: #REF!
Name フラグ: #REF!
Name 案件種別: [5]List!$A$3:$A$4
Name 案件種別: #REF!
Name 改善案件: #REF!
Name 拠点: [6]!tbl拠点情報[拠点]
Name 公休: [4]List!$C$3:$C$8
Name 公休検索: [4]List!$C$3:$D$8
Name 使用する: [5]List!$F$3:$F$4
Name 使用する: #REF!
Name 所属チーム: [4]List!$A$3:$A$5
Name 組織: '[7]CCJ管理用(記入不要)'!#REF!
Name 担当: #REF!
Name 担当グループ: [8]List!#REF!
Name 担当拠点: [5]List!$K$3:$K$7
Name 担当拠点: #REF!
Name 担当業務: [4]List!$B$3:$B$5
Name 判断基準: [4]習熟度!$C$2:$C$5
Name 非稼働日: #REF!
Name 頻度: [5]List!$E$3:$E$12
Name 頻度: #REF!
Name 返信方法: [5]List!$J$3:$J$5
Name 返信方法: #REF!
Name 優先度: #REF!
Name 有無: [5]List!$G$3:$G$6
Name 有無: #REF!
Name 立川: #REF!

Sheet Update History
B1: ***Highly Confidential. Not To Be Distributed Further Without Authorization of the Sender.***
B2: PJT・サテライト内のみ共有可
B3: Update History | H3: e
B4: Document History | H4: e
B5: Ver. | C5: Date | D5: Created/Updated by (Team, EID) | E5: Update contents | F5: Reviewed by (EID) | G5: Approved by (EID) | H5: e
B6: 1 | C6: 46182 | D6: PwD雇用促進PJT 運用企画T satomi.taguchi | E6: ・新規作成 | F6: shunya.furukawa tetsuyo.yonemura | G6: michiko.sone | H6: e
H7: e
H8: e
H9: e
H10: e
H11: e
H12: e
H13: e
H14: e
H15: e
H16: e
H17: e
H18: e
... H25: e
A26: e | B26: e | C26: e | D26: e | E26: e | F26: e | G26: e

Sheet 使い方ガイド
B1: ***Highly Confidential. Not To Be Distributed Further Without Authorization of the Sender. *** Copyright © 2026 Accenture. All rights reserved.
B2: PJT・サテライトのみ共有可
B3: 全員必ずお読みください！
B4: 本Excel使い方ガイド
B6: 前提： | C6: ①チーム毎に本Excelフォーマットを使って、SV/案件担当者の方より、案件・タスク管理をいただきます。
C7: ∟案件管理は本フォーマットを使うことを必須とします。
C8: ∟タスク管理は本フォーマットを使うか、各チームで既に使っている管理シートがあればそちらを使うでも構いません。
C9: 別途担当者への振り出し・進捗確認・完了やり取りは、これまで通りTeams専用チャネルを活用ください。
C10: 右記、概要説明会スライド参照
C12: ②チーム毎の過去のサービス/案件/タスク情報を反映した案件管理Excelは、PJTより現行BI[OrderList]からエクスポートの上、6月上~中旬頃断面版で配布予定です。
B14: [案件管理マスタ]シート
B15: 対象 | C15: 案件・タスクを管理するSV・案件管理担当者
C16: （案件・タスクの全体進捗状況を確認したいメンバ向け）
B17: 役割 | C17: 案件・タスクの進捗状況管理
B18: 更新者 | C18: SV・案件管理担当者
B19: 使い方 | C19: 新運用開始前(~6末)： | D19: 各チームでサービス/案件/（タスク）情報を最新化する ※PJTで6月上~中旬頃の断面版は配布予定
B20: 使い方 | C20: 新運用開始後(7/1~)： | D20: 常時：[案件管理マスタ]の折りたたみ（4～9行目）のガイドに沿って入力・管理をする
D21: 適宜：サービス情報に更新がある際は、最新のサービス情報マスタを[サービス情報マスタcopy]シートに転記する
B23: [マイタスク]シート
B24: 対象 | C24: 自分が対応するタスク情報のみを抽出して確認したい方
C25: ※本Excelの[案件・タスク版]でタスク管理する場合のみ使用できます。
B26: 役割 | C26: 自分のタスク一覧の確認
B27: 更新者 | C27: 全員
B28: 使い方 | C28: 前提： | D28: 本シートはExcelをダウンロードの上ローカル環境で使用ください（複数名同時に操作によるバッティングを防ぐため）
C29: 手順①： | D29: [マイタスク]シートを開く
C30: 手順②： | D30: U5セル（青いセル）に自分のEIDを入力する
D31: →自分が関わるタスクが自動で一覧表示される
C32: 手順③： | D32: 「自分の役割」列で作業者・ピアレビュー者・SVレビュー者のどれかを確認する

Sheet 案件管理マスタ_案件のみ版
B1: ***Highly Confidential. Not To Be Distributed Further Without Authorization of the Sender. *** Copyright © 2026 Accenture. All rights reserved.
B2: PJT・サテライトのみ共有可
B3: 更新頻度：日次でメンテナンスをお願いします。 | L3: e
C4: 【前提】 | L4: e
C5: ・案件管理は本フォーマットを使うことを必須とします。（全チームが必ず使う列を★で示していますので、必ず入力ください） | L5: e
C6: ・タスク管理は本フォーマットを使うか（[案件・タスク版]シート★以降の列）、各チームで既に使っている管理シートがあればそちらを使うでも構いません。 | L6: e
C7: 【SV・案件管理担当者による対応事項】 | L7: e
C8: サービス情報マスタより対象のサービス管理番号を転記する | D8: ー （サービス管理番号に応じて、サービス情報マスタcopyシートより、サービス名が自動反映される） | E8: 関数で採番された番号をダブルチェックの上、コピーし、値で貼り付けする ※過去の案件番号を参照し自動で番号が振りあてられるので、正しい採番かを再確認する ※その上で案件番号を値で貼り付けする（関数のままだと、過去の完了案件情報を消した際に採番が変わってしまうため） | F8: 対象案件の作業マニュアルで案内されているルールに沿って案件名を決める＆記載する | G8: チーム名を記載する（基本チーム毎のExcel管理を想定）チーム横断の場合の方針は下記参照 | H8: プルダウン選択 | I8: ー （作業実行者の実績開始日が自動反映される） ※本フォーマットでタスク管理を行わない場合は、関数を解除の上手入力ください。 | J8: ・依頼元レビューが完了した日(AD列)を入力する ・依頼元レビューがない場合は、SVレビューが完了し、全ての内部レビューが完了した日を入力する ※日付を入力するとグレーアウトされる | L8: e
L9: e
B10: 青字：関数で自動反映 | L10: e
B11: 必須： | C11: ★ | D11: ★ | E11: ★ | F11: ★ | G11: ★ | H11: ★ | I11: ★ | J11: ★ | L11: e
B12: # | C12: サービス管理番号 | D12: サービス名 | E12: 案件番号 | F12: 案件名 | G12: チーム(案件) | H12: 案件ステータス | I12: 案件デリバリ開始日 | J12: 案件デリバリ完了日 | K12: 採番用(触らない) | L12: e
B13: 1 | C13: A0098 | D13: HR_myTIM/OTデータ作成(Google) | E13: A0098-0032 | F13: 【OT】HR_myTIM/OTデータ作成(Google) 12月度 | G13: 生麦X | H13: デリバリ完了 | I13: 0 | K13: =VALUE(RIGHT($E13,4)) -> 32 | L13: e
B14: 2 | C14: P1999 | D14: テスト運用サービス(SN) | E14: P1999-0073 | F14: 【テスト運用】HPS_JPiT月次基盤資料作成 | G14: 生麦X | H14: デリバリ完了 | I14: 0 | K14: =VALUE(RIGHT($E14,4)) -> 73 | L14: e
B15: 3 | C15: P3999 | D15: テスト運用サービス・データ計測不可(共通) | E15: P3999-1986 | F15: 【杉山さん】ツール練習 | G15: 生麦X | H15: デリバリ完了 | I15: 0 | K15: =VALUE(RIGHT($E15,4)) -> 1986 | L15: e
B16: 4 | C16: A1031 | D16: I&D_Women's stories記事配信 | E16: A1031-0279 | F16: I&D_Women's stories記事配信 英訳追加① No1～7 | G16: 生麦X | H16: タスク進行中 | I16: 0 | K16: =VALUE(RIGHT($E16,4)) -> 279 | L16: e
B17: 5 | C17: A1031 | D17: I&D_Women's stories記事配信 | E17: A1031-0280 | F17: I&D_Women's stories記事配信 英訳追加② No8～13 | G17: 生麦X | H17: 内部完了 | I17: 0 | K17: =VALUE(RIGHT($E17,4)) -> 280 | L17: e
B18: 6 | C18: P1999 | D18: テスト運用サービス(SN) | E18: P1999-0011 | F18: IC-Energy_石油3社のプレスリリース__日経News情報11/24週テスト運用① | G18: 生麦X | H18: デリバリ完了 | I18: 0 | K18: =VALUE(RIGHT($E18,4)) -> 11 | L18: e
B19: 7 | C19: A1025 | D19: 人事異動・組織改編情報チェック(自動化) | E19: A1025-0880 | F19: Nトレーニング人事異動（佐藤さん）⑦ | G19: 生麦X | H19: デリバリ完了 | I19: 0 | K19: =VALUE(RIGHT($E19,4)) -> 880 | L19: e
B20: 8 | C20: A1025 | D20: 人事異動・組織改編情報チェック(自動化) | E20: A1025-0881 | F20: Nトレーニング人事異動（佐藤さん）⑦ | G20: 生麦X | H20: デリバリ完了 | I20: 0 | K20: =VALUE(RIGHT($E20,4)) -> 881 | L20: e
B21: 9 | C21: P3999 | D21: テスト運用サービス・データ計測不可(共通) | E21: P3999-1701 | F21: Nトレーニング人事異動（佐藤さん）⑦ | G21: 生麦X | H21: デリバリ完了 | I21: 0 | K21: =VALUE(RIGHT($E21,4)) -> 1701 | L21: e
B22: 10 | C22: P3999 | D22: テスト運用サービス・データ計測不可(共通) | E22: P3999-1705 | F22: Nトレーニング人事異動（佐藤さん）⑦ | G22: 生麦X | H22: デリバリ完了 | I22: 0 | K22: =VALUE(RIGHT($E22,4)) -> 1705 | L22: e
B23: 11 | C23: P3999 | D23: テスト運用サービス・データ計測不可(共通) | E23: P3999-1702 | F23: Nトレーニング人事異動（山岸さん）⑦ | G23: 生麦X | H23: デリバリ完了 | I23: 0 | K23: =VALUE(RIGHT($E23,4)) -> 1702 | L23: e
B24: 12 | C24: P3999 | D24: テスト運用サービス・データ計測不可(共通) | E24: P3999-1704 | F24: Nトレーニング人事異動（山岸さん）⑦ | G24: 生麦X | H24: デリバリ完了 | I24: 0 | K24: =VALUE(RIGHT($E24,4)) -> 1704 | L24: e
... B92: 80 | C92: A0098 | D92: HR_myTIM/OTデータ作成(Google) | E92: A0098-0004 | F92: 【myTIM】HR_myTIM/OTデータ作成(Google) 7/7週 | G92: 生麦X | H92: デリバリ完了 | I92: 0 | K92: =VALUE(RIGHT($E92,4)) -> 4 | L92: e
B93: 81 | C93: A0098 | D93: HR_myTIM/OTデータ作成(Google) | E93: A0098-0012 | F93: 【myTIM】HR_myTIM/OTデータ作成(Google) 8/18週 | G93: 生麦X | H93: デリバリ完了 | K93: =VALUE(RIGHT($E93,4)) -> 12 | L93: e
B94: 82 | C94: A0098 | D94: HR_myTIM/OTデータ作成(Google) | E94: A0098-0013 | F94: 【myTIM】HR_myTIM/OTデータ作成(Google) 8/18週 | G94: 生麦X | H94: デリバリ完了 | K94: =VALUE(RIGHT($E94,4)) -> 13 | L94: e
B95: 83 | C95: A0098 | D95: HR_myTIM/OTデータ作成(Google) | E95: A0098-0010 | F95: 【myTIM】HR_myTIM/OTデータ作成(Google) 8/4週 | G95: 生麦X | H95: デリバリ完了 | K95: =VALUE(RIGHT($E95,4)) -> 10 | L95: e
B96: 84 | C96: A0098 | D96: HR_myTIM/OTデータ作成(Google) | E96: A0098-0017 | F96: 【myTIM】HR_myTIM/OTデータ作成(Google) 9/15週 | G96: 生麦X | H96: デリバリ完了 | K96: =VALUE(RIGHT($E96,4)) -> 17 | L96: e
B97: 85 | C97: A0098 | D97: HR_myTIM/OTデータ作成(Google) | E97: A0098-0014 | F97: 【myTIM】HR_myTIM/OTデータ作成(Google) 9/1週 | G97: 生麦X | H97: デリバリ完了 | K97: =VALUE(RIGHT($E97,4)) -> 14 | L97: e
B98: 86 | C98: A0098 | D98: HR_myTIM/OTデータ作成(Google) | E98: A0098-0018 | F98: 【myTIM】HR_myTIM/OTデータ作成(Google) 9/22週 | G98: 生麦X | H98: デリバリ完了 | K98: =VALUE(RIGHT($E98,4)) -> 18 | L98: e
B99: 87 | C99: A0098 | D99: HR_myTIM/OTデータ作成(Google) | E99: A0098-0019 | F99: 【myTIM】HR_myTIM/OTデータ作成(Google) 9/29週 | G99: 生麦X | H99: デリバリ完了 | K99: =VALUE(RIGHT($E99,4)) -> 19 | L99: e
B100: 88 | C100: A0098 | D100: HR_myTIM/OTデータ作成(Google) | E100: A0098-0015 | F100: 【myTIM】HR_myTIM/OTデータ作成(Google) 9/8週 | G100: 生麦X | H100: デリバリ完了 | K100: =VALUE(RIGHT($E100,4)) -> 15 | L100: e
B101: 89 | C101: P3000 | D101: 改善案件(共通) | E101: P3000-0658 | F101: 【myTIM】HR_myTIM/OTデータ作成(Google) マニュアル修正 | G101: 生麦X | H101: デリバリ完了 | K101: =VALUE(RIGHT($E101,4)) -> 658 | L101: e
B102: 90 | C102: P3000 | D102: 改善案件(共通) | E102: P3000-0838 | F102: 【myTIM】HR_myTIM/OTデータ作成(Google) マニュアル修正 | G102: 生麦X | H102: デリバリ完了 | K102: =VALUE(RIGHT($E102,4)) -> 838 | L102: e
B103: 91 | C103: P3000 | D103: 改善案件(共通) | E103: P3000-0714 | F103: 【myTIM】HR_myTIM/OTデータ作成(Google) マニュアル改定 | G103: 生麦X | H103: デリバリ完了 | K103: =VALUE(RIGHT($E103,4)) -> 714 | L103: e
B104: 92 | C104: P3000 | D104: 改善案件(共通) | E104: P3000-0415 | F104: 【myTIM】マニュアル見直し | G104: 生麦X | H104: デリバリ完了 | K104: =VALUE(RIGHT($E104,4)) -> 415 | L104: e
... B4165: 4153 | C4165: P3999 | D4165: テスト運用サービス・データ計測不可(共通) | E4165: P3999-1700 | F4165: 起票練習用 | G4165: 生麦X | H4165: デリバリ完了 | K4165: =VALUE(RIGHT($E4165,4)) -> 1700 | L4165: e
B4166: 4154 | D4166: =_xlfn.XLOOKUP($C4166,サービス情報マスタcopy!$B:$B,サービス情報マスタcopy!$G:$G,0,0,1) -> 0 | E4166: =CONCATENATE($C4166,"-",TEXT(_xlfn.MAXIFS($K$12:K4165,$C$12:C4165,$C4166)+1,"0000")) -> -0001 | K4166: =VALUE(RIGHT($E4166,4)) -> 1 | L4166: e
B4167: 4155 | D4167: =_xlfn.XLOOKUP($C4167,サービス情報マスタcopy!$B:$B,サービス情報マスタcopy!$G:$G,0,0,1) -> 0 | E4167: =CONCATENATE($C4167,"-",TEXT(_xlfn.MAXIFS($K$12:K4166,$C$12:C4166,$C4167)+1,"0000")) -> -0001 | K4167: =VALUE(RIGHT($E4167,4)) -> 1 | L4167: e
B4168: 4156 | D4168: =_xlfn.XLOOKUP($C4168,サービス情報マスタcopy!$B:$B,サービス情報マスタcopy!$G:$G,0,0,1) -> 0 | E4168: =CONCATENATE($C4168,"-",TEXT(_xlfn.MAXIFS($K$12:K4167,$C$12:C4167,$C4168)+1,"0000")) -> -0001 | K4168: =VALUE(RIGHT($E4168,4)) -> 1 | L4168: e
B4169: 4157 | D4169: =_xlfn.XLOOKUP($C4169,サービス情報マスタcopy!$B:$B,サービス情報マスタcopy!$G:$G,0,0,1) -> 0 | E4169: =CONCATENATE($C4169,"-",TEXT(_xlfn.MAXIFS($K$12:K4168,$C$12:C4168,$C4169)+1,"0000")) -> -0001 | K4169: =VALUE(RIGHT($E4169,4)) -> 1 | L4169: e
B4170: 4158 | D4170: =_xlfn.XLOOKUP($C4170,サービス情報マスタcopy!$B:$B,サービス情報マスタcopy!$G:$G,0,0,1) -> 0 | E4170: =CONCATENATE($C4170,"-",TEXT(_xlfn.MAXIFS($K$12:K4169,$C$12:C4169,$C4170)+1,"0000")) -> -0001 | K4170: =VALUE(RIGHT($E4170,4)) -> 1 | L4170: e
B4171: 4159 | D4171: =_xlfn.XLOOKUP($C4171,サービス情報マスタcopy!$B:$B,サービス情報マスタcopy!$G:$G,0,0,1) -> 0 | E4171: =CONCATENATE($C4171,"-",TEXT(_xlfn.MAXIFS($K$12:K4170,$C$12:C4170,$C4171)+1,"0000")) -> -0001 | K4171: =VALUE(RIGHT($E4171,4)) -> 1 | L4171: e
B4172: 4160 | D4172: =_xlfn.XLOOKUP($C4172,サービス情報マスタcopy!$B:$B,サービス情報マスタcopy!$G:$G,0,0,1) -> 0 | E4172: =CONCATENATE($C4172,"-",TEXT(_xlfn.MAXIFS($K$12:K4171,$C$12:C4171,$C4172)+1,"0000")) -> -0001 | K4172: =VALUE(RIGHT($E4172,4)) -> 1 | L4172: e
B4173: 4161 | D4173: =_xlfn.XLOOKUP($C4173,サービス情報マスタcopy!$B:$B,サービス情報マスタcopy!$G:$G,0,0,1) -> 0 | E4173: =CONCATENATE($C4173,"-",TEXT(_xlfn.MAXIFS($K$12:K4172,$C$12:C4172,$C4173)+1,"0000")) -> -0001 | K4173: =VALUE(RIGHT($E4173,4)) -> 1 | L4173: e
B4174: 4162 | D4174: =_xlfn.XLOOKUP($C4174,サービス情報マスタcopy!$B:$B,サービス情報マスタcopy!$G:$G,0,0,1) -> 0 | E4174: =CONCATENATE($C4174,"-",TEXT(_xlfn.MAXIFS($K$12:K4173,$C$12:C4173,$C4174)+1,"0000")) -> -0001 | K4174: =VALUE(RIGHT($E4174,4)) -> 1 | L4174: e
B4175: 4163 | D4175: =_xlfn.XLOOKUP($C4175,サービス情報マスタcopy!$B:$B,サービス情報マスタcopy!$G:$G,0,0,1) -> 0 | E4175: =CONCATENATE($C4175,"-",TEXT(_xlfn.MAXIFS($K$12:K4174,$C$12:C4174,$C4175)+1,"0000")) -> -0001 | K4175: =VALUE(RIGHT($E4175,4)) -> 1 | L4175: e
B4176: 4164 | D4176: =_xlfn.XLOOKUP($C4176,サービス情報マスタcopy!$B:$B,サービス情報マスタcopy!$G:$G,0,0,1) -> 0 | E4176: =CONCATENATE($C4176,"-",TEXT(_xlfn.MAXIFS($K$12:K4175,$C$12:C4175,$C4176)+1,"0000")) -> -0001 | K4176: =VALUE(RIGHT($E4176,4)) -> 1 | L4176: e
B4177: 4165 | D4177: =_xlfn.XLOOKUP($C4177,サービス情報マスタcopy!$B:$B,サービス情報マスタcopy!$G:$G,0,0,1) -> 0 | E4177: =CONCATENATE($C4177,"-",TEXT(_xlfn.MAXIFS($K$12:K4176,$C$12:C4176,$C4177)+1,"0000")) -> -0001 | K4177: =VALUE(RIGHT($E4177,4)) -> 1 | L4177: e
... B10013: 10337 | D10013: =_xlfn.XLOOKUP($C10013,サービス情報マスタcopy!$B:$B,サービス情報マスタcopy!$G:$G,0,0,1) -> 0 | E10013: =CONCATENATE($C10013,"-",TEXT(_xlfn.MAXIFS($K$12:K10012,$C$12:C10012,$C10013)+1,"0000")) -> -0001 | K10013: =VALUE(RIGHT($E10013,4)) -> 1 | L10013: e
B10014: ↑行はこれより上に追加してください。 | L10014: e
A10015: e | B10015: e | C10015: e | D10015: e | E10015: e | F10015: e | G10015: e | H10015: e | I10015: e | J10015: e | K10015: e | L10015: e

Sheet 案件管理マスタ_案件・タスク版
B1: ***Highly Confidential. Not To Be Distributed Further Without Authorization of the Sender. *** Copyright © 2026 Accenture. All rights reserved.
B2: PJT・サテライトのみ共有可
B3: 更新頻度：日次でメンテナンスをお願いします。 | AG3: e
C4: 【前提】 | AG4: e
C5: ・案件管理は本フォーマットを使うことを必須とします。（全チームが必ず使う列を★で示していますので、必ず入力ください） | AG5: e
C6: ・タスク管理は本フォーマットを使うか（本シート★以降の列）、各チームで既に使っている管理シートがあればそちらを使うでも構いません。 | AG6: e
C7: 【SV・案件管理担当者による対応事項】 | AG7: e
C8: サービス情報マスタより対象のサービス管理番号を転記する | D8: ー （サービス管理番号に応じて、サービス情報マスタcopyシートより、サービス名が自動反映される） | E8: 関数で採番された番号をダブルチェックの上、コピーし、値で貼り付けする ※過去の案件番号を参照し自動で番号が振りあてられるので、正しい採番かを再確認する ※その上で案件番号を値で貼り付けする（関数のままだと、過去の完了案件情報を消した際に採番が変わってしまうため） | F8: 対象案件の作業マニュアルで案内されているルールに沿って案件名を決める＆記載する | G8: チーム名を記載する（基本チーム毎のExcel管理を想定）チーム横断の場合の方針は下記参照 | H8: プルダウン選択 | I8: ー （作業実行者の実績開始日が自動反映される） ※本フォーマットでタスク管理を行わない場合は、関数を解除の上手入力ください。 | J8: ・依頼元レビューが完了した日(AD列)を入力する ・依頼元レビューがない場合は、SVレビューが完了し、全ての内部レビューが完了した日を入力する ※日付を入力するとグレーアウトされる | K8: 過去の採番履歴を確認し、昇順でタスク番号を振る 例)最初のタスクであれば：サービス管理番号-案件番号-01 例)過去のタスクがあれば：サービス管理番号-案件番号-最終番号＋1 | L8: 対象案件の作業マニュアルで案内されているルールに沿ってタスク名を決める＆記載する | M8: プルダウンで選択 | N8: 対象者のEIDを入力する | O8: 実行作業者の開始予定日を入力する | P8: 実行作業者の完了予定日を入力する | Q8: 実行作業者の実際の開始日を入力する ※Teams専用チャネルにてメンバのステータスを確認 ※予定日を超えると赤色で表示されます | R8: 実行作業者の実際の完了日を入力する ※Teams専用チャネルにてメンバのステータスを確認 ※予定日を超えると赤色で表示されます | S8: 対象者のEIDを入力する | T8: ー （実行作業者の予定完了日が自動反映される） | U8: ピアレビュー者の完了予定日を入力する | V8: ピアレビュー者の実際の開始日を入力する ※Teams専用チャネルにてメンバのステータスを確認 ※予定日を超えると赤色で表示されます | W8: ピアレビュー者の実際の完了日を入力する ※Teams専用チャネルにてメンバのステータスを確認 ※予定日を超えると赤色で表示されます | X8: 対象者のEIDを入力する | Y8: ー （ピアレビュー者の予定完了日が自動反映される） | Z8: SVレビュー者の完了予定日を入力する | AA8: SVレビュー者の実際の開始日を入力する ※Teams専用チャネルにてメンバのステータスを確認 ※予定日を超えると赤色になります | AB8: SVレビュー者の実際の完了日を入力する ※Teams専用チャネルにてメンバのステータスを確認 ※予定日を超えると赤色になります | AC8: タスクの依頼元レビュー担当者を入力する ※必要に応じて記載 | AD8: タスクの依頼元レビュー完了日を入力する ※必要に応じて記載 | AE8: ー （マイタスクシートと連動・自動反映） | AG8: e
AG9: e
B10: 青字：関数で自動反映 | AG10: e
B11: 必須： | C11: ★ | D11: ★ | E11: ★ | F11: ★ | G11: ★ | H11: ★ | I11: ★ | J11: ★ | N11: 実行作業者 | S11: ピアレビュー担当者 | X11: SVレビュー担当者 | AC11: 依頼元レビュー担当者 | AG11: e
B12: # | C12: サービス管理番号 | D12: サービス名 | E12: 案件番号 | F12: 案件名 | G12: チーム(案件) | H12: 案件ステータス | I12: 案件デリバリ開始日 | J12: 案件デリバリ完了日 | K12: タスク番号 | L12: タスク名 | M12: タスクステータス | N12: 実行作業担当者 | O12: 予定：開始日 | P12: 予定：完了日 | Q12: 実績：開始日 | R12: 実績：完了日 | S12: ピアレビュー担当者 | T12: 予定：開始日 | U12: 予定：完了日 | V12: 実績：開始日 | W12: 実績：完了日 | X12: SVレビュー担当者 | Y12: 予定：開始日 | Z12: 予定：完了日 | AA12: 実績：開始日 | AB12: 実績：完了日 | AC12: 依頼元レビュー担当者 | AD12: 実績：依頼元レビュー完了日 | AE12: 自分の役割 | AF12: 採番用(触らない) | AG12: e
B13: 1 | C13: A0098 | D13: HR_myTIM/OTデータ作成(Google) | E13: A0098-0032 | F13: 【OT】HR_myTIM/OTデータ作成(Google) 12月度 | G13: 生麦X | H13: デリバリ完了 | I13: =$Q13 -> 0 | K13: A0098-0032-01 | L13: 【OT】HR_myTIM/OTデータ作成(Google) 12月度 調査依頼メール | M13: 集計完了 | N13: rintaro.watanabe | O13: 46000 | S13: shunsuke.taniguchi | T13: 46000 | X13: ryusei.inaba | Y13: 46000 | Z13: 46000 | AE13: =IF($N13=マイタスク!$U$5,"作業者","")&IF($S13=マイタスク!$U$5,"ピアレビュー","")&IF($X13=マイタスク!$U$5,"SVレビュー","") | AF13: =VALUE(RIGHT($E13,4)) -> 32 | AG13: e
B14: 2 | C14: A0098 | D14: HR_myTIM/OTデータ作成(Google) | E14: A0098-0032 | F14: 【OT】HR_myTIM/OTデータ作成(Google) 12月度 | G14: 生麦X | H14: デリバリ完了 | I14: =$Q14 -> 0 | K14: A0098-0032-02 | L14: 【OT】HR_myTIM/OTデータ作成(Google) 12月度 リマインド➀ | M14: 集計完了 | N14: rintaro.watanabe | O14: 46002 | S14: shunsuke.taniguchi | T14: 46002 | X14: ryusei.inaba | Y14: 46002 | Z14: 46002 | AE14: =IF($N14=マイタスク!$U$5,"作業者","")&IF($S14=マイタスク!$U$5,"ピアレビュー","")&IF($X14=マイタスク!$U$5,"SVレビュー","") | AF14: =VALUE(RIGHT($E14,4)) -> 32 | AG14: e
B15: 3 | C15: A0098 | D15: HR_myTIM/OTデータ作成(Google) | E15: A0098-0032 | F15: 【OT】HR_myTIM/OTデータ作成(Google) 12月度 | G15: 生麦X | H15: デリバリ完了 | I15: =$Q15 -> 0 | K15: A0098-0032-03 | L15: 【OT】HR_myTIM/OTデータ作成(Google) 12月度 リマインド② | M15: 集計完了 | N15: rintaro.watanabe | O15: 46003 | S15: shunsuke.taniguchi | T15: 46003 | X15: ryusei.inaba | Y15: 46003 | Z15: 46003 | AE15: =IF($N15=マイタスク!$U$5,"作業者","")&IF($S15=マイタスク!$U$5,"ピアレビュー","")&IF($X15=マイタスク!$U$5,"SVレビュー","") | AF15: =VALUE(RIGHT($E15,4)) -> 32 | AG15: e
B16: 4 | C16: A0098 | D16: HR_myTIM/OTデータ作成(Google) | E16: A0098-0032 | F16: 【OT】HR_myTIM/OTデータ作成(Google) 12月度 | G16: 生麦X | H16: デリバリ完了 | I16: =$Q16 -> 0 | K16: A0098-0032-04 | L16: 【OT】HR_myTIM/OTデータ作成(Google) 12月度 完了報告 | M16: 集計完了 | N16: rintaro.watanabe | O16: 46006 | S16: shunsuke.taniguchi | T16: 46006 | X16: ryusei.inaba | Y16: 46006 | Z16: 46006 | AE16: =IF($N16=マイタスク!$U$5,"作業者","")&IF($S16=マイタスク!$U$5,"ピアレビュー","")&IF($X16=マイタスク!$U$5,"SVレビュー","") | AF16: =VALUE(RIGHT($E16,4)) -> 32 | AG16: e
B17: 5 | C17: P1999 | D17: テスト運用サービス(SN) | E17: P1999-0073 | F17: 【テスト運用】HPS_JPiT月次基盤資料作成 | G17: 生麦X | H17: デリバリ完了 | I17: =$Q17 -> 0 | K17: P1999-0073-01 | L17: 【テスト運用】HPS_JPiT月次基盤資料作成 | M17: 集計完了 | N17: kazuma.motoyama | O17: 45356 | S17: kazuma.motoyama | T17: 45356 | X17: kazuma.motoyama | Y17: 45373 | Z17: 45373 | AE17: =IF($N17=マイタスク!$U$5,"作業者","")&IF($S17=マイタスク!$U$5,"ピアレビュー","")&IF($X17=マイタスク!$U$5,"SVレビュー","") | AF17: =VALUE(RIGHT($E17,4)) -> 73 | AG17: e
B18: 6 | C18: P3999 | D18: テスト運用サービス・データ計測不可(共通) | E18: P3999-1986 | F18: 【杉山さん】ツール練習 | G18: 生麦X | H18: デリバリ完了 | I18: =$Q18 -> 0 | K18: P3999-1986-01 | L18: 【杉山さん】ツール練習 | M18: 集計完了 | N18: joi.sugiyama | O18: 46149 | S18: manami.nanbu | T18: 46149 | X18: shingo.a.maeda | Y18: 46149 | Z18: 46149 | AE18: =IF($N18=マイタスク!$U$5,"作業者","")&IF($S18=マイタスク!$U$5,"ピアレビュー","")&IF($X18=マイタスク!$U$5,"SVレビュー","") | AF18: =VALUE(RIGHT($E18,4)) -> 1986 | AG18: e
B19: 7 | C19: A1031 | D19: I&D_Women's stories記事配信 | E19: A1031-0279 | F19: I&D_Women's stories記事配信 英訳追加① No1～7 | G19: 生麦X | H19: タスク進行中 | I19: =$Q19 -> 0 | K19: A1031-0279-01 | L19: I&D_Women's stories記事配信 英訳追加① No1～7 | M19: ピアレビュー | N19: riamu.daikusu | O19: 46153 | S19: rintaro.watanabe | T19: 46153 | X19: ryota.nozawa | Y19: 46185 | Z19: 46185 | AE19: =IF($N19=マイタスク!$U$5,"作業者","")&IF($S19=マイタスク!$U$5,"ピアレビュー","")&IF($X19=マイタスク!$U$5,"SVレビュー","") | AF19: =VALUE(RIGHT($E19,4)) -> 279 | AG19: e
B20: 8 | C20: A1031 | D20: I&D_Women's stories記事配信 | E20: A1031-0280 | F20: I&D_Women's stories記事配信 英訳追加② No8～13 | G20: 生麦X | H20: 内部完了 | I20: =$Q20 -> 0 | K20: A1031-0280-01 | L20: I&D_Women's stories記事配信 英訳追加② No8～13 | M20: 集計完了 | N20: rintaro.watanabe | O20: 46153 | S20: riamu.daikusu | T20: 46153 | X20: ryota.nozawa | Y20: 46185 | Z20: 46185 | AE20: =IF($N20=マイタスク!$U$5,"作業者","")&IF($S20=マイタスク!$U$5,"ピアレビュー","")&IF($X20=マイタスク!$U$5,"SVレビュー","") | AF20: =VALUE(RIGHT($E20,4)) -> 280 | AG20: e
B21: 9 | C21: P1999 | D21: テスト運用サービス(SN) | E21: P1999-0011 | F21: IC-Energy_石油3社のプレスリリース__日経News情報11/24週テスト運用① | G21: 生麦X | H21: デリバリ完了 | I21: =$Q21 -> 0 | K21: P1999-0011-01 | L21: IC-Energy_石油3社のプレスリリース__日経News情報11/24週テスト運用① | M21: 集計完了 | N21: ayumi.wada | O21: 44889.375 | S21: takuma.fukazawa | T21: 44889.375 | X21: takashi.muramatsu | Y21: 44889.375 | Z21: 44889.375 | AE21: =IF($N21=マイタスク!$U$5,"作業者","")&IF($S21=マイタスク!$U$5,"ピアレビュー","")&IF($X21=マイタスク!$U$5,"SVレビュー","") | AF21: =VALUE(RIGHT($E21,4)) -> 11 | AG21: e
B22: 10 | C22: A1025 | D22: 人事異動・組織改編情報チェック(自動化) | E22: A1025-0880 | F22: Nトレーニング人事異動（佐藤さん）⑦ | G22: 生麦X | H22: デリバリ完了 | I22: =$Q22 -> 0 | K22: A1025-0880-01 | L22: Nトレーニング人事異動（佐藤さん）⑦ | M22: 集計完了 | N22: takao.hattori | O22: 45974 | X22: takao.hattori | Y22: 45974 | Z22: 45974 | AE22: =IF($N22=マイタスク!$U$5,"作業者","")&IF($S22=マイタスク!$U$5,"ピアレビュー","")&IF($X22=マイタスク!$U$5,"SVレビュー","") | AF22: =VALUE(RIGHT($E22,4)) -> 880 | AG22: e
B23: 11 | C23: A1025 | D23: 人事異動・組織改編情報チェック(自動化) | E23: A1025-0881 | F23: Nトレーニング人事異動（佐藤さん）⑦ | G23: 生麦X | H23: デリバリ完了 | I23: =$Q23 -> 0 | K23: A1025-0881-01 | L23: Nトレーニング人事異動（佐藤さん）⑦ | M23: 集計完了 | N23: yuya.tanigaki | O23: 45974 | S23: yuya.tanigaki | T23: 45974 | Z23: 45974 | AE23: =IF($N23=マイタスク!$U$5,"作業者","")&IF($S23=マイタスク!$U$5,"ピアレビュー","")&IF($X23=マイタスク!$U$5,"SVレビュー","") | AF23: =VALUE(RIGHT($E23,4)) -> 881 | AG23: e
B24: 12 | C24: P3999 | D24: テスト運用サービス・データ計測不可(共通) | E24: P3999-1701 | F24: Nトレーニング人事異動（佐藤さん）⑦ | G24: 生麦X | H24: デリバリ完了 | I24: =$Q24 -> 0 | K24: P3999-1701-01 | L24: Nトレーニング人事異動（佐藤さん）⑦ | M24: 集計完了 | N24: yuya.tanigaki | O24: 45974 | S24: yuya.tanigaki | T24: 45974 | Z24: 45975 | AE24: =IF($N24=マイタスク!$U$5,"作業者","")&IF($S24=マイタスク!$U$5,"ピアレビュー","")&IF($X24=マイタスク!$U$5,"SVレビュー","") | AF24: =VALUE(RIGHT($E24,4)) -> 1701 | AG24: e
B25: 13 | C25: P3999 | D25: テスト運用サービス・データ計測不可(共通) | E25: P3999-1705 | F25: Nトレーニング人事異動（佐藤さん）⑦ | G25: 生麦X | H25: デリバリ完了 | I25: =$Q25 -> 0 | K25: P3999-1705-01 | L25: Nトレーニング人事異動（佐藤さん）⑦ | M25: 集計完了 | N25: yuya.tanigaki | O25: 45974 | S25: yuya.tanigaki | T25: 45974 | Z25: 45974 | AE25: =IF($N25=マイタスク!$U$5,"作業者","")&IF($S25=マイタスク!$U$5,"ピアレビュー","")&IF($X25=マイタスク!$U$5,"SVレビュー","") | AF25: =VALUE(RIGHT($E25,4)) -> 1705 | AG25: e
B26: 14 | C26: P3999 | D26: テスト運用サービス・データ計測不可(共通) | E26: P3999-1702 | F26: Nトレーニング人事異動（山岸さん）⑦ | G26: 生麦X | H26: デリバリ完了 | I26: =$Q26 -> 0 | K26: P3999-1702-01 | L26: Nトレーニング人事異動（山岸さん）⑦ | M26: 集計完了 | N26: yuya.tanigaki | O26: 45974 | S26: yuya.tanigaki | T26: 45974 | Z26: 45975 | AE26: =IF($N26=マイタスク!$U$5,"作業者","")&IF($S26=マイタスク!$U$5,"ピアレビュー","")&IF($X26=マイタスク!$U$5,"SVレビュー","") | AF26: =VALUE(RIGHT($E26,4)) -> 1702 | AG26: e
B27: 15 | C27: P3999 | D27: テスト運用サービス・データ計測不可(共通) | E27: P3999-1704 | F27: Nトレーニング人事異動（山岸さん）⑦ | G27: 生麦X | H27: デリバリ完了 | I27: =$Q27 -> 0 | K27: P3999-1704-01 | L27: Nトレーニング人事異動（山岸さん）⑦ | M27: 集計完了 | N27: yuya.tanigaki | O27: 45974 | S27: yuya.tanigaki | T27: 45974 | Z27: 45974 | AE27: =IF($N27=マイタスク!$U$5,"作業者","")&IF($S27=マイタスク!$U$5,"ピアレビュー","")&IF($X27=マイタスク!$U$5,"SVレビュー","") | AF27: =VALUE(RIGHT($E27,4)) -> 1704 | AG27: e
B28: 16 | C28: A1072 | D28: Technology_アクセンチュア健保_chatbot運用保守 | E28: A1072-0036 | F28: Technology_アクセンチュア健保_chatbot運用保守2/3・6 | G28: 生麦X | H28: デリバリ完了 | I28: =$Q28 -> 0 | K28: A1072-0036-01 | L28: Technology_アクセンチュア健保_chatbot運用保守2/3・6 | M28: 集計完了 | N28: takuma.fukazawa | O28: 44960.375 | S28: ryota.nozawa | T28: 44963.375 | X28: ryota.nozawa | Y28: 44963.375 | Z28: 44963.375 | AE28: =IF($N28=マイタスク!$U$5,"作業者","")&IF($S28=マイタスク!$U$5,"ピアレビュー","")&IF($X28=マイタスク!$U$5,"SVレビュー","") | AF28: =VALUE(RIGHT($E28,4)) -> 36 | AG28: e
B29: 17 | C29: A1025 | D29: 人事異動・組織改編情報チェック(自動化) | E29: A1025-0409 | F29: (追加)(PRD_人事異動・組織改編情報チェック(日経転記)⑥(3/4週) | G29: 生麦X | H29: デリバリ完了 | I29: =$Q29 -> 0 | K29: A1025-0409-01 | L29: (追加)(PRD_人事異動・組織改編情報チェック(日経転記)⑥(3/4週) | M29: 集計完了 | N29: kazuma.motoyama | O29: 45355 | S29: ayumi.wada | T29: 45359 | X29: kazuma.motoyama | Y29: 45359 | Z29: 45359 | AE29: =IF($N29=マイタスク!$U$5,"作業者","")&IF($S29=マイタスク!$U$5,"ピアレビュー","")&IF($X29=マイタスク!$U$5,"SVレビュー","") | AF29: =VALUE(RIGHT($E29,4)) -> 409 | AG29: e
B30: 18 | C30: A1025 | D30: 人事異動・組織改編情報チェック(自動化) | E30: A1025-0408 | F30: (追加)PRD_人事異動・組織改編情報チェック(日経転記)⑤(3/4週) | G30: 生麦X | H30: デリバリ完了 | I30: =$Q30 -> 0 | K30: A1025-0408-01 | L30: (追加)PRD_人事異動・組織改編情報チェック(日経転記)⑤(3/4週) | M30: 集計完了 | N30: ayumi.wada | O30: 45355 | S30: kazuma.motoyama | T30: 45359 | X30: kazuma.motoyama | Y30: 45359 | Z30: 45359 | AE30: =IF($N30=マイタスク!$U$5,"作業者","")&IF($S30=マイタスク!$U$5,"ピアレビュー","")&IF($X30=マイタスク!$U$5,"SVレビュー","") | AF30: =VALUE(RIGHT($E30,4)) -> 408 | AG30: e
B31: 19 | C31: P1000 | D31: 共通(SN) | E31: P1000-0130 | F31: [A1024]Digital_マイナポWeb問合せ回答_マニュアル修正 | G31: 生麦X | H31: デリバリ完了 | I31: =$Q31 -> 0 | K31: P1000-0130-01 | L31: [A1024]Digital_マイナポWeb問合せ回答_マニュアル修正 | M31: 集計完了 | N31: yuichi.kimura | O31: 44950.375 | S31: ryota.nozawa | T31: 44953.375 | X31: shigeki.ohtake | Y31: 44953.375 | Z31: 44953.375 | AE31: =IF($N31=マイタスク!$U$5,"作業者","")&IF($S31=マイタスク!$U$5,"ピアレビュー","")&IF($X31=マイタスク!$U$5,"SVレビュー","") | AF31: =VALUE(RIGHT($E31,4)) -> 130 | AG31: e
B32: 20 | C32: P1000 | D32: 共通(SN) | E32: P1000-0137 | F32: [A1046]CMT_クライアントのメディアリリース情報確認_マニュアル修正 | G32: 生麦X | H32: デリバリ完了 | I32: =$Q32 -> 0 | K32: P1000-0137-01 | L32: [A1046]CMT_クライアントのメディアリリース情報確認_マニュアル修正 | M32: 集計完了 | N32: yumi.terui | O32: 44970.375 | S32: takuma.fukazawa | T32: 44970.375 | X32: ayumi.wada | Y32: 44985.375 | Z32: 44985.375 | AE32: =IF($N32=マイタスク!$U$5,"作業者","")&IF($S32=マイタスク!$U$5,"ピアレビュー","")&IF($X32=マイタスク!$U$5,"SVレビュー","") | AF32: =VALUE(RIGHT($E32,4)) -> 137 | AG32: e
B33: 21 | C33: P3999 | D33: テスト運用サービス・データ計測不可(共通) | E33: P3999-1523 | F33: _HR_安全衛生委員会データ作成【横田さん】 | G33: 生麦X | H33: デリバリ完了 | I33: =$Q33 -> 0 | K33: P3999-1523-01 | L33: HR_安全衛生委員会データ作成【横田さん】 | M33: 集計完了 | N33: shinji.yokota | O33: 45861 | X33: shingo.a.maeda | Y33: 45861 | Z33: 45861 | AE33: =IF($N33=マイタスク!$U$5,"作業者","")&IF($S33=マイタスク!$U$5,"ピアレビュー","")&IF($X33=マイタスク!$U$5,"SVレビュー","") | AF33: =VALUE(RIGHT($E33,4)) -> 1523 | AG33: e
B34: 22 | C34: P3999 | D34: テスト運用サービス・データ計測不可(共通) | E34: P3999-1742 | F34: 【〆野さん】NトレーニングSupplier | G34: 生麦X | H34: デリバリ完了 | I34: =$Q34 -> 0 | K34: P3999-1742-01 | L34: 【〆野さん】NトレーニングSupplier ① | M34: 集計完了 | N34: kasumi.shimeno | O34: 46000 | S34: takao.hattori | T34: 46000 | X34: keita.anzai | Y34: 46000 | Z34: 46014 | AE34: =IF($N34=マイタスク!$U$5,"作業者","")&IF($S34=マイタスク!$U$5,"ピアレビュー","")&IF($X34=マイタスク!$U$5,"SVレビュー","") | AF34: =VALUE(RIGHT($E34,4)) -> 1742 | AG34: e
B35: 23 | C35: P3999 | D35: テスト運用サービス・データ計測不可(共通) | E35: P3999-1742 | F35: 【〆野さん】NトレーニングSupplier | G35: 生麦X | H35: デリバリ完了 | I35: =$Q35 -> 0 | K35: P3999-1742-02 | L35: 【〆野さん】NトレーニングSupplier ② | M35: 集計完了 | N35: kasumi.shimeno | O35: 46001 | S35: minoru.fujita | T35: 46001 | X35: keita.anzai | Y35: 46001 | Z35: 46001 | AE35: =IF($N35=マイタスク!$U$5,"作業者","")&IF($S35=マイタスク!$U$5,"ピアレビュー","")&IF($X35=マイタスク!$U$5,"SVレビュー","") | AF35: =VALUE(RIGHT($E35,4)) -> 1742 | AG35: e
B36: 24 | C36: P3999 | D36: テスト運用サービス・データ計測不可(共通) | E36: P3999-1742 | F36: 【〆野さん】NトレーニングSupplier | G36: 生麦X | H36: デリバリ完了 | I36: =$Q36 -> 0 | K36: P3999-1742-03 | L36: 【〆野さん】NトレーニングSupplier ③ | M36: 集計完了 | N36: kasumi.shimeno | O36: 46003 | S36: minoru.fujita | T36: 46003 | X36: keita.anzai | Y36: 46003 | Z36: 46017 | AE36: =IF($N36=マイタスク!$U$5,"作業者","")&IF($S36=マイタスク!$U$5,"ピアレビュー","")&IF($X36=マイタスク!$U$5,"SVレビュー","") | AF36: =VALUE(RIGHT($E36,4)) -> 1742 | AG36: e
B37: 25 | C37: P3999 | D37: テスト運用サービス・データ計測不可(共通) | E37: P3999-1757 | F37: 【〆野さん】サーバールームTRG | G37: 生麦X | H37: デリバリ完了 | I37: =$Q37 -> 0 | K37: P3999-1757-01 | L37: 【〆野さん】サーバールームTRG(7月分)【Excel工程】 | M37: 集計完了 | N37: kasumi.shimeno | O37: 46010 | S37: shinra.sakaki | T37: 46010 | X37: takao.hattori | Y37: 46010 | Z37: 46010 | AE37: =IF($N37=マイタスク!$U$5,"作業者","")&IF($S37=マイタスク!$U$5,"ピアレビュー","")&IF($X37=マイタスク!$U$5,"SVレビュー","") | AF37: =VALUE(RIGHT($E37,4)) -> 1757 | AG37: e
B38: 26 | C38: P3999 | D38: テスト運用サービス・データ計測不可(共通) | E38: P3999-1757 | F38: 【〆野さん】サーバールームTRG | G38: 生麦X | H38: デリバリ完了 | I38: =$Q38 -> 0 | K38: P3999-1757-02 | L38: 【〆野さん】サーバールームTRG(7月分)【メール工程】 | M38: 集計完了 | N38: kasumi.shimeno | O38: 46010 | S38: shinra.sakaki | T38: 46010 | X38: takao.hattori | Y38: 46010 | Z38: 46010 | AE38: =IF($N38=マイタスク!$U$5,"作業者","")&IF($S38=マイタスク!$U$5,"ピアレビュー","")&IF($X38=マイタスク!$U$5,"SVレビュー","") | AF38: =VALUE(RIGHT($E38,4)) -> 1757 | AG38: e
B39: 27 | C39: P3999 | D39: テスト運用サービス・データ計測不可(共通) | E39: P3999-1766 | F39: 【〆野さん】サーバールームTRG 8月分 | G39: 生麦X | H39: デリバリ完了 | I39: =$Q39 -> 0 | K39: P3999-1766-01 | L39: 【〆野さん】サーバールームTRG 8月分 Excel作成工程 | M39: 集計完了 | N39: kasumi.shimeno | O39: 46013 | S39: shinra.sakaki | T39: 46013 | X39: takao.hattori | Y39: 46013 | Z39: 46017 | AE39: =IF($N39=マイタスク!$U$5,"作業者","")&IF($S39=マイタスク!$U$5,"ピアレビュー","")&IF($X39=マイタスク!$U$5,"SVレビュー","") | AF39: =VALUE(RIGHT($E39,4)) -> 1766 | AG39: e
B40: 28 | C40: P3999 | D40: テスト運用サービス・データ計測不可(共通) | E40: P3999-1766 | F40: 【〆野さん】サーバールームTRG 8月分 | G40: 生麦X | H40: デリバリ完了 | I40: =$Q40 -> 0 | K40: P3999-1766-02 | L40: 【〆野さん】サーバールームTRG 8月分 メール作成工程 | M40: 集計完了 | N40: kasumi.shimeno | O40: 46013 | S40: shinra.sakaki | T40: 46013 | X40: takao.hattori | Y40: 46013 | Z40: 46017 | AE40: =IF($N40=マイタスク!$U$5,"作業者","")&IF($S40=マイタスク!$U$5,"ピアレビュー","")&IF($X40=マイタスク!$U$5,"SVレビュー","") | AF40: =VALUE(RIGHT($E40,4)) -> 1766 | AG40: e
B41: 29 | C41: P3999 | D41: テスト運用サービス・データ計測不可(共通) | E41: P3999-1542 | F41: 【〇〇さん】HR_myTIM（Google）Excelデータ作成 | G41: 生麦X | H41: デリバリ完了 | I41: =$Q41 -> 0 | K41: P3999-1542-01 | L41: 【〇〇さん】HR_myTIM（Google）Excel①工程 | M41: 集計完了 | N41: takao.hattori | O41: 45868 | X41: shingo.a.maeda | Y41: 45868 | Z41: 45868 | AE41: =IF($N41=マイタスク!$U$5,"作業者","")&IF($S41=マイタスク!$U$5,"ピアレビュー","")&IF($X41=マイタスク!$U$5,"SVレビュー","") | AF41: =VALUE(RIGHT($E41,4)) -> 1542 | AG41: e
B42: 30 | C42: P3999 | D42: テスト運用サービス・データ計測不可(共通) | E42: P3999-1542 | F42: 【〇〇さん】HR_myTIM（Google）Excelデータ作成 | G42: 生麦X | H42: デリバリ完了 | I42: =$Q42 -> 0 | K42: P3999-1542-02 | L42: 【〇〇さん】HR_myTIM（Google）Excel②工程 | M42: 集計完了 | N42: takao.hattori | O42: 45868 | X42: shingo.a.maeda | Y42: 45868 | Z42: 45868 | AE42: =IF($N42=マイタスク!$U$5,"作業者","")&IF($S42=マイタスク!$U$5,"ピアレビュー","")&IF($X42=マイタスク!$U$5,"SVレビュー","") | AF42: =VALUE(RIGHT($E42,4)) -> 1542 | AG42: e
B43: 31 | C43: P3998 | D43: テスト運用サービス(共通) | E43: P3998-0048 | F43: 【3週目】テスト案件_PRD_中計・決算発表チェック&レポート作成(優先50社） | G43: 生麦X | H43: デリバリ完了 | I43: =$Q43 -> 0 | K43: P3998-0048-01 | L43: 【3週目】テスト案件_PRD_中計・決算発表チェック&レポート作成(優先50社） | M43: 集計完了 | N43: takumi.kurematsu | O43: 45454 | S43: takashi.muramatsu | T43: 45457 | X43: kazuma.motoyama | Y43: 45457 | Z43: 45457 | AE43: =IF($N43=マイタスク!$U$5,"作業者","")&IF($S43=マイタスク!$U$5,"ピアレビュー","")&IF($X43=マイタスク!$U$5,"SVレビュー","") | AF43: =VALUE(RIGHT($E43,4)) -> 48 | AG43: e
B44: 32 | C44: P1000 | D44: 共通(SN) | E44: P1000-0101 | F44: 【A0003】IC-Energy_石油3社のプレスリリース_日経News情報 マニュアル修正 | G44: 生麦X | H44: デリバリ完了 | I44: =$Q44 -> 0 | K44: P1000-0101-01 | L44: 【A0003】IC-Energy_石油3社のプレスリリース_日経News情報 マニュアル修正 | M44: SVレビュー | N44: ayumi.wada | O44: 44890.375 | S44: takuma.fukazawa | T44: 44893.375 | X44: takashi.muramatsu | Y44: 44893.375 | Z44: 44895.375 | AE44: =IF($N44=マイタスク!$U$5,"作業者","")&IF($S44=マイタスク!$U$5,"ピアレビュー","")&IF($X44=マイタスク!$U$5,"SVレビュー","") | AF44: =VALUE(RIGHT($E44,4)) -> 101 | AG44: e
B45: 33 | C45: P1000 | D45: 共通(SN) | E45: P1000-0192 | F45: 【A0065】Procurement_在宅勤務サポートプログラム メールテンプレート追加 | G45: 生麦X | H45: デリバリ完了 | I45: =$Q45 -> 0 | K45: P1000-0192-01 | L45: 【A1065】Procurement_在宅勤務サポートプログラム メールテンプレート追記 | M45: 集計完了 | N45: ayumi.wada | O45: 45075.375 | S45: kazuma.motoyama | T45: 45075.375 | X45: takashi.muramatsu | Y45: 45075.375 | Z45: 45075.375 | AE45: =IF($N45=マイタスク!$U$5,"作業者","")&IF($S45=マイタスク!$U$5,"ピアレビュー","")&IF($X45=マイタスク!$U$5,"SVレビュー","") | AF45: =VALUE(RIGHT($E45,4)) -> 192 | AG45: e
B46: 34 | C46: P1000 | D46: 共通(SN) | E46: P1000-0270 | F46: 【A1025】PRD_人事異動・組織改編情報チェック(自動化)マニュアル_レビューチェックシート修正 | G46: 生麦X | H46: デリバリ完了 | I46: =$Q46 -> 0 | K46: P1000-0270-01 | L46: 【A1025】PRD_人事異動・組織改編情報チェック(自動化)マニュアル_レビューチェックシート修正 | M46: 集計完了 | N46: ayumi.wada | O46: 45174.375 | S46: kazuma.motoyama | T46: 45174.375 | X46: shigeki.ohtake | Y46: 45174.375 | Z46: 45184.375 | AE46: =IF($N46=マイタスク!$U$5,"作業者","")&IF($S46=マイタスク!$U$5,"ピアレビュー","")&IF($X46=マイタスク!$U$5,"SVレビュー","") | AF46: =VALUE(RIGHT($E46,4)) -> 270 | AG46: e
B47: 35 | C47: P1000 | D47: 共通(SN) | E47: P1000-0207 | F47: 【A1025】PRD_人事異動・組織改編情報チェック(自動化)マニュアル修正 | G47: 生麦X | H47: デリバリ完了 | I47: =$Q47 -> 0 | K47: P1000-0207-01 | L47: 【A1025】PRD_人事異動・組織改編情報チェック(自動化)マニュアル修正 | M47: 集計完了 | N47: takashi.muramatsu | O47: 45082.375 | X47: shigeki.ohtake | Y47: 45086.375 | Z47: 45086.375 | AE47: =IF($N47=マイタスク!$U$5,"作業者","")&IF($S47=マイタスク!$U$5,"ピアレビュー","")&IF($X47=マイタスク!$U$5,"SVレビュー","") | AF47: =VALUE(RIGHT($E47,4)) -> 207 | AG47: e
B48: 36 | C48: P1000 | D48: 共通(SN) | E48: P1000-0182 | F48: 【A1025】PRD_人事異動・組織改編情報チェック(自動化)マニュアル精査 | G48: 生麦X | H48: デリバリ完了 | I48: =$Q48 -> 0 | K48: P1000-0182-01 | L48: 【A1025】PRD_人事異動・組織改編情報チェック(自動化)マニュアル精査 | M48: 集計完了 | N48: shinsuke.eto | O48: 45040.375 | S48: ayumi.wada | T48: 45058.375 | X48: takashi.muramatsu | Y48: 45058.375 | Z48: 45058.375 | AE48: =IF($N48=マイタスク!$U$5,"作業者","")&IF($S48=マイタスク!$U$5,"ピアレビュー","")&IF($X48=マイタスク!$U$5,"SVレビュー","") | AF48: =VALUE(RIGHT($E48,4)) -> 182 | AG48: e
B49: 37 | C49: P1999 | D49: テスト運用サービス(SN) | E49: P1999-0084 | F49: 【A1025】人事異動マニュアル修正 | G49: 生麦X | H49: デリバリ完了 | I49: =$Q49 -> 0 | K49: P1999-0084-01 | L49: 【A1025】人事異動マニュアル修正 | M49: 集計完了 | N49: shingo.a.maeda | O49: 45379 | X49: ayumi.wada | Y49: 45379 | Z49: 45385 | AE49: =IF($N49=マイタスク!$U$5,"作業者","")&IF($S49=マイタスク!$U$5,"ピアレビュー","")&IF($X49=マイタスク!$U$5,"SVレビュー","") | AF49: =VALUE(RIGHT($E49,4)) -> 84 | AG49: e
B50: 38 | C50: P1000 | D50: 共通(SN) | E50: P1000-0385 | F50: 【A1025】人事異動マニュアル更新 | G50: 生麦X | H50: デリバリ完了 | I50: =$Q50 -> 0 | K50: P1000-0385-01 | L50: 【A1025】人事異動マニュアル更新 | M50: 集計完了 | N50: shingo.a.maeda | O50: 45387 | S50: ayumi.wada | T50: 45387 | X50: shigeki.ohtake | Y50: 45387 | Z50: 45387 | AE50: =IF($N50=マイタスク!$U$5,"作業者","")&IF($S50=マイタスク!$U$5,"ピアレビュー","")&IF($X50=マイタスク!$U$5,"SVレビュー","") | AF50: =VALUE(RIGHT($E50,4)) -> 385 | AG50: e
B51: 39 | C51: P1000 | D51: 共通(SN) | E51: P1000-0191 | F51: 【A1031】I&D_Women's stories記事配信 マニュアル修正 | G51: 生麦X | H51: デリバリ完了 | I51: =$Q51 -> 0 | K51: P1000-0191-01 | L51: 【A1031】I&D_Women's stories記事配信 マニュアル修正 | M51: 集計完了 | N51: yuichi.kimura | O51: 45070.375 | S51: riamu.daikusu | T51: 45071.375 | X51: ryota.nozawa | Y51: 45077.375 | Z51: 45077.375 | AE51: =IF($N51=マイタスク!$U$5,"作業者","")&IF($S51=マイタスク!$U$5,"ピアレビュー","")&IF($X51=マイタスク!$U$5,"SVレビュー","") | AF51: =VALUE(RIGHT($E51,4)) -> 191 | AG51: e
B52: 40 | C52: P1000 | D52: 共通(SN) | E52: P1000-0276 | F52: 【A1046】CMT_クライアントのメディアリリース情報確認_マニュアル修正 | G52: 生麦X | H52: デリバリ完了 | I52: =$Q52 -> 0 | K52: P1000-0276-01 | L52: 【A1046】CMT_クライアントのメディアリリース情報確認_マニュアル修正 | M52: 集計完了 | N52: ayumi.wada | O52: 45180.375 | S52: takashi.muramatsu | T52: 45180.375 | X52: shigeki.ohtake | Y52: 45180.375 | Z52: 45184.375 | AE52: =IF($N52=マイタスク!$U$5,"作業者","")&IF($S52=マイタスク!$U$5,"ピアレビュー","")&IF($X52=マイタスク!$U$5,"SVレビュー","") | AF52: =VALUE(RIGHT($E52,4)) -> 276 | AG52: e
B53: 41 | C53: P1000 | D53: 共通(SN) | E53: P1000-0180 | F53: 【A1054】Security_脆弱性情報マニュアル・納品テンプレート更新 | G53: 生麦X | H53: デリバリ完了 | I53: =$Q53 -> 0 | K53: P1000-0180-01 | L53: 【A1054】Security_脆弱性情報マニュアル・納品テンプレート更新 | M53: 集計完了 | N53: takuma.fukazawa | O53: 45033.375 | X53: takashi.muramatsu | Y53: 45033.375 | Z53: 45035.375 | AE53: =IF($N53=マイタスク!$U$5,"作業者","")&IF($S53=マイタスク!$U$5,"ピアレビュー","")&IF($X53=マイタスク!$U$5,"SVレビュー","") | AF53: =VALUE(RIGHT($E53,4)) -> 180 | AG53: e
B54: 42 | C54: P1999 | D54: テスト運用サービス(SN) | E54: P1999-0027 | F54: 【A1065】在宅勤務サポートプログラムテスト運用メール送付① | G54: 生麦X | H54: デリバリ完了 | I54: =$Q54 -> 0 | K54: P1999-0027-01 | L54: 【A1065】在宅勤務サポートプログラムテスト運用メール送付① | M54: 集計完了 | N54: takuma.fukazawa | O54: 44972.375 | S54: yuichi.kimura | T54: 44973.375 | X54: ayumi.wada | Y54: 44974.375 | Z54: 44974.375 | AE54: =IF($N54=マイタスク!$U$5,"作業者","")&IF($S54=マイタスク!$U$5,"ピアレビュー","")&IF($X54=マイタスク!$U$5,"SVレビュー","") | AF54: =VALUE(RIGHT($E54,4)) -> 27 | AG54: e
B55: 43 | C55: P1999 | D55: テスト運用サービス(SN) | E55: P1999-0028 | F55: 【A1065】在宅勤務サポートプログラムテスト運用メール送付② | G55: 生麦X | H55: デリバリ完了 | I55: =$Q55 -> 0 | K55: P1999-0028-01 | L55: 【A1065】在宅勤務サポートプログラムテスト運用メール送付② | M55: 集計完了 | N55: yumi.terui | O55: 44972.375 | S55: koji.fukui | T55: 44973.375 | X55: ayumi.wada | Y55: 44974.375 | Z55: 44974.375 | AE55: =IF($N55=マイタスク!$U$5,"作業者","")&IF($S55=マイタスク!$U$5,"ピアレビュー","")&IF($X55=マイタスク!$U$5,"SVレビュー","") | AF55: =VALUE(RIGHT($E55,4)) -> 28 | AG55: e
B56: 44 | C56: P1999 | D56: テスト運用サービス(SN) | E56: P1999-0029 | F56: 【A1065】在宅勤務サポートプログラムテスト運用メール送付② | G56: 生麦X | H56: デリバリ完了 | I56: =$Q56 -> 0 | K56: P1999-0029-01 | L56: 【A1065】在宅勤務サポートプログラムテスト運用メール送付③ | M56: 集計完了 | N56: yuichi.kimura | O56: 44972.375 | S56: takuma.fukazawa | T56: 44973.375 | X56: takashi.muramatsu | Y56: 44974.375 | Z56: 44974.375 | AE56: =IF($N56=マイタスク!$U$5,"作業者","")&IF($S56=マイタスク!$U$5,"ピアレビュー","")&IF($X56=マイタスク!$U$5,"SVレビュー","") | AF56: =VALUE(RIGHT($E56,4)) -> 29 | AG56: e
B57: 45 | C57: P1999 | D57: テスト運用サービス(SN) | E57: P1999-0030 | F57: 【A1065】在宅勤務サポートプログラムテスト運用メール送付④ | G57: 生麦X | H57: デリバリ完了 | I57: =$Q57 -> 0 | K57: P1999-0030-01 | L57: 【A1065】在宅勤務サポートプログラムテスト運用メール送付④ | M57: 集計完了 | N57: koji.fukui | O57: 44972.375 | S57: yumi.terui | T57: 44973.375 | X57: takashi.muramatsu | Y57: 44974.375 | Z57: 44974.375 | AE57: =IF($N57=マイタスク!$U$5,"作業者","")&IF($S57=マイタスク!$U$5,"ピアレビュー","")&IF($X57=マイタスク!$U$5,"SVレビュー","") | AF57: =VALUE(RIGHT($E57,4)) -> 30 | AG57: e
B58: 46 | C58: P1999 | D58: テスト運用サービス(SN) | E58: P1999-0031 | F58: 【A1065】在宅勤務サポートプログラムテスト運用メール送付④ | G58: 生麦X | H58: デリバリ完了 | I58: =$Q58 -> 0 | K58: P1999-0031-01 | L58: 【A1065】在宅勤務サポートプログラムテスト運用メール送付⑤ | M58: 集計完了 | N58: kazuma.motoyama | O58: 44972.375 | S58: rei.hasegawa | T58: 44973.375 | X58: ayumi.wada | Y58: 44974.375 | Z58: 44974.375 | AE58: =IF($N58=マイタスク!$U$5,"作業者","")&IF($S58=マイタスク!$U$5,"ピアレビュー","")&IF($X58=マイタスク!$U$5,"SVレビュー","") | AF58: =VALUE(RIGHT($E58,4)) -> 31 | AG58: e
B59: 47 | C59: P1999 | D59: テスト運用サービス(SN) | E59: P1999-0032 | F59: 【A1065】在宅勤務サポートプログラムテスト運用メール送付⑥ | G59: 生麦X | H59: デリバリ完了 | I59: =$Q59 -> 0 | K59: P1999-0032-01 | L59: 【A1065】在宅勤務サポートプログラムテスト運用メール送付⑥ | M59: 集計完了 | N59: rei.hasegawa | O59: 44972.375 | S59: kazuma.motoyama | T59: 44973.375 | X59: takashi.muramatsu | Y59: 44974.375 | Z59: 44974.375 | AE59: =IF($N59=マイタスク!$U$5,"作業者","")&IF($S59=マイタスク!$U$5,"ピアレビュー","")&IF($X59=マイタスク!$U$5,"SVレビュー","") | AF59: =VALUE(RIGHT($E59,4)) -> 32 | AG59: e
B60: 48 | C60: P1999 | D60: テスト運用サービス(SN) | E60: P1999-0033 | F60: 【A1065】在宅勤務サポートプログラムテスト運用管理担当① | G60: 生麦X | H60: デリバリ完了 | I60: =$Q60 -> 0 | K60: P1999-0033-01 | L60: 【A1065】在宅勤務サポートプログラムテスト運用管理担当① | M60: 集計完了 | N60: kazuma.motoyama | O60: 44971.375 | S60: ayumi.wada | T60: 44972.375 | X60: takashi.muramatsu | Y60: 44973.375 | Z60: 44974.375 | AE60: =IF($N60=マイタスク!$U$5,"作業者","")&IF($S60=マイタスク!$U$5,"ピアレビュー","")&IF($X60=マイタスク!$U$5,"SVレビュー","") | AF60: =VALUE(RIGHT($E60,4)) -> 33 | AG60: e
B61: 49 | C61: P1999 | D61: テスト運用サービス(SN) | E61: P1999-0034 | F61: 【A1065】在宅勤務サポートプログラムテスト運用管理担当② | G61: 生麦X | H61: デリバリ完了 | I61: =$Q61 -> 0 | K61: P1999-0034-01 | L61: 【A1065】在宅勤務サポートプログラムテスト運用管理担当② | M61: 集計完了 | N61: rei.hasegawa | O61: 44971.375 | S61: ayumi.wada | T61: 44972.375 | X61: takashi.muramatsu | Y61: 44973.375 | Z61: 44974.375 | AE61: =IF($N61=マイタスク!$U$5,"作業者","")&IF($S61=マイタスク!$U$5,"ピアレビュー","")&IF($X61=マイタスク!$U$5,"SVレビュー","") | AF61: =VALUE(RIGHT($E61,4)) -> 34 | AG61: e
B62: 50 | C62: P1999 | D62: テスト運用サービス(SN) | E62: P1999-0015 | F62: 【A1072】Technology_アクセンチュア健保_chatbot運用保守12/2/5① | G62: 生麦X | H62: デリバリ完了 | I62: =$Q62 -> 0 | K62: P1999-0015-01 | L62: 【A1072】Technology_アクセンチュア健保_chatbot運用保守12/2/5① | M62: 集計完了 | N62: ayumi.wada | O62: 44897.375 | S62: rei.hasegawa | T62: 44900.375 | X62: takashi.muramatsu | Y62: 44900.375 | Z62: 44900.375 | AE62: =IF($N62=マイタスク!$U$5,"作業者","")&IF($S62=マイタスク!$U$5,"ピアレビュー","")&IF($X62=マイタスク!$U$5,"SVレビュー","") | AF62: =VALUE(RIGHT($E62,4)) -> 15 | AG62: e
B63: 51 | C63: P1999 | D63: テスト運用サービス(SN) | E63: P1999-0016 | F63: 【A1072】Technology_アクセンチュア健保_chatbot運用保守12/2/5① | G63: 生麦X | H63: デリバリ完了 | I63: =$Q63 -> 0 | K63: P1999-0016-01 | L63: 【A1072】Technology_アクセンチュア健保_chatbot運用保守12/2/5② | M63: 集計完了 | N63: yumi.terui | O63: 44897.375 | S63: takuma.fukazawa | T63: 44900.375 | X63: takashi.muramatsu | Y63: 44900.375 | Z63: 44900.375 | AE63: =IF($N63=マイタスク!$U$5,"作業者","")&IF($S63=マイタスク!$U$5,"ピアレビュー","")&IF($X63=マイタスク!$U$5,"SVレビュー","") | AF63: =VALUE(RIGHT($E63,4)) -> 16 | AG63: e
B64: 52 | C64: P1999 | D64: テスト運用サービス(SN) | E64: P1999-0019 | F64: 【A1072】Technology_アクセンチュア健保_chatbot運用保守12/2/5①(Aチーム） | G64: 生麦X | H64: デリバリ完了 | I64: =$Q64 -> 0 | K64: P1999-0019-01 | L64: 【A1072】Technology_アクセンチュア健保_chatbot運用保守12/2/5①(Aチーム） | M64: 集計完了 | N64: yuichi.kimura | O64: 44897.375 | S64: riamu.daikusu | T64: 44897.375 | X64: ryota.nozawa | Y64: 44897.375 | Z64: 44900.375 | AE64: =IF($N64=マイタスク!$U$5,"作業者","")&IF($S64=マイタスク!$U$5,"ピアレビュー","")&IF($X64=マイタスク!$U$5,"SVレビュー","") | AF64: =VALUE(RIGHT($E64,4)) -> 19 | AG64: e
B65: 53 | C65: P1999 | D65: テスト運用サービス(SN) | E65: P1999-0019 | F65: 【A1072】Technology_アクセンチュア健保_chatbot運用保守12/2/5①(Aチーム） | G65: 生麦X | H65: デリバリ完了 | I65: =$Q65 -> 0 | K65: P1999-0019-02 | L65: 【A1072】Technology_アクセンチュア健保_chatbot運用保守12/8/12①(Aチーム） | M65: 集計完了 | N65: yuichi.kimura | O65: 44904.375 | S65: riamu.daikusu | T65: 44904.375 | X65: ryota.nozawa | Y65: 44904.375 | Z65: 44907.375 | AE65: =IF($N65=マイタスク!$U$5,"作業者","")&IF($S65=マイタスク!$U$5,"ピアレビュー","")&IF($X65=マイタスク!$U$5,"SVレビュー","") | AF65: =VALUE(RIGHT($E65,4)) -> 19 | AG65: e
... B77: 65 | C77: P1999 | D77: テスト運用サービス(SN) | E77: P1999-0026 | F77: 【A1072】Technology_アクセンチュア健保_chatbot運用保守12/9/12④ | G77: 生麦X | H77: デリバリ完了 | I77: =$Q77 -> 0 | K77: P1999-0026-01 | L77: 【A1072】Technology_アクセンチュア健保_chatbot運用保守12/9/12④ | M77: 集計完了 | N77: takuma.fukazawa | O77: 44904.375 | S77: ayumi.wada | T77: 44907.375 | X77: takashi.muramatsu | Y77: 44907.375 | Z77: 44907.375 | AE77: =IF($N77=マイタスク!$U$5,"作業者","")&IF($S77=マイタスク!$U$5,"ピアレビュー","")&IF($X77=マイタスク!$U$5,"SVレビュー","") | AF77: =VALUE(RIGHT($E77,4)) -> 26 | AG77: e
B78: 66 | C78: P1000 | D78: 共通(SN) | E78: P1000-0042 | F78: 【A1073】S&C_購買レポートリスト更新_マニュアル更新 | G78: 生麦X | H78: デリバリ完了 | I78: =$Q78 -> 0 | K78: P1000-0042-01 | L78: 【A1073】S&C_購買レポートリスト更新_マニュアル更新 | M78: 内部レビュー完了 | N78: kotaro.honma | O78: 44826.375 | S78: kotaro.honma | T78: 44840.375 | Y78: 44840.375 | Z78: 44841.375 | AE78: =IF($N78=マイタスク!$U$5,"作業者","")&IF($S78=マイタスク!$U$5,"ピアレビュー","")&IF($X78=マイタスク!$U$5,"SVレビュー","") | AF78: =VALUE(RIGHT($E78,4)) -> 42 | AG78: e
B79: 67 | C79: P3999 | D79: テスト運用サービス(共通) | E79: P3999-0227 | F79: 【IC-Energy】Nグループ練習（谷口さん） | G79: 生麦X | H79: デリバリ完了 | I79: =$Q79 -> 0 | K79: P3999-0227-01 | L79: 【IC-Energy】Nグループ練習（谷口さん） | M79: 集計完了 | N79: shunsuke.taniguchi | O79: 45505 | S79: eri.wakabayashi | T79: 45505 | X79: takashi.muramatsu | Y79: 45505 | Z79: 45505 | AE79: =IF($N79=マイタスク!$U$5,"作業者","")&IF($S79=マイタスク!$U$5,"ピアレビュー","")&IF($X79=マイタスク!$U$5,"SVレビュー","") | AF79: =VALUE(RIGHT($E79,4)) -> 227 | AG79: e
B80: 68 | C80: P3999 | D80: テスト運用サービス(共通) | E80: P3999-0226 | F80: 【IC-Energy】Nグループ練習（谷川さん） | G80: 生麦X | H80: デリバリ完了 | I80: =$Q80 -> 0 | K80: P3999-0226-01 | L80: 【IC-Energy】Nグループ練習（谷川さん） | M80: 集計完了 | N80: hironori.tanikawa | O80: 45505 | S80: eri.wakabayashi | T80: 45505 | X80: takashi.muramatsu | Y80: 45505 | Z80: 45505 | AE80: =IF($N80=マイタスク!$U$5,"作業者","")&IF($S80=マイタスク!$U$5,"ピアレビュー","")&IF($X80=マイタスク!$U$5,"SVレビュー","") | AF80: =VALUE(RIGHT($E80,4)) -> 226 | AG80: e
B81: 69 | C81: P3999 | D81: テスト運用サービス(共通) | E81: P3999-0228 | F81: 【IC-Energy】Nグループ練習8/5週（谷口さん） | G81: 生麦X | H81: デリバリ完了 | I81: =$Q81 -> 0 | K81: P3999-0228-01 | L81: 【IC-Energy】Nグループ練習8/5週（谷口さん） | M81: 集計完了 | N81: shunsuke.taniguchi | O81: 45512 | S81: eri.wakabayashi | T81: 45512 | X81: takashi.muramatsu | Y81: 45512 | Z81: 45512 | AE81: =IF($N81=マイタスク!$U$5,"作業者","")&IF($S81=マイタスク!$U$5,"ピアレビュー","")&IF($X81=マイタスク!$U$5,"SVレビュー","") | AF81: =VALUE(RIGHT($E81,4)) -> 228 | AG81: e
B82: 70 | C82: P3999 | D82: テスト運用サービス(共通) | E82: P3999-0229 | F82: 【IC-Energy】Nグループ練習8/5週（谷川さん） | G82: 生麦X | H82: デリバリ完了 | I82: =$Q82 -> 0 | K82: P3999-0229-01 | L82: 【IC-Energy】Nグループ練習8/5週（谷川さん） | M82: 集計完了 | N82: hironori.tanikawa | O82: 45512 | S82: eri.wakabayashi | T82: 45512 | X82: takashi.muramatsu | Y82: 45512 | Z82: 45512 | AE82: =IF($N82=マイタスク!$U$5,"作業者","")&IF($S82=マイタスク!$U$5,"ピアレビュー","")&IF($X82=マイタスク!$U$5,"SVレビュー","") | AF82: =VALUE(RIGHT($E82,4)) -> 229 | AG82: e
B83: 71 | C83: P3999 | D83: テスト運用サービス・データ計測不可(共通) | E83: P3999-1407 | F83: 【myTIM】HR_myTIM/OTデータ作成(Google) 6/9週 | G83: 生麦X | H83: デリバリ完了 | I83: =$Q83 -> 0 | K83: P3999-1407-01 | L83: 【myTIM】HR_myTIM/OTデータ作成(Google) 6/9週 Excel作業 | M83: 集計完了 | N83: riamu.daikusu | O83: 45817 | S83: shinra.sakaki | T83: 45817 | X83: ryota.nozawa | Y83: 45821 | Z83: 45821 | AE83: =IF($N83=マイタスク!$U$5,"作業者","")&IF($S83=マイタスク!$U$5,"ピアレビュー","")&IF($X83=マイタスク!$U$5,"SVレビュー","") | AF83: =VALUE(RIGHT($E83,4)) -> 1407 | AG83: e
B84: 72 | C84: P3999 | D84: テスト運用サービス・データ計測不可(共通) | E84: P3999-1407 | F84: 【myTIM】HR_myTIM/OTデータ作成(Google) 6/9週 | G84: 生麦X | H84: デリバリ完了 | I84: =$Q84 -> 0 | K84: P3999-1407-02 | L84: 【myTIM】HR_myTIM/OTデータ作成(Google) 6/9週 メール作業 | M84: 集計完了 | N84: riamu.daikusu | O84: 45817 | S84: shinra.sakaki | T84: 45817 | X84: ryota.nozawa | Y84: 45821 | Z84: 45821 | AE84: =IF($N84=マイタスク!$U$5,"作業者","")&IF($S84=マイタスク!$U$5,"ピアレビュー","")&IF($X84=マイタスク!$U$5,"SVレビュー","") | AF84: =VALUE(RIGHT($E84,4)) -> 1407 | AG84: e
B85: 73 | C85: A0098 | D85: HR_myTIM/OTデータ作成(Google) | E85: A0098-0022 | F85: 【myTIM】HR_myTIM/OTデータ作成(Google) 10/13週 | G85: 生麦X | H85: デリバリ完了 | I85: =$Q85 -> 0 | K85: A0098-0022-01 | L85: 【myTIM】HR_myTIM/OTデータ作成(Google) 10/13週 Excel作業 | M85: 集計完了 | N85: shinsuke.eto | O85: 45944 | S85: naoto.maejima | T85: 45947 | X85: ryusei.inaba | Y85: 45947 | Z85: 45947 | AE85: =IF($N85=マイタスク!$U$5,"作業者","")&IF($S85=マイタスク!$U$5,"ピアレビュー","")&IF($X85=マイタスク!$U$5,"SVレビュー","") | AF85: =VALUE(RIGHT($E85,4)) -> 22 | AG85: e
B86: 74 | C86: A0098 | D86: HR_myTIM/OTデータ作成(Google) | E86: A0098-0022 | F86: 【myTIM】HR_myTIM/OTデータ作成(Google) 10/13週 | G86: 生麦X | H86: デリバリ完了 | I86: =$Q86 -> 0 | K86: A0098-0022-02 | L86: 【myTIM】HR_myTIM/OTデータ作成(Google) 10/13週 メール作業 | M86: 集計完了 | N86: shinsuke.eto | O86: 45944 | S86: naoto.maejima | T86: 45947 | X86: ryusei.inaba | Y86: 45947 | Z86: 45947 | AE86: =IF($N86=マイタスク!$U$5,"作業者","")&IF($S86=マイタスク!$U$5,"ピアレビュー","")&IF($X86=マイタスク!$U$5,"SVレビュー","") | AF86: =VALUE(RIGHT($E86,4)) -> 22 | AG86: e
B87: 75 | C87: A0098 | D87: HR_myTIM/OTデータ作成(Google) | E87: A0098-0023 | F87: 【myTIM】HR_myTIM/OTデータ作成(Google) 10/20週 | G87: 生麦X | H87: デリバリ完了 | I87: =$Q87 -> 0 | K87: A0098-0023-01 | L87: 【myTIM】HR_myTIM/OTデータ作成(Google) 10/20週 Excel作業 | M87: 集計完了 | N87: naoto.maejima | O87: 45950 | S87: rintaro.watanabe | T87: 45954 | X87: ryusei.inaba | Y87: 45954 | Z87: 45954 | AE87: =IF($N87=マイタスク!$U$5,"作業者","")&IF($S87=マイタスク!$U$5,"ピアレビュー","")&IF($X87=マイタスク!$U$5,"SVレビュー","") | AF87: =VALUE(RIGHT($E87,4)) -> 23 | AG87: e
B88: 76 | C88: A0098 | D88: HR_myTIM/OTデータ作成(Google) | E88: A0098-0023 | F88: 【myTIM】HR_myTIM/OTデータ作成(Google) 10/20週 | G88: 生麦X | H88: デリバリ完了 | I88: =$Q88 -> 0 | K88: A0098-0023-02 | L88: 【myTIM】HR_myTIM/OTデータ作成(Google) 10/20週 メール作業 | M88: 集計完了 | N88: naoto.maejima | O88: 45950 | S88: rintaro.watanabe | T88: 45954 | X88: ryusei.inaba | Y88: 45954 | Z88: 45954 | AE88: =IF($N88=マイタスク!$U$5,"作業者","")&IF($S88=マイタスク!$U$5,"ピアレビュー","")&IF($X88=マイタスク!$U$5,"SVレビュー","") | AF88: =VALUE(RIGHT($E88,4)) -> 23 | AG88: e
B89: 77 | C89: A0098 | D89: HR_myTIM/OTデータ作成(Google) | E89: A0098-0024 | F89: 【myTIM】HR_myTIM/OTデータ作成(Google) 10/27週 | G89: 生麦X | H89: デリバリ完了 | I89: =$Q89 -> 0 | K89: A0098-0024-01 | L89: 【myTIM】HR_myTIM/OTデータ作成(Google) 10/27週 Excel作業 | M89: 内部レビュー完了 | N89: naoto.maejima | O89: 45957 | S89: shunsuke.taniguchi | T89: 45961 | X89: ryusei.inaba | Y89: 45961 | Z89: 45961 | AE89: =IF($N89=マイタスク!$U$5,"作業者","")&IF($S89=マイタスク!$U$5,"ピアレビュー","")&IF($X89=マイタスク!$U$5,"SVレビュー","") | AF89: =VALUE(RIGHT($E89,4)) -> 24 | AG89: e
B90: 78 | C90: A0098 | D90: HR_myTIM/OTデータ作成(Google) | E90: A0098-0024 | F90: 【myTIM】HR_myTIM/OTデータ作成(Google) 10/27週 | G90: 生麦X | H90: デリバリ完了 | I90: =$Q90 -> 0 | K90: A0098-0024-02 | L90: 【myTIM】HR_myTIM/OTデータ作成(Google) 10/27週 メール作業 | M90: 内部レビュー完了 | N90: naoto.maejima | O90: 45957 | S90: shunsuke.taniguchi | T90: 45961 | X90: ryusei.inaba | Y90: 45961 | Z90: 45961 | AE90: =IF($N90=マイタスク!$U$5,"作業者","")&IF($S90=マイタスク!$U$5,"ピアレビュー","")&IF($X90=マイタスク!$U$5,"SVレビュー","") | AF90: =VALUE(RIGHT($E90,4)) -> 24 | AG90: e
... B118: 106 | C118: A0098 | D118: HR_myTIM/OTデータ作成(Google) | E118: A0098-0006 | F118: 【myTIM】HR_myTIM/OTデータ作成(Google) 7/22週 | G118: 生麦X | H118: デリバリ完了 | I118: =$Q118 -> 0 | K118: A0098-0006-02 | L118: 【myTIM】HR_myTIM/OTデータ作成(Google) 7/22週 メール作業 | M118: 集計完了 | N118: rintaro.watanabe | O118: 45860 | S118: shinsuke.eto | T118: 45860 | X118: ryusei.inaba | Y118: 45863 | Z118: 45863 | AE118: =IF($N118=マイタスク!$U$5,"作業者","")&IF($S118=マイタスク!$U$5,"ピアレビュー","")&IF($X118=マイタスク!$U$5,"SVレビュー","") | AF118: =VALUE(RIGHT($E118,4)) -> 6 | AG118: e
B119: 107 | C119: A0098 | D119: HR_myTIM/OTデータ作成(Google) | E119: A0098-0007 | F119: 【myTIM】HR_myTIM/OTデータ作成(Google) 7/22週 Excel作業 | G119: 生麦X | H119: デリバリ完了 | I119: =$Q119 -> 0 | K119: A0098-0007-01 | L119: 【myTIM】HR_myTIM/OTデータ作成(Google) 7/28週 Excel作業 | M119: 集計完了 | N119: shingo.a.maeda | O119: 45856 | S119: shingo.a.maeda | T119: 45856 | Z119: 45856 | AE119: =IF($N119=マイタスク!$U$5,"作業者","")&IF($S119=マイタスク!$U$5,"ピアレビュー","")&IF($X119=マイタスク!$U$5,"SVレビュー","") | AF119: =VALUE(RIGHT($E119,4)) -> 7 | AG119: e
B120: 108 | C120: A0098 | D120: HR_myTIM/OTデータ作成(Google) | E120: A0098-0008 | F120: 【myTIM】HR_myTIM/OTデータ作成(Google) 7/22週 メール作業 | G120: 生麦X | H120: デリバリ完了 | I120: =$Q120 -> 0 | K120: A0098-0008-01 | L120: 【myTIM】HR_myTIM/OTデータ作成(Google) 8/4週 Excel作業 | M120: 集計完了 | N120: shingo.a.maeda | O120: 45856 | S120: shingo.a.maeda | T120: 45856 | Z120: 45856 | AE120: =IF($N120=マイタスク!$U$5,"作業者","")&IF($S120=マイタスク!$U$5,"ピアレビュー","")&IF($X120=マイタスク!$U$5,"SVレビュー","") | AF120: =VALUE(RIGHT($E120,4)) -> 8 | AG120: e
B121: 109 | C121: A0098 | D121: HR_myTIM/OTデータ作成(Google) | E121: A0098-0009 | F121: 【myTIM】HR_myTIM/OTデータ作成(Google) 7/28週 | G121: 生麦X | H121: デリバリ完了 | I121: =$Q121 -> 0 | K121: A0098-0009-01 | L121: 【myTIM】HR_myTIM/OTデータ作成(Google) 7/28週 Excel工程 | M121: 内部レビュー完了 | N121: shunsuke.taniguchi | O121: 45866 | S121: shinsuke.eto | T121: 45870 | X121: ryusei.inaba | Y121: 45870 | Z121: 45870 | AE121: =IF($N121=マイタスク!$U$5,"作業者","")&IF($S121=マイタスク!$U$5,"ピアレビュー","")&IF($X121=マイタスク!$U$5,"SVレビュー","") | AF121: =VALUE(RIGHT($E121,4)) -> 9 | AG121: e
B122: 110 | C122: A0098 | D122: HR_myTIM/OTデータ作成(Google) | E122: A0098-0009 | F122: 【myTIM】HR_myTIM/OTデータ作成(Google) 7/28週 | G122: 生麦X | H122: デリバリ完了 | I122: =$Q122 -> 0 | K122: A0098-0009-02 | L122: 【myTIM】HR_myTIM/OTデータ作成(Google) 7/28週 メール工程 | M122: 内部レビュー完了 | N122: shunsuke.taniguchi | O122: 45866 | S122: shinsuke.eto | T122: 45870 | X122: ryusei.inaba | Y122: 45870 | Z122: 45870 | AE122: =IF($N122=マイタスク!$U$5,"作業者","")&IF($S122=マイタスク!$U$5,"ピアレビュー","")&IF($X122=マイタスク!$U$5,"SVレビュー","") | AF122: =VALUE(RIGHT($E122,4)) -> 9 | AG122: e
B123: 111 | C123: A0098 | D123: HR_myTIM/OTデータ作成(Google) | E123: A0098-0004 | F123: 【myTIM】HR_myTIM/OTデータ作成(Google) 7/7週 | G123: 生麦X | H123: デリバリ完了 | I123: =$Q123 -> 0 | K123: A0098-0004-01 | L123: 【myTIM】HR_myTIM/OTデータ作成(Google) 7/7週 Excel作業 | M123: 集計完了 | N123: shunsuke.taniguchi | O123: 45845 | S123: riamu.daikusu | T123: 45849 | X123: ryusei.inaba | Y123: 45849 | Z123: 45849 | AE123: =IF($N123=マイタスク!$U$5,"作業者","")&IF($S123=マイタスク!$U$5,"ピアレビュー","")&IF($X123=マイタスク!$U$5,"SVレビュー","") | AF123: =VALUE(RIGHT($E123,4)) -> 4 | AG123: e
B124: 112 | C124: A0098 | D124: HR_myTIM/OTデータ作成(Google) | E124: A0098-0004 | F124: 【myTIM】HR_myTIM/OTデータ作成(Google) 7/7週 | G124: 生麦X | H124: デリバリ完了 | I124: =$Q124 -> 0 | K124: A0098-0004-02 | L124: 【myTIM】HR_myTIM/OTデータ作成(Google) 7/7週 メール作業 | M124: 集計完了 | N124: shunsuke.taniguchi | O124: 45845 | S124: riamu.daikusu | T124: 45849 | X124: ryusei.inaba | Y124: 45849 | Z124: 45849 | AE124: =IF($N124=マイタスク!$U$5,"作業者","")&IF($S124=マイタスク!$U$5,"ピアレビュー","")&IF($X124=マイタスク!$U$5,"SVレビュー","") | AF124: =VALUE(RIGHT($E124,4)) -> 4 | AG124: e
B125: 113 | C125: A0098 | D125: HR_myTIM/OTデータ作成(Google) | E125: A0098-0012 | F125: 【myTIM】HR_myTIM/OTデータ作成(Google) 8/18週 | G125: 生麦X | H125: デリバリ完了 | I125: =$Q125 -> 0 | K125: A0098-0012-01 | L125: 【myTIM】HR_myTIM/OTデータ作成(Google) 8/18週 Excel工程 | M125: 集計完了 | N125: shinra.sakaki | O125: 45887 | S125: rintaro.watanabe | T125: 45891 | X125: ryusei.inaba | Y125: 45891 | Z125: 45891 | AE125: =IF($N125=マイタスク!$U$5,"作業者","")&IF($S125=マイタスク!$U$5,"ピアレビュー","")&IF($X125=マイタスク!$U$5,"SVレビュー","") | AF125: =VALUE(RIGHT($E125,4)) -> 12 | AG125: e
B126: 114 | C126: A0098 | D126: HR_myTIM/OTデータ作成(Google) | E126: A0098-0012 | F126: 【myTIM】HR_myTIM/OTデータ作成(Google) 8/18週 | G126: 生麦X | H126: デリバリ完了 | I126: =$Q126 -> 0 | K126: A0098-0012-02 | L126: 【myTIM】HR_myTIM/OTデータ作成(Google) 8/18週 メール工程 | M126: 集計完了 | N126: shinra.sakaki | O126: 45887 | S126: rintaro.watanabe | T126: 45891 | X126: ryusei.inaba | Y126: 45891 | Z126: 45891 | AE126: =IF($N126=マイタスク!$U$5,"作業者","")&IF($S126=マイタスク!$U$5,"ピアレビュー","")&IF($X126=マイタスク!$U$5,"SVレビュー","") | AF126: =VALUE(RIGHT($E126,4)) -> 12 | AG126: e
B127: 115 | C127: A0098 | D127: HR_myTIM/OTデータ作成(Google) | E127: A0098-0013 | F127: 【myTIM】HR_myTIM/OTデータ作成(Google) 8/18週 | G127: 生麦X | H127: デリバリ完了 | I127: =$Q127 -> 0 | K127: A0098-0013-01 | L127: 【myTIM】HR_myTIM/OTデータ作成(Google) 8/25週 Excel作業 | M127: 集計完了 | N127: riamu.daikusu | O127: 45894 | S127: shinsuke.eto | T127: 45898 | X127: ryusei.inaba | Y127: 45898 | Z127: 45898 | AE127: =IF($N127=マイタスク!$U$5,"作業者","")&IF($S127=マイタスク!$U$5,"ピアレビュー","")&IF($X127=マイタスク!$U$5,"SVレビュー","") | AF127: =VALUE(RIGHT($E127,4)) -> 13 | AG127: e
B128: 116 | C128: A0098 | D128: HR_myTIM/OTデータ作成(Google) | E128: A0098-0013 | F128: 【myTIM】HR_myTIM/OTデータ作成(Google) 8/18週 | G128: 生麦X | H128: デリバリ完了 | I128: =$Q128 -> 0 | K128: A0098-0013-02 | L128: 【myTIM】HR_myTIM/OTデータ作成(Google) 8/25週 メール作業 | M128: 集計完了 | N128: riamu.daikusu | O128: 45894 | S128: shinsuke.eto | T128: 45898 | X128: ryusei.inaba | Y128: 45898 | Z128: 45898 | AE128: =IF($N128=マイタスク!$U$5,"作業者","")&IF($S128=マイタスク!$U$5,"ピアレビュー","")&IF($X128=マイタスク!$U$5,"SVレビュー","") | AF128: =VALUE(RIGHT($E128,4)) -> 13 | AG128: e
B129: 117 | C129: A0098 | D129: HR_myTIM/OTデータ作成(Google) | E129: A0098-0010 | F129: 【myTIM】HR_myTIM/OTデータ作成(Google) 8/4週 | G129: 生麦X | H129: デリバリ完了 | I129: =$Q129 -> 0 | K129: A0098-0010-01 | L129: 【myTIM】HR_myTIM/OTデータ作成(Google) 8/4週 Excel作業 | M129: 集計完了 | N129: rintaro.watanabe | O129: 45873 | S129: shunsuke.taniguchi | T129: 45873 | X129: ryusei.inaba | Y129: 45877 | Z129: 45877 | AE129: =IF($N129=マイタスク!$U$5,"作業者","")&IF($S129=マイタスク!$U$5,"ピアレビュー","")&IF($X129=マイタスク!$U$5,"SVレビュー","") | AF129: =VALUE(RIGHT($E129,4)) -> 10 | AG129: e
B130: 118 | C130: A0098 | D130: HR_myTIM/OTデータ作成(Google) | E130: A0098-0010 | F130: 【myTIM】HR_myTIM/OTデータ作成(Google) 8/4週 | G130: 生麦X | H130: デリバリ完了 | I130: =$Q130 -> 0 | K130: A0098-0010-02 | L130: 【myTIM】HR_myTIM/OTデータ作成(Google) 8/4週 メール作業 | M130: 集計完了 | N130: rintaro.watanabe | O130: 45873 | S130: shunsuke.taniguchi | T130: 45873 | X130: ryusei.inaba | Y130: 45877 | Z130: 45877 | AE130: =IF($N130=マイタスク!$U$5,"作業者","")&IF($S130=マイタスク!$U$5,"ピアレビュー","")&IF($X130=マイタスク!$U$5,"SVレビュー","") | AF130: =VALUE(RIGHT($E130,4)) -> 10 | AG130: e
B131: 119 | C131: A0098 | D131: HR_myTIM/OTデータ作成(Google) | E131: A0098-0017 | F131: 【myTIM】HR_myTIM/OTデータ作成(Google) 9/15週 | G131: 生麦X | H131: デリバリ完了 | I131: =$Q131 -> 0 | K131: A0098-0017-01 | L131: 【myTIM】HR_myTIM/OTデータ作成(Google) 9/15週 Excel作業 | M131: 集計完了 | N131: shinsuke.eto | O131: 45916 | S131: shinra.sakaki | T131: 45919 | X131: ryusei.inaba | Y131: 45919 | Z131: 45919 | AE131: =IF($N131=マイタスク!$U$5,"作業者","")&IF($S131=マイタスク!$U$5,"ピアレビュー","")&IF($X131=マイタスク!$U$5,"SVレビュー","") | AF131: =VALUE(RIGHT($E131,4)) -> 17 | AG131: e
B132: 120 | C132: A0098 | D132: HR_myTIM/OTデータ作成(Google) | E132: A0098-0017 | F132: 【myTIM】HR_myTIM/OTデータ作成(Google) 9/15週 | G132: 生麦X | H132: デリバリ完了 | I132: =$Q132 -> 0 | K132: A0098-0017-02 | L132: 【myTIM】HR_myTIM/OTデータ作成(Google) 9/15週 メール作業 | M132: 集計完了 | N132: shinsuke.eto | O132: 45916 | S132: shinra.sakaki | T132: 45919 | X132: ryusei.inaba | Y132: 45919 | Z132: 45919 | AE132: =IF($N132=マイタスク!$U$5,"作業者","")&IF($S132=マイタスク!$U$5,"ピアレビュー","")&IF($X132=マイタスク!$U$5,"SVレビュー","") | AF132: =VALUE(RIGHT($E132,4)) -> 17 | AG132: e
... B140: 128 | C140: A0098 | D140: HR_myTIM/OTデータ作成(Google) | E140: A0098-0015 | F140: 【myTIM】HR_myTIM/OTデータ作成(Google) 9/8週 | G140: 生麦X | H140: デリバリ完了 | I140: =$Q140 -> 0 | K140: A0098-0015-02 | L140: 【myTIM】HR_myTIM/OTデータ作成(Google) 9/8週 メール工程 | M140: 集計完了 | N140: shunsuke.taniguchi | O140: 45908 | S140: riamu.daikusu | T140: 45912 | X140: ryusei.inaba | Y140: 45912 | Z140: 45912 | AE140: =IF($N140=マイタスク!$U$5,"作業者","")&IF($S140=マイタスク!$U$5,"ピアレビュー","")&IF($X140=マイタスク!$U$5,"SVレビュー","") | AF140: =VALUE(RIGHT($E140,4)) -> 15 | AG140: e
B141: 129 | C141: P3000 | D141: 改善案件(共通) | E141: P3000-0658 | F141: 【myTIM】HR_myTIM/OTデータ作成(Google) マニュアル修正 | G141: 生麦X | H141: デリバリ完了 | I141: =$Q141 -> 0 | K141: P3000-0658-01 | L141: 【myTIM】HR_myTIM/OTデータ作成(Google) マニュアル修正 | M141: 集計完了 | N141: shinra.sakaki | O141: 45856 | X141: yuichi.kimura | Y141: 45856 | Z141: 45856 | AE141: =IF($N141=マイタスク!$U$5,"作業者","")&IF($S141=マイタスク!$U$5,"ピアレビュー","")&IF($X141=マイタスク!$U$5,"SVレビュー","") | AF141: =VALUE(RIGHT($E141,4)) -> 658 | AG141: e
B142: 130 | C142: P3000 | D142: 改善案件(共通) | E142: P3000-0838 | F142: 【myTIM】HR_myTIM/OTデータ作成(Google) マニュアル修正 | G142: 生麦X | H142: デリバリ完了 | I142: =$Q142 -> 0 | K142: P3000-0838-01 | L142: 【myTIM】HR_myTIM/OTデータ作成(Google) マニュアル修正 | M142: 集計完了 | N142: naoto.maejima | O142: 45979 | S142: ryota.nozawa | T142: 45989 | X142: ryusei.inaba | Y142: 45989 | Z142: 45989 | AE142: =IF($N142=マイタスク!$U$5,"作業者","")&IF($S142=マイタスク!$U$5,"ピアレビュー","")&IF($X142=マイタスク!$U$5,"SVレビュー","") | AF142: =VALUE(RIGHT($E142,4)) -> 838 | AG142: e
B143: 131 | C143: P3000 | D143: 改善案件(共通) | E143: P3000-0714 | F143: 【myTIM】HR_myTIM/OTデータ作成(Google) マニュアル改定 | G143: 生麦X | H143: デリバリ完了 | I143: =$Q143 -> 0 | K143: P3000-0714-01 | L143: 【myTIM】HR_myTIM/OTデータ作成(Google) マニュアル改定 | M143: 集計完了 | N143: shinra.sakaki | O143: 45895 | S143: ryota.nozawa | T143: 45895 | X143: ryusei.inaba | Y143: 45895 | Z143: 45898 | AE143: =IF($N143=マイタスク!$U$5,"作業者","")&IF($S143=マイタスク!$U$5,"ピアレビュー","")&IF($X143=マイタスク!$U$5,"SVレビュー","") | AF143: =VALUE(RIGHT($E143,4)) -> 714 | AG143: e
B144: 132 | C144: P3000 | D144: 改善案件(共通) | E144: P3000-0415 | F144: 【myTIM】マニュアル見直し | G144: 生麦X | H144: デリバリ完了 | I144: =$Q144 -> 0 | K144: P3000-0415-01 | L144: 【myTIM】マニュアル見直し | M144: 集計完了 | N144: shinra.sakaki | O144: 45708 | S144: rintaro.watanabe | T144: 45716 | X144: yuichi.kimura | Y144: 45716 | Z144: 45716 | AE144: =IF($N144=マイタスク!$U$5,"作業者","")&IF($S144=マイタスク!$U$5,"ピアレビュー","")&IF($X144=マイタスク!$U$5,"SVレビュー","") | AF144: =VALUE(RIGHT($E144,4)) -> 415 | AG144: e
B145: 133 | C145: P3999 | D145: テスト運用サービス(共通) | E145: P3999-0432 | F145: 【Nグループ】Supplier_榊さん | G145: 生麦X | H145: デリバリ完了 | I145: =$Q145 -> 0 | K145: P3999-0432-01 | L145: 【Nグループ】Supplier_榊さん | M145: 集計完了 | N145: shinra.sakaki | O145: 45580 | S145: hironori.tanikawa | T145: 45580 | X145: takashi.muramatsu | Y145: 45580 | Z145: 45590 | AE145: =IF($N145=マイタスク!$U$5,"作業者","")&IF($S145=マイタスク!$U$5,"ピアレビュー","")&IF($X145=マイタスク!$U$5,"SVレビュー","") | AF145: =VALUE(RIGHT($E145,4)) -> 432 | AG145: e
...

Sheet マイタスク
B1: ***Highly Confidential. Not To Be Distributed Further Without Authorization of the Sender. *** Copyright © 2026 Accenture. All rights reserved.
B2: PJT・サテライトのみ共有可
AF3: e
K4: マイタスクシート | AF4: e
R5: 自分のEIDを入力→ | U5: EIDxxxxx | AF5: e
AF6: e
N7: 実行作業者 | S7: ピアレビュー担当者 | X7: SVレビュー担当者 | AC7: 依頼元レビュー担当者 | AF7: e
B8: # | C8: サービス管理番号 | D8: サービス名 | E8: 案件番号 | F8: 案件名 | G8: チーム(案件) | H8: 案件ステータス | I8: 案件デリバリ開始日 | J8: 案件デリバリ完了日 | K8: タスク番号 | L8: タスク名 | M8: タスクステータス | N8: 実行作業担当者 | O8: 予定：開始日 | P8: 予定：完了日 | Q8: 実績：開始日 | R8: 実績：完了日 | S8: ピアレビュー担当者 | T8: 予定：開始日 | U8: 予定：完了日 | V8: 実績：開始日 | W8: 実績：完了日 | X8: SVレビュー担当者 | Y8: 予定：開始日 | Z8: 予定：完了日 | AA8: 実績：開始日 | AB8: 実績：完了日 | AC8: 依頼元レビュー担当者 | AD8: 実績：依頼元レビュー完了日 | AE8: 自分の役割 | AF8: e
B9: {=IFERROR(_xlfn._xlws.FILTER(案件管理マスタ_案件・タスク版!$B$13:$AE$1048576,(TRIM(案件管理マスタ_案件・タスク版!$N$13:$N$1048576)=TRIM($U$5))+(TRIM(案件管理マスタ_案件・タスク版!$S$13:$S$1048576)=TRIM($U$5))+(TRIM(案件管理マスタ_案件・タスク版!$X$13:$X$1048576)=TRIM($U$5)),"該当タスクなし"),"該当タスクなし")} -> 該当タスクなし | AF9: e
AF10: e
AF11: e
AF12: e
AF13: e
AF14: e
AF15: e
AF16: e
AF17: e
AF18: e
AF19: e
AF20: e
AF21: e
... AF569: e
A570: e | B570: e | C570: e | D570: e | E570: e | F570: e | G570: e | H570: e | I570: e | J570: e | K570: e | L570: e | M570: e | N570: e | O570: e | P570: e | Q570: e | R570: e | S570: e | T570: e | U570: e | V570: e | W570: e | X570: e | Y570: e | Z570: e | AA570: e | AB570: e | AC570: e | AD570: e | AE570: e | AF570: e

Sheet マスタ-->

Sheet サービス情報マスタcopy
B1: 凡例 | AN1: ↓↓↓ | BB1: e
B2: フリーテキストエリア | F2: 別チームへのサービス移管を行う場合、移管元/移管先の拠点に依存せず、常に新規サービス番号を採番する。 | BB2: e
B3: 値選択エリア | BB3: e
B4: 自動表示(関数)エリア | F4: ↓PJT運用企画Tで決定・記入 | L4: › | AG4: ↓G列に共通している名称をAG列に記入 | AI4: ↓PJT業務企画Tで記入 | AO4: ↓サテライト(SSD/担当T)、PJTで記入 | AQ4: ↓PJT運用企画Tで記入【2025/05廃止予定】 | AT4: ↓PJT運用企画Tで記入 | AU4: 最新更新日➡ | AV4: =MAX(AV8:AV431) -> 45902 | BB4: e
B5: ★受託ｻｰﾋﾞｽ： WDM登録項目 | D5: ★ | E5: ★WDM登録項目 | F5: ★ | G5: ★ | H5: ★ | I5: ★ | J5: ★ | K5: ★ | Z5: ★ | AA5: ★ | AC5: ★（サービス停止時に記入） | AI5: ★ | AJ5: ★ | AK5: ★ | AL5: ★ | BB5: e
A6: =IF(Z6="サービス停止",Z6,"") | B6: サービス管理番号 | C6: サービス管理番号 重複チェック | D6: 案件種別 | E6: 旧サービス 管理番号 | F6: サービスカテゴリ | G6: サービス名 | H6: サービス概要 | I6: 担当拠点 | J6: 担当チーム | K6: 担当SV | L6: 配送物 の有無 | M6: 頻度 | N6: 依頼方法 | O6: 納期 (リードタイム) | P6: 依頼者からの レビューバック | Q6: 成果物の 提出方法 | R6: データ保持期限 | S6: 依頼者への完了報告 | U6: 対応リスク | V6: 依頼元への権限付与依頼 | W6: 依頼元 | Z6: ステータス | AA6: サービス開始年月日 | AC6: サービス停止年月日 | AE6: 移管先サービス番号 | AF6: 単発依頼フラグ | AG6: サービスグループ情報 | AI6: 組織情報(集計用) | AN6: メモ/備考 | AO6: WDMメンテステータス | AQ6: 運用企画T | AY6: 運用企画T_必須入力項目確認 | BA6: 記載順ソート用No | BB6: e
S7: 返信方法 | T7: 返信手段 | U7: 扱っているデータに顧客データ/情報が含まれている | W7: DTE | X7: 担当者 | Y7: スポンサーMD | AA7: システム有効開始 | AB7: 業務的開始日 | AC7: システム有効終了 | AD7: 業務的停止日 | AG7: グループ | AH7: 順序 | AI7: ①組織名 | AJ7: ①割合 | AK7: ②組織名 | AL7: ②割合 | AM7: 更新日 | AO7: Status | AP7: 備考 | AQ7: 【2025/05廃止予定】 データ計測方法検討ステータス | AR7: 【2025/05廃止予定】 ステータス更新日 | AS7: 【作業後廃止予定】 WDM登録状況 (2025/5/8時点) | AT7: WDM登録方針(2025/5/8以降) | AU7: 備考 | AV7: 方針決定日 | AW7: 対応内容 (Liさんへの依頼) | AX7: 対応日 (担当:Liさん) | AY7: 必須入力 Check <サテライト> | AZ7: 必須入力Check <PJT> | BB7: e
A8: =IF(Z8="サービス停止",Z8,"") -> サービス停止 | C8: =IF(B8="","-",IF(COUNTIF($B$8:B8,B8)=1,"〇","×")) -> - | D8: 受託 | E8: SN_0001 | F8: 07入力・登録代行 | G8: 名刺情報入力代行 | H8: Outlookの連絡先に連絡先を追加するマクロの入力テンプレート(myBiC)に名刺情報を入力する。 | I8: 生麦 | K8: emiko.maeyama | L8: 有 | M8: 随時 | N8: リクエストフォーム | O8: 入力：4営業日 ※Outbox投函からmyBiC提供まで最長1ヶ月 | P8: 無 (但し、入力不備があった場合はメールでの指摘有り) | Q8: SharePoint上の個別フォルダ (権限設定有り) | R8: SharePoint上は3か月 | S8: 手動 | T8: ・アップロード完了連絡 ・配送完了連絡 | U8: 〇 | V8: × | W8: Strategy | X8: 別紙参照（SN_対象者リスト_20200529_v1.0） | Z8: サービス停止 | AA8: 43709 | AB8: ー | AC8: FY24以前 | AD8: ー | AI8: ー | AJ8: ー | AK8: ー | AL8: ー | AN8: myTE経費入力代行と同時依頼 2019/11/1より、リクエストフォームからの非定常サービスに変更 但し、名刺返却はmyTE経費入力代行と同タイミングで配送 ・2022年7月より、立川Ｘチームにサービス移管（ST_0049） | AO8: - | AS8: (サービス停止) | AT8: 9.対応不要 | AV8: 45785 | AY8: =IF(D8="受託",IF(COUNTA(B8,F8,G8:J8,Z8:AA8)=8,"OK","NG"),"確認対象外") -> NG | AZ8: =ISNUMBER(AJ8) -> FALSE | BA8: =ROW()-7 -> 1 | BB8: e
A9: =IF(Z9="サービス停止",Z9,"") -> サービス停止 | C9: =IF(B9="","-",IF(COUNTIF($B$8:B9,B9)=1,"〇","×")) -> - | D9: 受託 | E9: SN_0002 | G9: myTE経費入力代行 | H9: myTEの入力補助マクロ(myTES)の 入力テンプレートに経費情報を入力する。 | I9: 生麦 | K9: emiko.maeyama | L9: 有 | M9: 指定Period | N9: 定常作業のため、無し (情報提供依頼メールへの返信によって、対応開始) | O9: 入力：4営業日 | P9: 無 (但し、入力不備があった場合はメールでの指摘有り) | Q9: SharePoint上の個別フォルダ (権限設定有り) | R9: SharePoint上は3か月 | S9: 手動 | T9: ・アップロード完了連絡 ・配送完了連絡 | U9: 〇 | V9: × | W9: Strategy | X9: 別紙参照（SN_対象者リスト_20200529_v1.0） | Z9: サービス停止 | AA9: 43709 | AB9: ー | AC9: FY24以前 | AD9: ー | AI9: ー | AJ9: ー | AK9: ー | AL9: ー | AN9: 名刺情報入力代行と同時依頼 2019/11/15Pより、各依頼者に対し、全Period分を対応。(1Periodは、2グループに分けて実施) ・2022/6/30Pをもって、サービス終了 | AO9: - | AS9: (サービス停止) | AT9: 9.対応不要 | AV9: 45785 | AY9: =IF(D9="受託",IF(COUNTA(B9,F9,G9:J9,Z9:AA9)=8,"OK","NG"),"確認対象外") -> NG | AZ9: =ISNUMBER(AJ9) -> FALSE | BA9: =ROW()-7 -> 2 | BB9: e
A10: =IF(Z10="サービス停止",Z10,"") | B10: A1003 | C10: =IF(B10="","-",IF(COUNTIF($B$8:B10,B10)=1,"〇","×")) -> 〇 | D10: 受託 | E10: SN_0003 | F10: 03サニタイズ編集 | G10: KXサニタイズ代行 | H10: 依頼されたドキュメントをKXに登録可能なフォーマットに修正する。 2020/10/1以降から、SN_0027の後続タスク追加 Quarter単位でサニタイズ依頼が発生(Best project、FORM) フローから外れたもののみ、リクエストフォームでの依頼 | I10: 生麦 | J10: TF | K10: tomoyuki.a.hishiki | L10: 無 | M10: 随時 | N10: ・SN内担当チームからのメール受信 ・リクエストフォーム | O10: 一次提出：3週間 納期:4週間 | P10: 有(メール) レビューバック反映も実施する | Q10: SharePoint上の個別フォルダ (権限設定有り) | R10: 作業完了後3ヶ月経過したら削除 | S10: 手動 | T10: ・アップロード完了連絡 | U10: 〇 | V10: × | W10: CF_KM | X10: 酒井さん（takahiro.a.sakai）:BEST担当 西田さん（kumiko.nishida）:BEST担当 榊原さん（anna.sakakibara）:FORM担当 Japan.ACSKM@accenture.com Japan.ACSKM.FORM@accenture.com | Z10: =IF(AC10="",IF(AA10="","",IF(TODAY()>=AA10,"サービス開始",IF(TODAY()<AA10,"本稼働前",""))),IF(TODAY()>=AC10,"サービス停止",IF(AA10="","",IF(TODAY()>=AA10,"サービス開始",IF(TODAY()<AA10,"本稼働前",""))))) -> サービス開始 | AA10: 43770 | AB10: ー | AG10: KXサニタイズ代行 | AH10: ①A1004 ②A1003 | AI10: Corporate Function | AJ10: 1 | AK10: ー | AL10: ー | AM10: 45674 | AN10: 2021/10/1より、担当SV変更：Maeyama→（Takahashi,Airi)→Ito 2022/05/15より、担当SV変更：Ito→Watanabe 2023/3/1より、担当SV変更：koji.c.watanabe→hiroyuki.hishiki | AO10: - | AQ10: A_通常_決定(登録可) | AS10: 登録済_本登録 | AT10: 4b.本登録_計測方法確定(FY24以前) | AV10: 45785 | AY10: =IF(D10="受託",IF(COUNTA(B10,F10,G10:J10,Z10:AA10)=8,"OK","NG"),"確認対象外") -> OK | AZ10: =ISNUMBER(AJ10) -> TRUE | BA10: =ROW()-7 -> 3 | BB10: e
A11: =IF(Z11="サービス停止",Z11,"") | B11: A1004 | C11: =IF(B11="","-",IF(COUNTIF($B$8:B11,B11)=1,"〇","×")) -> 〇 | D11: 受託 | E11: SN_0004 | F11: 02サニタイズ編集要件 | G11: WordList作成作業(KXサニタイズ代行) | H11: KXサニタイズに必要なWordListを作成する。 2020/10/1以降から、SN_0027の後続タスク追加 Quarter単位でサニタイズ依頼が発生(Best project、FORM) フローから外れたもののみ、リクエストフォームでの依頼 | I11: 生麦 | J11: TF | K11: tomoyuki.a.hishiki | L11: 無 | M11: 随時 | N11: ・SN内担当チームからのメール受信 ・リクエストフォーム | O11: 一次提出：3週間 納期:4週間 | P11: 有(メール) レビューバック反映も実施する | Q11: SharePoint上の個別フォルダ (権限設定有り) | R11: 作業完了後3ヶ月経過したら削除 | S11: 手動 | T11: ・アップロード完了連絡 | U11: 〇 | V11: × | W11: CF_KM | X11: 酒井さん（takahiro.a.sakai）:BEST担当 西田さん（kumiko.nishida）:BEST担当 榊原さん（anna.sakakibara）:FORM担当 Japan.ACSKM@accenture.com Japan.ACSKM.FORM@accenture.com | Z11: =IF(AC11="",IF(AA11="","",IF(TODAY()>=AA11,"サービス開始",IF(TODAY()<AA11,"本稼働前",""))),IF(TODAY()>=AC11,"サービス停止",IF(AA11="","",IF(TODAY()>=AA11,"サービス開始",IF(TODAY()<AA11,"本稼働前",""))))) -> サービス開始 | AA11: 43770 | AB11: ー | AG11: KXサニタイズ代行 | AH11: ①A1004 ②A1003 | AI11: Corporate Function | AJ11: 1 | AK11: ー | AL11: ー | AM11: 45674 | AN11: 2019/11/1より、案件リスト上で分割。 KXサニタイズ作業とWordlist作成が同時に依頼された場合、別の案件として起票する。 2021/10/1より、担当SV変更：Maeyama→（Takahashi,Airi)→Ito 2022/05/15より、担当SV変更：Ito→Watanabe 2023/3/1より、担当SV変更：koji.c.watanabe→hiroyuki.hishiki | AO11: - | AQ11: A_通常_決定(登録可) | AS11: 登録済_本登録 | AT11: 4b.本登録_計測方法確定(FY24以前) | AV11: 45785 | AY11: =IF(D11="受託",IF(COUNTA(B11,F11,G11:J11,Z11:AA11)=8,"OK","NG"),"確認対象外") -> OK | AZ11: =ISNUMBER(AJ11) -> TRUE | BA11: =ROW()-7 -> 4 | BB11: e
A12: =IF(Z12="サービス停止",Z12,"") -> サービス停止 | C12: =IF(B12="","-",IF(COUNTIF($B$8:B12,B12)=1,"〇","×")) -> - | D12: 受託 | E12: SN_0005 | G12: MCOM_記事配信(中途社員紹介) | H12: MCOMの配信用記事の中途社員紹介を作成する。 | I12: 生麦 | K12: akiko.a.hirano | L12: 無 | M12: 月次 | N12: 定常作業のため、無し (指定のフォルダーに毎月15日17:00までに格納(15日が土日祝日の場合、その前の営業日)され次営業日より、対応開始) | O12: 作成：3営業日 | P12: 無 (メールにてレビューバックはあるが、指摘反映は不要) | Q12: レビューURLをメールにて送付 | S12: 手動 | T12: 作業提出メールと同時に完了報告を行う | U12: 〇 | V12: 〇 Wordpress （指定の申請書に直接記入で申請メールなし：備考欄参照） | W12: CF_MCOM | X12: 河村さん（takuro.kawamura） →魚住さん(Uozumi, Azusa) 加藤さん（mayako.kato）退職 小畑さん（kaoru.obata）退職 IMJ担当者 村上さん（kumiko.murakami) | Z12: サービス停止 | AA12: 43770 | AB12: ー | AC12: FY24以前 | AD12: ー | AI12: ー | AJ12: ー | AK12: ー | AL12: ー | AM12: 45674 | AN12: 2019年11月より開始で、初回は2019/11/15に作業依頼として依頼元が、指定フォルダーに格納 ■Japan information siteの「Editor」権限が必要。 下記申請フォームに入力。(いむじぇ分の登録も必要) https://ts.accenture.com/:x:/r/Sites/mcomjapan/_layouts/15/Doc.aspx?sourcedoc=%7B97EFB4A5-D615-4C87-B04E-09AAA524F65B%7D&file=ApplicationForm-EditingRightsForJIS_2020.xlsx&action=default&mobileredirect=true&cid=f148a7a4-b329-46fa-a3b0-6c1cb44c4d8b ※いむじぇ追加の場合IMJ側の担当者の情報もメモ欄に記入が必要。 2021/12/20 依頼元からの作業依頼が滞っていたため、状況を確認。中途社員紹介はIMJの案件だったが、先日完全子会社となったこともあり諸々体制が変更中のため、一旦クローズして構わない。→クローズ。 | AO12: - | AS12: (サービス停止) | AT12: 9.対応不要 | AV12: 45785 | AY12: =IF(D12="受託",IF(COUNTA(B12,F12,G12:J12,Z12:AA12)=8,"OK","NG"),"確認対象外") -> NG | AZ12: =ISNUMBER(AJ12) -> FALSE | BA12: =ROW()-7 -> 5 | BB12: e
A13: =IF(Z13="サービス停止",Z13,"") | B13: A1006 | C13: =IF(B13="","-",IF(COUNTIF($B$8:B13,B13)=1,"〇","×")) -> 〇 | D13: 受託 | E13: SN_0006 | F13: 05配信記事編集 | G13: MCOM_記事配信(Article)-Media Report | H13: MCOMの配信用記事のArticleのMedia Reportを作成する。 | I13: 生麦 | J13: 生麦Z | K13: =IFERROR(VLOOKUP([9]サービス一覧!J13,[9]List!$M$3:$N$24,2,FALSE)&"","") -> hiroyuki.yoshida | L13: 無 | M13: 週次 | N13: メールで日本語と英語の記事が届く。定常作業のため、無し (指定のフォルダーに毎週月曜17:00 毎週火曜日18:00 までに格納された分を翌営業日から対応開始) | O13: 記事作成対象期間の最終日の1営業日後から3営業日目まで | P13: 無(Teamsにてレビューバックはあるが、指摘反映は不要) | Q13: Formsに記事のURL等を記入して提出 | R13: １カ月 | S13: 手動 | T13: Teams | U13: × | V13: 〇 Wordpress （指定の申請書に直接記入で申請メールなし：備考欄参照） | W13: CF_MCOM | X13: 魚住さん（azusa.uozumi） 村上さん（ayami.murakami） | Z13: =IF(AC13="",IF(AA13="","",IF(TODAY()>=AA13,"サービス開始",IF(TODAY()<AA13,"本稼働前",""))),IF(TODAY()>=AC13,"サービス停止",IF(AA13="","",IF(TODAY()>=AA13,"サービス開始",IF(TODAY()<AA13,"本稼働前",""))))) -> サービス開始 | AA13: 43770 | AB13: ー | AI13: Corporate Function | AJ13: 1 | AK13: ー | AL13: ー | AM13: 45674 | AN13: 2019年11月より開始で、初回は2019/11/5に作業依頼として依頼元が、指定フォルダーに格納 2020年6月9日より、格納タイミングを変更 ■Japan information siteの「Editor」権限が必要。 下記申請フォームに入力。 https://ts.accenture.com/:x:/r/Sites/mcomjapan/_layouts/15/Doc.aspx?sourcedoc=%7B97EFB4A5-D615-4C87-B04E-09AAA524F65B%7D&file=ApplicationForm-EditingRightsForJIS_2020.xlsx&action=default&mobileredirect=true&cid=f148a7a4-b329-46fa-a3b0-6c1cb44c4d8b 2026/3/1：担当SV変更（hiroshi.a.harashima → hiroyuki.yoshida） | AO13: - | AQ13: A_通常_決定(登録可) | AS13: 登録済_本登録 | AT13: 3.登録修正_計測方法要再検討 | AU13: ＜10/7＞ 変更業務確認し、サービスカテゴリ「05配信記事編集」と再定義 ＜5/8＞ 定義済み計測方法ではなくなった為(担当チームで独自に変更)、サービスカテゴリ「05配信記事編集」から「93TBD_保留」へ変更 ➡WDM登録方法： ・サービスカテゴリ変更は、新規登録(別レコード)で行う。 ・旧サービスカテゴリ「05配信記事編集」のサービスの停止日は、2025/06/08とする。 | AV13: 45785 | AW13: ('25/10/7)サービスカテゴリを変更 | AX13: 45786 | AY13: =IF(D13="受託",IF(COUNTA(B13,F13,G13:J13,Z13:AA13)=8,"OK","NG"),"確認対象外") -> OK | AZ13: =ISNUMBER(AJ13) -> TRUE | BA13: =ROW()-7 -> 6 | BB13: e
A14: =IF(Z14="サービス停止",Z14,"") -> サービス停止 | B14: A1007 | C14: =IF(B14="","-",IF(COUNTIF($B$8:B14,B14)=1,"〇","×")) -> 〇 | D14: 受託 | E14: SN_0007 | F14: 08データ集計・整形 | G14: WP_社内環境データ集計(Census) | H14: WPの社内環境データ集計として、Censusを集計する。(対象ビル：３) | I14: 生麦 | J14: 生麦Y | K14: emiko.maeyama | L14: 無 | M14: 週次 | N14: 定常作業のため、無し (指定のフォルダーに毎週金曜17:00までに格納) | O14: 作成：3営業日 (最大８営業日：第一次提出日までは３営業日、作業Excelレビューに3営業日、指摘反映＋反映確認に2営業日) | P14: 有(メール) ・レビューバック：3営業日 ・レビュー反映：２営業日 | Q14: 作業Excelを指定フォルダーに格納して提出 | R14: １カ月 【データ保持期限の確認対象】 １．生麦から提供している情報でoldに退避した分 (censusーold) (空気環境測定-old) (サーバルーム温度-old) ２．生麦の報告資料作成のための作業用情報（毎回作成して、バックアップしています） | S14: 手動 | T14: 作業提出メールと同時に完了報告を行う | U14: × | V14: × | W14: CF_WP | X14: 藤井さん（kenji.fujii） 齊藤さん（h.saito） 提出メール宛先／廣瀬さん（hirose.rio） | Z14: サービス停止 | AA14: 43770 | AB14: ー | AC14: FY24以前 | AD14: ー | AI14: ー | AJ14: ー | AK14: ー | AL14: ー | AM14: 45674 | AN14: 2019年11月より開始で、初回は2019/11/8に作業依頼として依頼元が、指定フォルダーに格納 2022年9月、サービス停止 | AO14: - | AS14: (サービス停止) | AT14: 9.対応不要 | AV14: 45785 | AY14: =IF(D14="受託",IF(COUNTA(B14,F14,G14:J14,Z14:AA14)=8,"OK","NG"),"確認対象外") -> OK | AZ14: =ISNUMBER(AJ14) -> FALSE | BA14: =ROW()-7 -> 7 | BB14: e
A15: =IF(Z15="サービス停止",Z15,"") -> サービス停止 | B15: A1008 | C15: =IF(B15="","-",IF(COUNTIF($B$8:B15,B15)=1,"〇","×")) -> 〇 | D15: 受託 | E15: SN_0008 | F15: 08データ集計・整形 | G15: WP_社内環境データ集計(サーバールーム温度) | H15: WPの社内環境データ集計として、サーバールーム温度を集計する。(対象ビル：7) | I15: 生麦 | J15: 生麦Y | K15: emiko.maeyama | L15: 無 | M15: 月次 | N15: 定常作業のため、無し (指定サイトに当月のデータを翌月の月初(第一営業日)にダウンロード) ※：作業者が指定サイトを確認し、ダウンロード | O15: 作成：3営業日 (最大８営業日：第一次提出日までは３営業日、作業Excelレビューに3営業日、指摘反映＋反映確認に2営業日) | P15: 有(メール) ・レビューバック：3営業日 ・レビュー反映：２営業日 | Q15: 作業Excelを指定フォルダーに格納して提出 | R15: １カ月 【データ保持期限の確認対象】 １．生麦から提供している情報でoldに退避した分 (censusーold) (空気環境測定-old) (サーバルーム温度-old) ２．生麦の報告資料作成のための作業用情報（毎回作成して、バックアップしています） | S15: 手動 | T15: 作業提出メールと同時に完了報告を行う | U15: × | V15: × | W15: CF_WP | X15: 藤井さん（kenji.fujii） 齊藤さん（h.saito） 提出メール宛先／廣瀬さん（hirose.rio） | Z15: サービス停止 | AA15: 43770 | AB15: ー | AC15: 45351 | AD15: ー | AI15: ー | AJ15: ー | AK15: ー | AL15: ー | AM15: 45674 | AN15: 2019年11月より開始。 2021年2月から拠点増(TSC)。8拠点→9拠点に変更。 2022年8月、対応7拠点に変更 2024/2/29：生麦Xへの移管に伴いサービス停止 | AO15: - | AS15: (サービス停止) | AT15: 9.対応不要 | AV15: 45785 | AY15: =IF(D15="受託",IF(COUNTA(B15,F15,G15:J15,Z15:AA15)=8,"OK","NG"),"確認対象外") -> OK | AZ15: =ISNUMBER(AJ15) -> FALSE | BA15: =ROW()-7 -> 8 | BB15: e
A16: =IF(Z16="サービス停止",Z16,"") -> サービス停止 | B16: A1009 | C16: =IF(B16="","-",IF(COUNTIF($B$8:B16,B16)=1,"〇","×")) -> 〇 | D16: 受託 | E16: SN_0009 | F16: 08データ集計・整形 | G16: WP_社内環境データ集計(空調設備) | H16: WPの社内環境データ集計として、空調測定結果を集計する。(対象ビル：8) | I16: 共通 | J16: 生麦Y 中津Y | K16: emiko.maeyama | L16: 無 | M16: 月次 | N16: 定常作業のため、無し (指定のフォルダーに当月のデータを翌月の月初(第一営業日)までに格納) | O16: 作成：3営業日 (最大８営業日：第一次提出日までは３営業日、作業Excelレビューに3営業日、指摘反映＋反映確認に2営業日) | P16: 有(メール) ・レビューバック：3営業日 ・レビュー反映：２営業日 | Q16: 作業Excelを指定フォルダーに格納して提出 | R16: １カ月 【データ保持期限の確認対象】 １．生麦から提供している情報でoldに退避した分 (censusーold) (空気環境測定-old) (サーバルーム温度-old) ２．生麦の報告資料作成のための作業用情報（毎回作成して、バックアップしています） | S16: 手動 | T16: 作業提出メールと同時に完了報告を行う | U16: × | V16: × | W16: CF_WP | X16: 藤井さん（kenji.fujii） 齊藤さん（h.saito） 提出メール宛先／廣瀬さん（hirose.rio） | Z16: サービス停止 | AA16: 43770 | AB16: ー | AC16: FY24以前 | AD16: ー | AI16: ー | AJ16: ー | AK16: ー | AL16: ー | AM16: 45674 | AN16: 2019年11月より開始 ベンダー情報が必要なため、依頼元で取得できない場合は、依頼がないことがある。2020年1月分より地方拠点3ビル追加。(作業は2月月初より)AIO及びAIFは奇数月分、AIHは偶数月分について作業。 2024/2/29：生麦Yに加え、中津Yも参画 2024/4/1 チーム移管に伴いサービス停止 | AO16: - | AS16: (サービス停止) | AT16: 9.対応不要 | AV16: 45785 | AY16: =IF(D16="受託",IF(COUNTA(B16,F16,G16:J16,Z16:AA16)=8,"OK","NG"),"確認対象外") -> OK | AZ16: =ISNUMBER(AJ16) -> FALSE | BA16: =ROW()-7 -> 9 | BB16: e
A17: =IF(Z17="サービス停止",Z17,"") -> サービス停止 | C17: =IF(B17="","-",IF(COUNTIF($B$8:B17,B17)=1,"〇","×")) -> - | D17: 受託 | E17: SN_0010 | G17: ACS_記事配信(各DTE) | H17: 各部署(DTE)の配信用記事のArticleのMedia Reportを作成する。 (SN_0006ではMCOMの特定記事だったが、本サービスでは複数部署) | I17: 生麦 | K17: akiko.a.hirano | L17: 無 | M17: 随時 | N17: リクエストフォーム | O17: 作成：5-10営業日 (最大10営業日：担当者の稼働状況に応じてリクエストフォームで納期提示する) | P17: 有(メール) レビューバック反映も実施する | Q17: 編集画面URLと画面キャプチャをメールで担当者に送付(公開したい方はURL、レビューのみしたい方はキャプチャでご確認頂く) | S17: 手動 | T17: 公開後にその旨メールで担当者にお知らせ(公開がご担当者の場合はレビュー後に完了) | U17: × | V17: 〇 ACS記事作成 （ACN.Collaboration.Services.Japan@accenture.comへメールにて依頼） | W17: HPS Delivery_Control AABG IES CSA ITO AMBG サービス依頼元：OK&DS 各記事の依頼元：Technology内の全組織 | X17: 米山さん（mizuki.yoneyama） 熊井さん（hitomi.kumai） ACN.Collaboration.Services.Japan@accenture.com | Z17: サービス停止 | AA17: 43801 | AB17: ー | AC17: FY24以前 | AD17: ー | AI17: ー | AJ17: ー | AK17: ー | AL17: ー | AM17: 45674 | AN17: 2019年12月2日より開始 「作業依頼から納期までのリードタイム」は5営業日にしていますが、依頼の件数が集中する場合も想定されますので、案件ごとに実施の可否判断。 2020年10月中旬より運用変更： 質問事項対応：確認リストに記入し、メールさせて頂く。リスト格納場所はメールに記載。(宛先：米山さん（mizuki.yoneyama）、CC: ACN.Collaboration.Services.Japan@accenture.com) 【対象DTE】 ・2019年時点実績：2DTE(CMT、RES) ・2020年1月中旬：PRD追加(月4-6記事程度) ・2020年2月：HPS追加 ・2020年5月：CMT(削除)、IES(追加) ・2020年6月：AABG ・2020年7月：CSA追加(月1記事程度) ・2020年8月：ITO追加(月1記事程度) ・2020年9月：AMBG追加(週3記事程度) ・2020年10月：Technology内の全組織（その他DTEは除外） 2021/1/1 から伊藤チーム対応へ変更(ST_0010) | AO17: - | AS17: (サービス停止) | AT17: 9.対応不要 | AV17: 45785 | AY17: =IF(D17="受託",IF(COUNTA(B17,F17,G17:J17,Z17:AA17)=8,"OK","NG"),"確認対象外") -> NG | AZ17: =ISNUMBER(AJ17) -> FALSE | BA17: =ROW()-7 -> 10 | BB17: e
A18: =IF(Z18="サービス停止",Z18,"") -> サービス停止 | C18: =IF(B18="","-",IF(COUNTIF($B$8:B18,B18)=1,"〇","×")) -> - | D18: 受託 | E18: SN_0011 | G18: Digital_マニュアルWeb化 | H18: DigitalのPPTマニュアルをTool(ホームページビルダー)にてWeb化 予定期間：2019/12/~2020/12/24 | I18: 生麦 | K18: hiroshi.a.harashima | L18: 無 | M18: 随時 | N18: 定常作業のため、無し (毎週水曜日に、次週分のWeb化マニュアルを格納) | O18: 該当週分を金曜日に指定フォルダーにアップロード | P18: 有(メール。必要に応じてCall) | Q18: Exportファイルを指定フォルダーに格納 | S18: 手動 | T18: 作業提出メールと同時に完了報告を行う | U18: 〇 | W18: Digital | X18: 内田さん（yuki.uchida） 清水さん（ryoichi.shimizu） 劉さん（dongqing.liu） | Z18: サービス停止 | AA18: 43800 | AB18: ー | AC18: FY24以前 | AD18: ー | AI18: ー | AJ18: ー | AK18: ー | AL18: ー | AM18: 45674 | AN18: 2019年12月よりテスト運用兼本番運用として開始し、2020年2月上旬までの予定。 →期間限定のため、「サービス停止」（本来は案件終了） | AO18: - | AS18: (サービス停止) | AT18: 9.対応不要 | AV18: 45785 | AY18: =IF(D18="受託",IF(COUNTA(B18,F18,G18:J18,Z18:AA18)=8,"OK","NG"),"確認対象外") -> NG | AZ18: =ISNUMBER(AJ18) -> FALSE | BA18: =ROW()-7 -> 11 | BB18: e
A19: =IF(Z19="サービス停止",Z19,"") -> サービス停止 | C19: =IF(B19="","-",IF(COUNTIF($B$8:B19,B19)=1,"〇","×")) -> - | D19: 受託 | E19: SN_0012 | G19: CCPMO_記事作成 | H19: CCPMOの配信用記事のArticleを作成する。 | I19: 生麦 | K19: akiko.a.hirano | L19: 無 | M19: 随時 | N19: リクエストフォーム | O19: 作成：４営業日 (最大６営業日：第一次提出日：4営業日、レビュー・指摘反映：2営業日) | P19: 有(メール) レビューバック反映も実施する | Q19: 編集画面URLをメールにて送付(TO：依頼者、CC：PMOのメーリス) | S19: 手動 | T19: 公開後にその旨メールでお知らせ | U19: × | X19: 栁谷さん（kikuko.yanagidani） | Z19: サービス停止 | AA19: 43822 | AB19: ー | AC19: FY24以前 | AD19: ー | AI19: ー | AJ19: ー | AK19: ー | AL19: ー | AM19: 45674 | AN19: 2019年12月23日より開始 →依頼元都合により、2020年8月に停止 | AO19: - | AS19: (サービス停止) | AT19: 9.対応不要 | AV19: 45785 | AY19: =IF(D19="受託",IF(COUNTA(B19,F19,G19:J19,Z19:AA19)=8,"OK","NG"),"確認対象外") -> NG | AZ19: =ISNUMBER(AJ19) -> FALSE | BA19: =ROW()-7 -> 12 | BB19: e
A20: =IF(Z20="サービス停止",Z20,"") -> サービス停止 | C20: =IF(B20="","-",IF(COUNTIF($B$8:B20,B20)=1,"〇","×")) -> - | D20: 受託 | E20: SN_0013 | G20: CCPMO_アサイン調整 | H20: CCPMOのアサイン調整の会議室確保とインビテーション送付する。 | I20: 生麦 | K20: akiko.a.hirano | L20: 無 | M20: 随時 | N20: リクエストフォーム | O20: 2営業日 | P20: 有(メール) レビューバック反映も実施する | Q20: インビテーション送付 | S20: 手動 | T20: インビテーション送付完了で対応完了とさせて頂く(再調整依頼メールがあった場合は対応) | U20: 〇 | X20: 栁谷さん（kikuko.yanagidani） | Z20: サービス停止 | AA20: 43822 | AB20: ー | AC20: FY24以前 | AD20: ー | AI20: ー | AJ20: ー | AK20: ー | AL20: ー | AM20: 45674 | AN20: 2019年12月23日より開始 2019/12/20時点では、日程調整はCCPMOの方に行って頂き、生麦での実施は別途検討。 →依頼元都合により、2020年8月に停止 | AO20: - | AS20: (サービス停止) | AT20: 9.対応不要 | AV20: 45785 | AY20: =IF(D20="受託",IF(COUNTA(B20,F20,G20:J20,Z20:AA20)=8,"OK","NG"),"確認対象外") -> NG | AZ20: =ISNUMBER(AJ20) -> FALSE | BA20: =ROW()-7 -> 13 | BB20: e
A21: =IF(Z21="サービス停止",Z21,"") -> サービス停止 | C21: =IF(B21="","-",IF(COUNTIF($B$8:B21,B21)=1,"〇","×")) -> - | D21: 受託 | E21: SN_0014 | G21: MCOM_記事配信(長編記事) | H21: MCOMの配信用記事の長編記事を作成する。 (Japan Information Site、いむじぇ 両方の対応あり) | I21: 生麦 | K21: akiko.a.hirano | L21: 無 | M21: 随時 | N21: リクエストフォーム (月2~3記事を想定) 原稿(編集画面URL記載頂く)・画像データをこちらに格納(フォルダ名「リクエストフォーム上のID_格納日」でフォルダを作成し格納 原稿のWordファイルを添付して頂く | O21: 作成：５営業日 (第一次提出日：５営業日、レビュー・指摘反映：なし) | P21: 無 (最終化は依頼元にて対応。ただし次回以降の改善につながるご指摘事項はメールにて共有頂く。) | Q21: 編集画面URLをメールで担当者に送付 | S21: 手動 | T21: 作業提出メールと同時に完了報告を行う | U21: × | V21: 〇 Wordpress （指定の申請書に直接記入で申請メールなし：備考欄参照） | W21: CF_MCOM | X21: 魚住さん（azusa.uozumi） IMJ担当者 村上さん（kumiko.murakami) | Z21: サービス停止 | AA21: 43844 | AB21: ー | AC21: FY24以前 | AD21: ー | AI21: ー | AJ21: ー | AK21: ー | AL21: ー | AM21: 45674 | AN21: 2020年1月14日より開始 2021/3/1 から、いむじぇサイトの記事依頼も受領開始 ■Japan information siteの「Editor」権限が必要。 下記申請フォームに入力。(いむじぇ分の登録も必要) https://ts.accenture.com/:x:/r/Sites/mcomjapan/_layouts/15/Doc.aspx?sourcedoc=%7B97EFB4A5-D615-4C87-B04E-09AAA524F65B%7D&file=ApplicationForm-EditingRightsForJIS_2020.xlsx&action=default&mobileredirect=true&cid=f148a7a4-b329-46fa-a3b0-6c1cb44c4d8b ※いむじぇ追加の場合IMJ側の担当者の情報もメモ欄に記入が必要。 2021/12/20 依頼が滞っていたため、依頼元に今後の依頼予定を確認したところ、当面長編記事依頼の見込みはございませんので 一旦取り下げていただいて結構ですとのこと。→クローズ。 | AO21: - | AS21: (サービス停止) | AT21: 9.対応不要 | AV21: 45785 | AY21: =IF(D21="受託",IF(COUNTA(B21,F21,G21:J21,Z21:AA21)=8,"OK","NG"),"確認対象外") -> NG | AZ21: =ISNUMBER(AJ21) -> FALSE | BA21: =ROW()-7 -> 14 | BB21: e
A22: =IF(Z22="サービス停止",Z22,"") -> サービス停止 | C22: =IF(B22="","-",IF(COUNTIF($B$8:B22,B22)=1,"〇","×")) -> - | D22: 受託 | E22: SN_0015 | G22: T-Pro_工数分析 | H22: T-Proの工数分析レポートを作成する。 | I22: 生麦 | K22: shigeki.ohtake | L22: 無 | M22: 月次 | N22: 期日が到来したら作業を開始する（作業トリガー：火曜日＠月末最終木曜週） ※月末最終木曜日が祝日を含む非営業日の場合、3営業日前から作業を開始する ※12月のみ 火曜日＠月末最終木曜週の前週対応 (依頼元にて、顧客の休日となるため) | O22: 作成：1.4営業日（以下の曜日で、祝日を含む非営業日がある場合は前営業日） 最大2.3営業日 ・第一次提出：1.4営業日(水曜日AM@月末最終木曜週) ・レビュー・指摘反映：0.9営業日(木曜日AM11時@月末最終木曜週まで) ※「木曜PM以降に修正が必要となった場合」及び「AM11時までに修正が完了しない場合」、プロジェクト側で巻き取っていただく | P22: 有(メール) レビューバック反映も実施する | Q22: 作業ファイルを指定フォルダーに格納してメールにて提出報告 | R22: 依頼元：指定なし 内部処理：納品物のみ保存、期間は指定なし | S22: 手動 | T22: 「レビュー反映後の納品物を格納」又は「確認完了メール受領」をもって完了とする | U22: 〇 | V22: × | W22: Technology | X22: 桑崎さん（norimi.kuwasaki） | Z22: サービス停止 | AA22: 43886 | AB22: ー | AC22: FY24以前 | AD22: ー | AI22: ー | AJ22: ー | AK22: ー | AL22: ー | AM22: 45674 | AN22: 2020年2月25日より開始 (対象レコードは万単位) 2022/7月にて業務終了 | AO22: - | AS22: (サービス停止) | AT22: 9.対応不要 | AV22: 45785 | AY22: =IF(D22="受託",IF(COUNTA(B22,F22,G22:J22,Z22:AA22)=8,"OK","NG"),"確認対象外") -> NG | AZ22: =ISNUMBER(AJ22) -> FALSE | BA22: =ROW()-7 -> 15 | BB22: e
A23: =IF(Z23="サービス停止",Z23,"") -> サービス停止 | B23: A1016 | C23: =IF(B23="","-",IF(COUNTIF($B$8:B23,B23)=1,"〇","×")) -> 〇 | D23: 受託 | E23: SN_0016 | F23: 07入力・登録代行 | G23: T-Pro_RedmineID追加 | H23: T-ProのRedmineIDを登録し、ID発行メールを送信する。 | I23: 生麦 | J23: 生麦X | K23: shigeki.ohtake | L23: 無 | M23: 随時 | N23: リクエストフォーム (アサイン情報のメールを添付) | O23: 登録：2営業日(リクエストフォーム依頼の翌営業日から2営業日) 最大5営業日 ・第一次提出：2営業日 ・レビュー・指摘反映：3営業日 ※IDの作成は5営業日だが、ID発行メールは対象者別にアサイン日から5営業日以内にメールする ID登録・ID発行メール：対象者別にアサイン日から5営業日以内にメール送信できるようにIDを登録する。 | P23: 有(メール) レビューバック反映も実施する 無 (但し、不備があった場合はメールでの指摘有り。反映も実施する。) | Q23: 作業ファイルを指定フォルダーに格納してメールにて提出報告 PJTアサイン対象者本人にID発行メールを送信 | R23: 過去３カ月もしくは過去３回分を保持。(2022/02/24確認リストにて依頼元了承) | S23: 手動 | T23: 作業完了およびレビュー反映をもって完了とする ※ID発行メールは対象者別にアサイン日から5営業日以内にメールし完了とする | U23: 〇 | V23: × | W23: Technology | X23: 王さん（dan.wang） 桑崎さん（norimi.kuwasaki） | Z23: =IF(AC23="",IF(AA23="","",IF(TODAY()>=AA23,"サービス開始",IF(TODAY()<AA23,"本稼働前",""))),IF(TODAY()>=AC23,"サービス停止",IF(AA23="","",IF(TODAY()>=AA23,"サービス開始",IF(TODAY()<AA23,"本稼働前",""))))) -> サービス停止 | AA23: 43886 | AB23: ー | AC23: 45970 | AD23: ー | AG23: T-Pro_RedmineID追加 | AI23: Technology | AJ23: 1 | AK23: ー | AL23: ー | AM23: 45674 | AN23: 2025/10/7：サービス終了。WDMの更新未対応であったため、サービス停止に変更 2020年2月25日より開始 2020年9月より運用変更（依頼元からの要請） ・ID登録後の作業完了メールは不要 ・ID登録はアサイン日から5営業日以内のID発行メールに間に合うように実施することでOK ・2022・6～生麦Yから生麦Xへ業務移管 | AO23: - | AQ23: A_通常_決定(登録可) | AS23: 登録済_本登録 | AT23: 4b.本登録_計測方法確定(FY24以前) | AV23: 45785 | AW23: ('25/10/7)サービス停止に変更 | AY23: =IF(D23="受託",IF(COUNTA(B23,F23,G23:J23,Z23:AA23)=8,"OK","NG"),"確認対象外") -> OK | AZ23: =ISNUMBER(AJ23) -> TRUE | BA23: =ROW()-7 -> 16 | BB23: e
A24: =IF(Z24="サービス停止",Z24,"") | B24: A1017 | C24: =IF(B24="","-",IF(COUNTIF($B$8:B24,B24)=1,"〇","×")) -> 〇 | D24: 受託 | E24: SN_0017 | F24: 01調査・結果纏め | G24: HPS_教育・大学ニュース関連配信作業 | H24: HPS用の教育・大学ニュース関連記事を検索し配信する作業 | I24: 生麦 | J24: 生麦Y | K24: atsushi.b.yamamoto | L24: 無 | M24: 週次 | N24: 期日が到来したら作業を開始する （作業トリガー：月曜日、祝日の場合は次営業日） | O24: 検索：2営業日 最大3営業日（以下の曜日で、祝日がある場合は次営業日） ・第一次提出：2営業日（月曜日～火曜日） ・レビュー・指摘反映・ ニュース配信：1営業日（水曜日） | P24: 有(メール) 作業ファイル・配信メールテキスト本文を確認し、指摘事項をメール返信にてご連絡いただく | Q24: 作業ファイル・配信用メールテキスト本文を、指定フォルダに格納して、メールにて提出報告 | R24: 3か月 ※2022.4.15確認済 | S24: 手動 | T24: 「ニュース配信」をもって完了とする | U24: × | V24: × | W24: HPS | X24: 今井さん（shingo.imai） | Z24: =IF(AC24="",IF(AA24="","",IF(TODAY()>=AA24,"サービス開始",IF(TODAY()<AA24,"本稼働前",""))),IF(TODAY()>=AC24,"サービス停止",IF(AA24="","",IF(TODAY()>=AA24,"サービス開始",IF(TODAY()<AA24,"本稼働前",""))))) -> サービス開始 | AA24: 43920 | AB24: ー | AI24: Technology | AJ24: 1 | AK24: ー | AL24: ー | AM24: 45674 | AN24: 2020年3月30日より開始 2020年4月6日より運用変更（依頼元との認識違いによりマニュアル等変更必要） ・第一次提出：2営業日 ・レビュー・指摘反映・ ニュース配信：1営業日 →第一次提出時にレビュー依頼なしでニュース配信 に変更 2024/6/17：依頼元担当者が「大久保さん（chikara.ohkubo）」から「今井さん（shingo.imai）」変更。 2024/7/1：担当SV変更＞emiko.maeyama ➡ atsushi.b.yamamoto | AO24: - | AQ24: A_通常_決定(登録可) | AS24: 登録済_本登録 | AT24: 4b.本登録_計測方法確定(FY24以前) | AV24: 45785 | AY24: =IF(D24="受託",IF(COUNTA(B24,F24,G24:J24,Z24:AA24)=8,"OK","NG"),"確認対象外") -> OK | AZ24: =ISNUMBER(AJ24) -> TRUE | BA24: =ROW()-7 -> 17 | BB24: e
A25: =IF(Z25="サービス停止",Z25,"") -> サービス停止 | C25: =IF(B25="","-",IF(COUNTIF($B$8:B25,B25)=1,"〇","×")) -> - | D25: 受託 | E25: SN_0018 | G25: Digital_マイナポレスポンシブ | H25: Digitalの次期マイナポ再構築として、レスポンシブ対応 | I25: 生麦 | K25: hiroshi.a.harashima | L25: 無 | M25: 随時 | N25: 設計書・モック等必要ファイルを指定フォルダに格納のうえ、Teamsにてメンションいただく | O25: 提示スケジュールにもとづき対応とする。納期遅延の見込みが発生した場合は、至急相談のうえ調整させていただく。 | P25: レビュー結果一覧に結果を記載いただき、指定フォルダに格納して、Teamsメンションにて返信いただく | Q25: レスポンシブ化済みHTMLファイル/レビューチェックシート/テスト結果一覧を、指定フォルダに格納して、Teamsメンションにて提出報告 | S25: 手動 | T25: レビュー結果一覧で指摘なしの旨のレビューバックをもって完了とする | U25: 〇 | V25: × | W25: Digital | X25: 内田さん（yuki.uchida） 清水さん（ryoichi.shimizu） 劉さん（dongqing.liu） | Z25: サービス停止 | AA25: 43941 | AB25: ー | AC25: FY24以前 | AD25: ー | AI25: ー | AJ25: ー | AK25: ー | AL25: ー | AM25: 45674 | AN25: 2020年4月20日より開始 スケジュール・作業量は、依頼元スケジュールにより、変動することがある。 また、週次で依頼元と状況確認。 | AO25: - | AS25: (サービス停止) | AT25: 9.対応不要 | AV25: 45785 | AY25: =IF(D25="受託",IF(COUNTA(B25,F25,G25:J25,Z25:AA25)=8,"OK","NG"),"確認対象外") -> NG | AZ25: =ISNUMBER(AJ25) -> FALSE | BA25: =ROW()-7 -> 18 | BB25: e
A26: =IF(Z26="サービス停止",Z26,"") -> サービス停止 | B26: A1019 | C26: =IF(B26="","-",IF(COUNTIF($B$8:B26,B26)=1,"〇","×")) -> 〇 | D26: 受託 | E26: SN_0019 | F26: 01調査・結果纏め | G26: 人事異動・メディアリリース情報チェック | H26: 人事異動・メディアリリースニュース関連記事を検索し配信する作業 | I26: 共通 | J26: 生麦Y 中津Y | K26: emiko.maeyama | L26: 無 | M26: 週次 | N26: 期日が到来したら作業を開始する （作業トリガー：月曜日、祝日の場合は次営業日） | O26: 検索：3営業日 （以下の曜日で、祝日がある場合は次営業日） ・第一次提出：3営業日（月曜日～水曜日） | P26: 無 (但し、入力不備があった場合はメールでの指摘有り) | Q26: 作業ファイルを、メールに添付して提出報告 | R26: 3か月 ※2022.4.15確認済 | S26: 手動 | T26: メール配信連絡をもって完了とする | U26: 〇 | V26: × | W26: RES | X26: 竹村さん（ryo.takemura） 吉松さん（yuriko.yoshimatsu） | Z26: サービス停止 | AA26: 43990 | AB26: ー | AC26: FY24以前 | AD26: ー | AI26: ー | AJ26: ー | AK26: ー | AL26: ー | AM26: 45674 | AN26: 2020年6月8日より開始 2024/2/29：生麦Yに加え、中津Yも参画 2024/4/22：チーム移管に伴いサービス停止 | AO26: - | AS26: (サービス停止) | AT26: 9.対応不要 | AV26: 45785 | AY26: =IF(D26="受託",IF(COUNTA(B26,F26,G26:J26,Z26:AA26)=8,"OK","NG"),"確認対象外") -> OK | AZ26: =ISNUMBER(AJ26) -> FALSE | BA26: =ROW()-7 -> 19 | BB26: e
A27: =IF(Z27="サービス停止",Z27,"") | B27: A1020 | C27: =IF(B27="","-",IF(COUNTIF($B$8:B27,B27)=1,"〇","×")) -> 〇 | D27: 受託 | E27: SN_0020 | F27: 91TBD_仮登録 | G27: RES_SharePointデータ移行 | H27: RESの日東電工PJTが持つ複数Sharepoint間でのファイル・フォルダ移行作業 | I27: 生麦 | J27: 生麦X | K27: shigeki.ohtake | L27: 無 | M27: 随時 | N27: リクエストフォーム | O27: 2週間 | P27: 有 指摘があれば、指摘事項と共に対応が必要か、メール返信にてご連絡いただく | Q27: 作業結果をメールに添付して報告 | R27: 依頼元：指定なし | S27: 手動 | T27: 作業結果を添付したメールの配信を以て完了 | U27: 〇 | V27: × | W27: RES | X27: 月岡さん（ryosuke.tsukioka） NTD.PMO.Adm@accenture.com | Z27: =IF(AC27="",IF(AA27="","",IF(TODAY()>=AA27,"サービス開始",IF(TODAY()<AA27,"本稼働前",""))),IF(TODAY()>=AC27,"サービス停止",IF(AA27="","",IF(TODAY()>=AA27,"サービス開始",IF(TODAY()<AA27,"本稼働前",""))))) -> サービス開始 | AA27: 43997 | AB27: ー | AG27: RES_SharePointデータ移行 | AI27: Technology | AJ27: 1 | AK27: ー | AL27: ー | AM27: 45674 | AN27: サービス開始後依頼なし | AO27: - | AQ27: C_通常_未定(仮登録可) | AS27: 登録済_仮登録 | AT27: 2b.仮登録_計測方法未定(FY24以前) | AV27: 45785 | AY27: =IF(D27="受託",IF(COUNTA(B27,F27,G27:J27,Z27:AA27)=8,"OK","NG"),"確認対象外") -> OK | AZ27: =ISNUMBER(AJ27) -> TRUE | BA27: =ROW()-7 -> 20 | BB27: e
A28: =IF(Z28="サービス停止",Z28,"") -> サービス停止 | C28: =IF(B28="","-",IF(COUNTIF($B$8:B28,B28)=1,"〇","×")) -> - | D28: 受託 | E28: SN_0021 | G28: PRD_人事異動・組織改編情報チェック(優先50社) | H28: PRDのクライアント50社の人事異動情報・組織改編情報を検索し、配信する作業 | I28: 生麦 | K28: akiko.a.hirano | L28: 無 | M28: 週次 | N28: 期日が到来したら作業を開始する (作業トリガー: 毎週第一営業日) | O28: 最大6営業日 | P28: 無 (但し、入力不備があった場合はメールでの指摘有り) | Q28: 作業ファイルをメールに添付して報告 | S28: 手動 | T28: 作業ファイルを添付したメールの配信を以て完了 | U28: 〇 | V28: × | W28: PRD | X28: 山口さん（kunishige.yamaguchi） | Z28: サービス停止 | AA28: 43990 | AB28: ー | AC28: FY24以前 | AD28: ー | AI28: ー | AJ28: ー | AK28: ー | AL28: ー | AM28: 45674 | AN28: 2020年6月8日より開始 SN_0025に置き換え | AO28: - | AS28: (サービス停止) | AT28: 9.対応不要 | AV28: 45785 | AY28: =IF(D28="受託",IF(COUNTA(B28,F28,G28:J28,Z28:AA28)=8,"OK","NG"),"確認対象外") -> NG | AZ28: =ISNUMBER(AJ28) -> FALSE | BA28: =ROW()-7 -> 21 | BB28: e
A29: =IF(Z29="サービス停止",Z29,"") | B29: A1022 | C29: =IF(B29="","-",IF(COUNTIF($B$8:B29,B29)=1,"〇","×")) -> 〇 | D29: 受託 | E29: SN_0022 | F29: 03サニタイズ編集 | G29: RES_KXサニタイズ代行 | H29: RESから依頼された日東電工PJTドキュメントをKXに登録可能な フォーマットに修正する。 | I29: 生麦 | J29: TF | K29: tomoyuki.a.hishiki | L29: 無 | M29: 随時 | N29: リクエストフォーム | O29: 一次提出：3週間 納期:4週間 | P29: 有(メール) レビューバック反映も実施する | Q29: SharePoint上の個別フォルダ (権限設定有り) | S29: 手動 | T29: ・アップロード完了連絡 | U29: 〇 | V29: × | W29: AS_RES | X29: 吉松さん（yuriko.yoshimatsu） | Z29: =IF(AC29="",IF(AA29="","",IF(TODAY()>=AA29,"サービス開始",IF(TODAY()<AA29,"本稼働前",""))),IF(TODAY()>=AC29,"サービス停止",IF(AA29="","",IF(TODAY()>=AA29,"サービス開始",IF(TODAY()<AA29,"本稼働前",""))))) -> サービス開始 | AA29: 44004 | AB29: ー | AG29: RES_KXサニタイズ代行 | AH29: ①A1023 ②A1022 | AI29: Technology | AJ29: 1 | AK29: ー | AL29: ー | AM29: 45674 | AN29: 2020年6月22日より開始 2021/10/1より、担当SV変更：Maeyama→（Takahashi,Airi)→Ito 2022/05/15より、担当SV変更：Ito→Watanabe 2023/3/1より、担当SV変更：koji.c.watanabe→hiroyuki.hishiki | AO29: - | AQ29: A_通常_決定(登録可) | AS29: 登録済_本登録 | AT29: 4b.本登録_計測方法確定(FY24以前) | AV29: 45785 | AY29: =IF(D29="受託",IF(COUNTA(B29,F29,G29:J29,Z29:AA29)=8,"OK","NG"),"確認対象外") -> OK | AZ29: =ISNUMBER(AJ29) -> TRUE | BA29: =ROW()-7 -> 22 | BB29: e
A30: =IF(Z30="サービス停止",Z30,"") | B30: A1023 | C30: =IF(B30="","-",IF(COUNTIF($B$8:B30,B30)=1,"〇","×")) -> 〇 | D30: 受託 | E30: SN_0023 | F30: 02サニタイズ編集要件 | G30: RES_WordList作成作業(KXサニタイズ代行) | H30: RESから依頼された日東電工PJTドキュメントの、KXサニタイズに必要なWordListを作成する。 | I30: 生麦 | J30: TF | K30: tomoyuki.a.hishiki | L30: 無 | M30: 随時 | N30: リクエストフォーム | O30: 一次提出：3週間 納期:4週間 | P30: 有(メール) レビューバック反映も実施する | Q30: SharePoint上の個別フォルダ (権限設定有り) | S30: 手動 | T30: ・アップロード完了連絡 | U30: 〇 | V30: × | W30: AS_RES | X30: 吉松さん（yuriko.yoshimatsu） | Z30: =IF(AC30="",IF(AA30="","",IF(TODAY()>=AA30,"サービス開始",IF(TODAY()<AA30,"本稼働前",""))),IF(TODAY()>=AC30,"サービス停止",IF(AA30="","",IF(TODAY()>=AA30,"サービス開始",IF(TODAY()<AA30,"本稼働前",""))))) -> サービス開始 | AA30: 44004 | AB30: ー | AG30: RES_KXサニタイズ代行 | AH30: ①A1023 ②A1022 | AI30: Technology | AJ30: 1 | AK30: ー | AL30: ー | AM30: 45674 | AN30: 基本的に、0022と0023が別に依頼されることはないが、作業は分かれるためそれぞれサービス管理番号を設定。 2021/10/1より、担当SV変更：Maeyama→（Takahashi,Airi)→Ito 2022/05/15より、担当SV変更：Ito→Watanabe 2023/3/1より、担当SV変更：koji.c.watanabe→hiroyuki.hishiki | AO30: - | AQ30: A_通常_決定(登録可) | AS30: 登録済_本登録 | AT30: 4b.本登録_計測方法確定(FY24以前) | AV30: 45785 | AY30: =IF(D30="受託",IF(COUNTA(B30,F30,G30:J30,Z30:AA30)=8,"OK","NG"),"確認対象外") -> OK | AZ30: =ISNUMBER(AJ30) -> TRUE | BA30: =ROW()-7 -> 23 | BB30: e
A31: =IF(Z31="サービス停止",Z31,"") -> サービス停止 | B31: A1024 | C31: =IF(B31="","-",IF(COUNTIF($B$8:B31,B31)=1,"〇","×")) -> 〇 | D31: 受託 | E31: SN_0024 | F31: 10回答作成 | G31: Digital_マイナポWeb問合せ回答 | H31: 国民からマイナポータルへ届く、お問い合わせへの回答を作成する業務 | I31: 生麦 | J31: 生麦X | K31: shigeki.ohtake | L31: 無 | M31: 日次 | N31: 定常作業のため、無し (毎日朝9:30に、当日の作業量を確認) | O31: 問い合わせ一覧作成：当日10:00まで 回答入力: 当日11:00まで 回答案作成: 当日15:00まで | P31: 有 提出した翌日にいただける想定 | Q31: 依頼元とのTeams上の個別フォルダ | R31: 依頼元：指定なし 内部処理：納品物のみ保存、期間は指定なし | S31: 手動 | T31: Teamsにて連絡 | U31: × | V31: × | W31: Digital | X31: 宮嶋さん（tatsuya.miyajima） 安部さん（yoshiaki.abe） | Z31: =IF(AC31="",IF(AA31="","",IF(TODAY()>=AA31,"サービス開始",IF(TODAY()<AA31,"本稼働前",""))),IF(TODAY()>=AC31,"サービス停止",IF(AA31="","",IF(TODAY()>=AA31,"サービス開始",IF(TODAY()<AA31,"本稼働前",""))))) -> サービス停止 | AA31: 44032 | AB31: ー | AC31: 45291 | AD31: ー | AG31: Digital_マイナポWeb問合せ回答 | AI31: ー | AJ31: ー | AK31: ー | AL31: ー | AM31: 45674 | AN31: 2020年7月20日より開始 | AO31: - | AS31: (サービス停止) | AT31: 9.対応不要 | AV31: 45785 | AY31: =IF(D31="受託",IF(COUNTA(B31,F31,G31:J31,Z31:AA31)=8,"OK","NG"),"確認対象外") -> OK | AZ31: =ISNUMBER(AJ31) -> FALSE | BA31: =ROW()-7 -> 24 | BB31: e
A32: =IF(Z32="サービス停止",Z32,"") | B32: A1025 | C32: =IF(B32="","-",IF(COUNTIF($B$8:B32,B32)=1,"〇","×")) -> 〇 | D32: 受託 | E32: SN_0025 | F32: 01調査・結果纏め | G32: 人事異動・組織改編情報チェック(自動化) | H32: PRDのクライアント459社の人事異動情報・組織改編情報を自動化ツール(UiPath)を使用して検索し、一覧にまとめて配信する作業 | I32: 生麦 | J32: 生麦X | K32: shigeki.ohtake | L32: 無 | M32: 週次 | N32: 期日が到来したら作業を開始する (作業トリガー: 毎週第一営業日) | O32: 最大6営業日 | P32: 無 (但し、入力不備があった場合はメールでの指摘有り) | Q32: 作業ファイルをメールに添付して報告 | R32: 依頼元：指定なし 内部処理：納品物のみ保存、期間は指定なし | S32: 手動 | T32: 作業ファイルを添付したTeamsの配信を以て完了 | U32: 〇 | V32: × | W32: PRD | X32: 山口さん（kunishige.yamaguchi） | Z32: =IF(AC32="",IF(AA32="","",IF(TODAY()>=AA32,"サービス開始",IF(TODAY()<AA32,"本稼働前",""))),IF(TODAY()>=AC32,"サービス停止",IF(AA32="","",IF(TODAY()>=AA32,"サービス開始",IF(TODAY()<AA32,"本稼働前",""))))) -> サービス開始 | AA32: 44075 | AB32: ー | AG32: 人事異動・組織改編情報チェック(自動化) | AI32: Client Service Group | AJ32: 1 | AK32: ー | AL32: ー | AM32: 45674 | AN32: SN_0021の自動化後の案件(置き換え) 2020年9月中旬のサービス開始を想定 | AO32: - | AQ32: A_通常_決定(登録可) | AS32: 登録済_本登録 | AT32: 4b.本登録_計測方法確定(FY24以前) | AV32: 45785 | AY32: =IF(D32="受託",IF(COUNTA(B32,F32,G32:J32,Z32:AA32)=8,"OK","NG"),"確認対象外") -> OK | AZ32: =ISNUMBER(AJ32) -> TRUE | BA32: =ROW()-7 -> 25 | BB32: e
A33: =IF(Z33="サービス停止",Z33,"") -> サービス停止 | C33: =IF(B33="","-",IF(COUNTIF($B$8:B33,B33)=1,"〇","×")) -> - | D33: 受託 | E33: SN_0026 | G33: Operations_ファミ通Collections登録 | H33: Operations本部内で送信されているファミリー通信(ファミ通)をCollectionsに登録する作業 | I33: 生麦 | K33: shigeki.ohtake | L33: 無 | M33: 隔週 | N33: リクエストフォーム | O33: リクエストフォームでの依頼から5営業日 （隔週金曜に依頼→翌週金曜が納期） | P33: 無 (但し、入力不備があった場合はメールでの指摘有り) | Q33: 提出はなし (Collectionsに登録することが業務) | R33: 依頼元：指定なし 内部処理：納品物のみ保存、期間は指定なし | S33: 手動 | T33: メールでの完了報告 | U33: × | V33: 〇 Collectionsへのアクセス権限付与依頼が必要(メール) | W33: Operations | X33: 遠藤さん（mai.endo） | Z33: サービス停止 | AA33: 44043 | AB33: ー | AC33: FY24以前 | AD33: ー | AI33: ー | AJ33: ー | AK33: ー | AL33: ー | AM33: 45674 | AN33: 2020/7/31より開始 2022/6より依頼元サイト閉鎖のため、終了 | AO33: - | AS33: (サービス停止) | AT33: 9.対応不要 | AV33: 45785 | AY33: =IF(D33="受託",IF(COUNTA(B33,F33,G33:J33,Z33:AA33)=8,"OK","NG"),"確認対象外") -> NG | AZ33: =ISNUMBER(AJ33) -> FALSE | BA33: =ROW()-7 -> 26 | BB33: e
A34: =IF(Z34="サービス停止",Z34,"") -> サービス停止 | B34: A1027 | C34: =IF(B34="","-",IF(COUNTIF($B$8:B34,B34)=1,"〇","×")) -> 〇 | D34: 受託 | E34: SN_0027 | F34: 06連絡・確認代行 | G34: Japan BEST PJT依頼対応 | H34: 四半期ごとに各組織から選出されるJapan BEST PJTのサニタイズを実施するにあたり、各PJTへの資料提出依頼、受領資料チェック、Kxinfo更新依頼、サニタイズ依頼を行う作業 | I34: 生麦 | J34: 生麦Y | K34: emiko.maeyama | L34: 無 | M34: 四半期 | N34: 各組織でベストプロジェクト選定が完了した段階で選定メールが転送され、作業開始する。 | O34: ※各アクションに厳密な納期設定はないので、状況に応じて順次対応していく。下記は目安。 ・資料提出依頼（初回）：選定メール転送から2営業日 ・資料提出依頼（リマインド）：初回提出期限到来から3営業日 ・受領資料チェック・対応方針連絡：資料受領から2営業日 ・KXinfo更新依頼：OppID受領から2営業日 ・サニタイズ依頼：上記完了から2営業日以内 | P34: 有 (対応に関してコメントあれば都度Teamsで指摘あり) | Q34: 提出はなし (各種メール送信と管理Excelの更新が成果となる) | R34: Q毎単位で、完全に対応完了したら削除可（削除時期はサテライトで決定） ※2022/2/21確認済 | S34: 手動 | T34: Teamsでの完了報告 | U34: 〇 | V34: × | W34: CF_KM | X34: 西田さん（kumiko.nishida） Japan.KM@accenture.com | Z34: サービス停止 | AA34: 44174 | AB34: ー | AC34: FY24以前 | AD34: ー | AI34: ー | AJ34: ー | AK34: ー | AL34: ー | AM34: 45674 | AN34: 担当者はaceture_satellite_KX、運用チームTeamsへの参加が必要。 2020/9～のQ1はテスト運用 2020/12～のQ2から本稼働 2023/5末Q3分まで対応し、2023/6以降Q4依頼分の対応は「A0015」のサービスで対応予定。 2024/2/6 サービス停止、A0015に移管 | AO34: 依頼済(担当:SSD/アサインT) | AP34: 25/1/27_停止依頼 | AS34: (サービス停止) | AT34: 9.対応不要 | AV34: 45785 | AY34: =IF(D34="受託",IF(COUNTA(B34,F34,G34:J34,Z34:AA34)=8,"OK","NG"),"確認対象外") -> OK | AZ34: =ISNUMBER(AJ34) -> FALSE | BA34: =ROW()-7 -> 27 | BB34: e
A35: =IF(Z35="サービス停止",Z35,"") -> サービス停止 | B35: A1028 | C35: =IF(B35="","-",IF(COUNTIF($B$8:B35,B35)=1,"〇","×")) -> 〇 | D35: 受託 | E35: SN_0028 | F35: 08データ集計・整形 | G35: Digital_マイナポサイトデータ分析(データ加工) | H35: 内閣府のマイナンバーポータルPJT内で行っている、国民・団体等のマイナンバーポータル利用状況について、分析のインプットとなるデータ取得・加工をする業務。 | I35: 生麦 | J35: 生麦Y | K35: atsushi.b.yamamoto | L35: 無 | M35: 月次 | N35: 期日が到来したら作業を開始する （作業トリガー：毎月第一営業日） ※一部依頼元提供データあり | O35: 4営業日 | P35: 無 (但し、入力不備があった場合はTeamsでの指摘有り) | Q35: 依頼元とのTeams上の個別フォルダ | R35: 3か月 | S35: 手動 | T35: Teamsにて完了連絡 | U35: × | V35: × | W35: Operations | X35: 六郷さん／yushi.rokugo@imjp.co.jp 隈本さん／shota.a.kumamoto@imjp.co.jp | Z35: =IF(AC35="",IF(AA35="","",IF(TODAY()>=AA35,"サービス開始",IF(TODAY()<AA35,"本稼働前",""))),IF(TODAY()>=AC35,"サービス停止",IF(AA35="","",IF(TODAY()>=AA35,"サービス開始",IF(TODAY()<AA35,"本稼働前",""))))) -> サービス停止 | AA35: 44112 | AB35: ー | AC35: 46022 | AD35: ー | AG35: Digital_マイナポサイトデータ分析 | AH35: 1 | AI35: Operations | AJ35: 1 | AK35: ー | AL35: ー | AM35: 45674 | AN35: 2020/10/8より開始（9月度分報告から） 2024/7/1：担当SV変更＞emiko.maeyama ➡ atsushi.b.yamamoto 2025/12/31：サービス停止 | AO35: 完了(担当:運用企画-Tech) | AP35: 26-02-02_Li_サービス停止 | AQ35: A_通常_決定(登録可) | AS35: 登録済_本登録 | AT35: 4b.本登録_計測方法確定(FY24以前) | AV35: 45785 | AY35: =IF(D35="受託",IF(COUNTA(B35,F35,G35:J35,Z35:AA35)=8,"OK","NG"),"確認対象外") -> OK | AZ35: =ISNUMBER(AJ35) -> TRUE | BA35: =ROW()-7 -> 28 | BB35: e
A36: =IF(Z36="サービス停止",Z36,"") -> サービス停止 | B36: A1029 | C36: =IF(B36="","-",IF(COUNTIF($B$8:B36,B36)=1,"〇","×")) -> 〇 | D36: 受託 | E36: SN_0029 | F36: 01調査・結果纏め | G36: Security_脆弱性情報収集 | H36: 特定OS・ミドルウェア・ソフトウェアに関する脆弱性情報を検索し、必要情報をまとめる作業 | I36: 生麦 | J36: 生麦Z | K36: hiroshi.a.harashima | L36: 無 | M36: 随時 | N36: 依頼元が指定のフォルダに格納し、メールにて依頼 | O36: 依頼元の指示による ※週次(週の最終営業日まで)で提出し、50件/週を目安 ただし、提出タイミングは、月の第1週が5営業日未満の場合は、翌週の最終営業日まで。月次分の最終提出は、月末最終営業日まで。 →依頼件数により、納期見積もり・調整 | P36: 有(メール) レビューバック反映も実施する | Q36: 作業ファイルをアップロードフォルダに格納 | R36: 依頼元が依頼元用フォルダに格納後。 基本は各製品毎で管理し、各製品で数が異なるため期限も異なる。 | S36: 手動 | T36: メールにて完了報告 →Teamsにて完了報告 | U36: × | V36: × | W36: Security | X36: 増田さん（so.masuda） 酒井さん（kenta.sakai） 佐藤さん（tatsuki.sato） | Z36: サービス停止 | AA36: 44116 | AB36: ー | AC36: FY24以前 | AD36: ー | AI36: ー | AJ36: ー | AK36: ー | AL36: ー | AM36: 45674 | AN36: 2020/10/12より開始 2024/3/13 サービス停止 | AO36: - | AS36: (サービス停止) | AT36: 9.対応不要 | AV36: 45785 | AY36: =IF(D36="受託",IF(COUNTA(B36,F36,G36:J36,Z36:AA36)=8,"OK","NG"),"確認対象外") -> OK | AZ36: =ISNUMBER(AJ36) -> FALSE | BA36: =ROW()-7 -> 29 | BB36: e
A37: =IF(Z37="サービス停止",Z37,"") -> サービス停止 | C37: =IF(B37="","-",IF(COUNTIF($B$8:B37,B37)=1,"〇","×")) -> - | D37: 受託 | E37: ST_0001 | G37: Offering_Wordlist作成作業(KXサニタイズ代行) | H37: SN_0004と同じ | I37: 立川 | K37: nobuyuki.ushikubo | L37: 無 | M37: 随時 | N37: 依頼元が指定のフォルダに格納し、メールにて依頼 | O37: Wordlist作成・サニタイズ作業合わせて 5営業日 | P37: 有(Teams) レビューバック反映も実施する | Q37: SharePoint上の個別フォルダ (権限設定有り) | S37: 自動 | T37: ステータスを更新すると自動でKMにメール通知 | U37: 〇 | V37: 〇 | W37: CF_KM | X37: Kumai, Hitomi | Z37: サービス停止 | AA37: 44172 | AB37: ー | AC37: FY24以前 | AD37: ー | AI37: ー | AJ37: ー | AK37: ー | AL37: ー | AM37: 45674 | AN37: KMのSharePoint、KMリクエストフォーム(ステータス更新のため）への権限設定が必要 | AO37: - | AS37: (サービス停止) | AT37: 9.対応不要 | AV37: 45785 | AY37: =IF(D37="受託",IF(COUNTA(B37,F37,G37:J37,Z37:AA37)=8,"OK","NG"),"確認対象外") -> NG | AZ37: =ISNUMBER(AJ37) -> FALSE | BA37: =ROW()-7 -> 30 | BB37: e
A38: =IF(Z38="サービス停止",Z38,"") -> サービス停止 | C38: =IF(B38="","-",IF(COUNTIF($B$8:B38,B38)=1,"〇","×")) -> - | D38: 受託 | E38: ST_0002 | G38: Offering_KXサニタイズ代行 | H38: SN_0003と同じ | I38: 立川 | K38: nobuyuki.ushikubo | L38: 無 | M38: 随時 | N38: 依頼元が指定のフォルダに格納し、メールにて依頼 | O38: Wordlist作成・サニタイズ作業合わせて 5営業日 | P38: 有(Teams) レビューバック反映も実施する | Q38: SharePoint上の個別フォルダ (権限設定有り) | S38: 自動 | T38: ステータスを更新すると自動でKMにメール通知 | U38: 〇 | V38: 〇 | W38: CF_KM | X38: Kumai, Hitomi | Z38: サービス停止 | AA38: 44172 | AB38: ー | AC38: FY24以前 | AD38: ー | AI38: ー | AJ38: ー | AK38: ー | AL38: ー | AM38: 45674 | AN38: KMのSharePoint、KMリクエストフォーム(ステータス更新のため）への権限設定が必要 | AO38: - | AS38: (サービス停止) | AT38: 9.対応不要 | AV38: 45785 | AY38: =IF(D38="受託",IF(COUNTA(B38,F38,G38:J38,Z38:AA38)=8,"OK","NG"),"確認対象外") -> NG | AZ38: =ISNUMBER(AJ38) -> FALSE | BA38: =ROW()-7 -> 31 | BB38: e
A39: =IF(Z39="サービス停止",Z39,"") -> サービス停止 | B39: A2003 | C39: =IF(B39="","-",IF(COUNTIF($B$8:B39,B39)=1,"〇","×")) -> 〇 | D39: 受託 | E39: ST_0003 | F39: 01調査・結果纏め | G39: Security_脆弱性情報収集 | H39: A1029と同じ | I39: 立川 | J39: 立川Z | K39: hiroshi.a.harashima | L39: 無 | M39: 随時 | N39: teamsにて依頼 | O39: 依頼件数により、納期見積もり・調整 | P39: 有(Teams) レビューバック反映も実施する | Q39: ファイルを共有フォルダへアップロード | R39: SN_0029と同じ | S39: 手動 | T39: Teamsにて生麦へ報告 | U39: × | V39: × | Z39: サービス停止 | AA39: 44116 | AB39: ー | AC39: FY24以前 | AD39: ー | AI39: ー | AJ39: ー | AK39: ー | AL39: ー | AM39: 45674 | AN39: 2021年10月より、担当SV変更：Ito→Harashima 2024/3/13 サービス停止 | AO39: - | AS39: (サービス停止) | AT39: 9.対応不要 | AV39: 45785 | AY39: =IF(D39="受託",IF(COUNTA(B39,F39,G39:J39,Z39:AA39)=8,"OK","NG"),"確認対象外") -> OK | AZ39: =ISNUMBER(AJ39) -> FALSE | BA39: =ROW()-7 -> 32 | BB39: e
A40: =IF(Z40="サービス停止",Z40,"") -> サービス停止 | B40: A1030 | C40: =IF(B40="","-",IF(COUNTIF($B$8:B40,B40)=1,"〇","×")) -> 〇 | D40: 受託 | E40: SN_0030 | F40: 91TBD_仮登録 | G40: Interactive_マイナポUIUX改善業務 | H40: マイナンバーポータルPJTの使い勝手の改善として、プロトタイプを基にWebページを作成 2021/1/15：以下に変更し、上記Webページ作成なし ①レスポンシブ対応：過去の「SN_0018 Digital_マイナポレスポンシブ」対応と同様 ②HTMLテスト：PJTで作成したHTMLのテスト ③マイナポ―タルマニュアルページ更新：過去の「SN_0011 Digital_マニュアルWeb化」対応と同様 →プロジェクトに合わせた対応となり、都度内容・規模が変わる。 | I40: 生麦 | J40: 生麦Z | K40: hiroshi.a.harashima | L40: 無 | M40: 随時 | N40: ①：（未定） ②：（未定） ③：②と同様 | O40: ①（未定） ②（未定） ③依頼ごとに設定 | P40: 【未定】 ① ② ③有(Teams) レビューバック反映も実施する | Q40: 【未定分あり】 ① ② ③依頼元用のアップロードフォルダ | S40: 手動 | T40: Teamsにて完了連絡 ① ② ③日々格納し報告 →Teamsにて完了連絡 | U40: 〇 | V40: × | W40: Interactive | X40: ①レスポンシブ対応：未定 ②HTMLテスト：未定 ③マイナポ―タルマニュアルページ更新： ・Matsuda, Ryuji ・その他各案件ごとの開発チームご担当者 | Z40: =IF(AC40="",IF(AA40="","",IF(TODAY()>=AA40,"サービス開始",IF(TODAY()<AA40,"本稼働前",""))),IF(TODAY()>=AC40,"サービス停止",IF(AA40="","",IF(TODAY()>=AA40,"サービス開始",IF(TODAY()<AA40,"本稼働前",""))))) -> サービス停止 | AA40: 44228 | AB40: ー | AC40: 46112 | AD40: ー | AI40: Song | AJ40: 1 | AK40: ー | AL40: ー | AM40: 45674 | AN40: ①レスポンシブ対応：未定 ②マニュアルページ更新＋テスト：本稼働2021/3/1開始 ③マイナポ―タルマニュアルページ更新：本稼働2021/2/1～2/26 →2022年もマニュアルページ更新を継続 2022/04/08 ①、②の対応はなし。③のマニュアルページ更新のみ対応中 2026/03/31:サービス停止 | AO40: 完了(担当:運用企画-Tech) | AP40: 2026/04/07_Li_WDM更新済み 2026/03/31_停止依頼 | AQ40: C_通常_未定(仮登録可) | AS40: 登録済_仮登録 | AT40: 2b.仮登録_計測方法未定(FY24以前) | AV40: 45785 | AY40: =IF(D40="受託",IF(COUNTA(B40,F40,G40:J40,Z40:AA40)=8,"OK","NG"),"確認対象外") -> OK | AZ40: =ISNUMBER(AJ40) -> TRUE | BA40: =ROW()-7 -> 33 | BB40: e
A41: =IF(Z41="サービス停止",Z41,"") | B41: A1031 | C41: =IF(B41="","-",IF(COUNTIF($B$8:B41,B41)=1,"〇","×")) -> 〇 | D41: 受託 | E41: SN_0031 | F41: 05配信記事編集 | G41: I&D_Women's stories記事配信 | H41: 女性社員の活躍に関する記事原稿に基づき、Japan information site掲載用の記事作成。Teamsでの配信およびメール配信用のドラフト作成。 | I41: 生麦 | J41: 生麦X | K41: shigeki.ohtake | L41: 無 | M41: 週次 | N41: Teams | O41: 作成：3営業日(火曜公開） Teams配信・メールドラフト作成：4営業日（水曜配信/連絡） ※前週木曜日までに依頼有 ※火曜・水曜が非稼働日の場合、翌営業日へ変更 | P41: 有(Teams) レビューバック反映も実施する | Q41: ・記事作成：記事公開 ・Teams配信：該当Teamsチャネルに投稿 ・メールドラフト作成：メール送信 | R41: 依頼元：指定なし 内部処理：納品物のみ保存、期間は指定なし | S41: 手動 | T41: ・記事作成：Teamsスレッドで完了報告 ・Teams配信：Teamsスレッドで完了報告 ・メールドラフト作成：北川さんへのドラフト送信をもって完了報告とする。 | U41: × | V41: 〇 Wordpress （指定の申請書に直接記入で申請メールなし：備考欄参照） Teams （PrivateTeamsへの参加依頼が必要：備考参照) | W41: OD&KS | X41: ■記事配信 川島さん（miki.kawashima） 櫻川さん（miyako.sakuragawa） 米山さん（mizuki.yoneyama） ■Teams配信・メールドラフト送付 北川さん（akiko.kitagawa） | Z41: =IF(AC41="",IF(AA41="","",IF(TODAY()>=AA41,"サービス開始",IF(TODAY()<AA41,"本稼働前",""))),IF(TODAY()>=AC41,"サービス停止",IF(AA41="","",IF(TODAY()>=AA41,"サービス開始",IF(TODAY()<AA41,"本稼働前",""))))) -> サービス開始 | AA41: 44148 | AB41: ー | AG41: I&D_Women's stories記事配信 | AI41: 組織横断 | AJ41: 1 | AK41: ー | AL41: ー | AM41: 45674 | AN41: ■Japan information siteの「Editor」権限が必要。 下記申請フォームに入力。 https://ts.accenture.com/:x:/r/Sites/mcomjapan/_layouts/15/Doc.aspx?sourcedoc=%7B97EFB4A5-D615-4C87-B04E-09AAA524F65B%7D&file=ApplicationForm-EditingRightsForJIS_2020.xlsx&action=default&mobileredirect=true&cid=f148a7a4-b329-46fa-a3b0-6c1cb44c4d8b ■PrivateTeamsへの参加は、下記所有者へ連絡 ◎Interactive Japan All Teams 中村さん(yuki.a.nakamura) ◎Japan Technology Teams 関西事務局(Kansai_Jimukyoku@accenture.com)⇒Teamsで可能に変更2021/5/17変更 | AO41: - | AQ41: A_通常_決定(登録可) | AS41: 登録済_本登録 | AT41: 4b.本登録_計測方法確定(FY24以前) | AV41: 45785 | AY41: =IF(D41="受託",IF(COUNTA(B41,F41,G41:J41,Z41:AA41)=8,"OK","NG"),"確認対象外") -> OK | AZ41: =ISNUMBER(AJ41) -> TRUE | BA41: =ROW()-7 -> 34 | BB41: e | BC41: [1/21]AH①割合：－→100
A42: =IF(Z42="サービス停止",Z42,"") -> サービス停止 | C42: =IF(B42="","-",IF(COUNTIF($B$8:B42,B42)=1,"〇","×")) -> - | D42: 受託 | E42: ST_0004 | G42: KM_Webinar資料サニタイズ作業 | H42: Webinarにて使用した資料をKXに掲載するための編集作業(サニタイズ作業） | I42: 立川 | K42: ー | L42: 有 | M42: 週次 | N42: KM/依頼元が指定のフォルダに格納し、メールにて依頼 | O42: Wordlist作成：２営業日 サニタイズ資料提出：３営業日 | P42: ・Wordlist:有(Teams)レビューバック反映も実施する ・サニタイズ後資料：無 | Q42: ・Wordlist：該当TeamsチャネルでKMに提出 ・依頼元SharePointに格納し、メールにて完了連絡 | S42: 手動 | T42: ・Wordlist：該当TeamsチャネルでKMに提出 ・依頼元SharePointに格納し、メールにて完了連絡 | U42: 〇 | V42: 〇 | W42: KM | Z42: サービス停止 | AA42: 44112 | AB42: ー | AC42: FY24以前 | AD42: ー | AI42: ー | AJ42: ー | AK42: ー | AL42: ー | AM42: 45674 | AN42: 2020/10/8より開始（9月度分報告から） | AO42: - | AS42: (サービス停止) | AT42: 9.対応不要 | AV42: 45785 | AY42: =IF(D42="受託",IF(COUNTA(B42,F42,G42:J42,Z42:AA42)=8,"OK","NG"),"確認対象外") -> NG | AZ42: =ISNUMBER(AJ42) -> FALSE | BA42: =ROW()-7 -> 35 | BB42: e
A43: =IF(Z43="サービス停止",Z43,"") -> サービス停止 | C43: =IF(B43="","-",IF(COUNTIF($B$8:B43,B43)=1,"〇","×")) -> - | D43: 受託 | E43: ST_0005 | G43: KM_Webinar動画サニタイズ作業 | H43: Webinarにて使用した動画をKXに掲載するための編集作業(サニタイズ作業） | I43: 立川 | K43: ー | L43: 有 | M43: 週次 | N43: KMが指定のフォルダに格納し、Teamsにて依頼 | O43: 一次提出：３営業日 レビュー指摘反映：２営業日 | P43: 有(Teams) レビューバック反映も実施する | Q43: KMのSharePoint上の個別フォルダ | S43: 手動 | T43: Teamsスレッドで完了報告 | U43: 〇 | V43: 〇 | W43: KM | Z43: サービス停止 | AA43: 44112 | AB43: ー | AC43: FY24以前 | AD43: ー | AI43: ー | AJ43: ー | AK43: ー | AL43: ー | AM43: 45674 | AO43: - | AS43: (サービス停止) | AT43: 9.対応不要 | AV43: 45785 | AY43: =IF(D43="受託",IF(COUNTA(B43,F43,G43:J43,Z43:AA43)=8,"OK","NG"),"確認対象外") -> NG | AZ43: =ISNUMBER(AJ43) -> FALSE | BA43: =ROW()-7 -> 36 | BB43: e
A44: =IF(Z44="サービス停止",Z44,"") -> サービス停止 | B44: A1032 | C44: =IF(B44="","-",IF(COUNTIF($B$8:B44,B44)=1,"〇","×")) -> 〇 | D44: 受託 | E44: SN_0032 | F44: 04資料編集 | G44: Digital_マイナポサイトデータ分析(レポート作成) | H44: ※SN_0028の後続作業。 内閣府のマイナンバーポータルPJT内で行っている、国民・団体等のマイナンバーポータル利用状況について、分析レポートを作成する業務。 | I44: 生麦 | J44: 生麦Y | K44: atsushi.b.yamamoto | L44: 無 | M44: 月次 | N44: 期日が到来したら作業を開始する （作業トリガー：SN_0028作業完了後） | O44: 4営業日 | P44: 有(Teams) レビューバック反映も実施する | Q44: 依頼元とのTeams上の個別フォルダ | R44: 3か月 | S44: 手動 | T44: Teamsにて完了連絡 | U44: × | V44: × | W44: Operations | X44: 六郷さん／yushi.rokugo@imjp.co.jp 隈本さん／shota.a.kumamoto@imjp.co.jp | Z44: =IF(AC44="",IF(AA44="","",IF(TODAY()>=AA44,"サービス開始",IF(TODAY()<AA44,"本稼働前",""))),IF(TODAY()>=AC44,"サービス停止",IF(AA44="","",IF(TODAY()>=AA44,"サービス開始",IF(TODAY()<AA44,"本稼働前",""))))) -> サービス停止 | AA44: 44179 | AB44: ー | AC44: 46022 | AD44: ー | AG44: Digital_マイナポサイトデータ分析 | AH44: 2 | AI44: Song | AJ44: 1 | AK44: ー | AL44: ー | AM44: 45674 | AN44: 2024/7/2：サービスカテゴリをデータ集計・整形 →資料編集に変更 2024/7/1：担当SV変更＞emiko.maeyama ➡ atsushi.b.yamamoto 2025/12/31：サービス停止 | AO44: 完了(担当:運用企画-Tech) | AP44: 25/1/27_停止依頼 26-02-02_Li_サービス停止 | AQ44: A_通常_決定(登録可) | AS44: 登録済_本登録 | AT44: 4b.本登録_計測方法確定(FY24以前) | AV44: 45785 | AY44: =IF(D44="受託",IF(COUNTA(B44,F44,G44:J44,Z44:AA44)=8,"OK","NG"),"確認対象外") -> OK | AZ44: =ISNUMBER(AJ44) -> TRUE | BA44: =ROW()-7 -> 37 | BB44: e
A45: =IF(Z45="サービス停止",Z45,"") -> サービス停止 | C45: =IF(B45="","-",IF(COUNTIF($B$8:B45,B45)=1,"〇","×")) -> - | D45: 受託 | E45: SN_0033 | G45: Japan information site英語化 | H45: アクセンチュア社員の日本語が母国語以外の方がwebを閲覧した時に必要な情報を取得するための英訳編集作業。 | I45: 生麦 | K45: shigeki.ohtake | L45: 有 | M45: 週次 | N45: 依頼元からページ更新用の原稿を連携いただく。 | O45: 記事作成の目安(Word原稿6~7枚あたり)→2.5営業日。記事量にも依るが金曜日を一旦の納期とする。金曜日が祝日の場合は木曜日とする。 | Q45: Teamsにて完了報告。 | R45: 依頼元：指定なし | S45: 手動 | T45: 記事ごとに用意したTeamsスレッドにて、作業依頼担当者をメンションして完了報告(※記事はドラフトの状態)。 | Z45: サービス停止 | AA45: 44172 | AB45: ー | AC45: FY24以前 | AD45: ー | AI45: ー | AJ45: ー | AK45: ー | AL45: ー | AM45: 45674 | AO45: - | AS45: (サービス停止) | AT45: 9.対応不要 | AV45: 45785 | AY45: =IF(D45="受託",IF(COUNTA(B45,F45,G45:J45,Z45:AA45)=8,"OK","NG"),"確認対象外") -> NG | AZ45: =ISNUMBER(AJ45) -> FALSE | BA45: =ROW()-7 -> 38 | BB45: e
A46: =IF(Z46="サービス停止",Z46,"") -> サービス停止 | C46: =IF(B46="","-",IF(COUNTIF($B$8:B46,B46)=1,"〇","×")) -> - | D46: 受託 | E46: ST_0006 | G46: ODKS_NJページ更新作業 | H46: 月2回更新される人事情報（Roster）をもとに、New Joinerを特定し、ページに掲載する。 | I46: 立川 | K46: nobuyuki.ushikubo | L46: 無 | M46: 隔週 | N46: 毎月2回(14日頃、28日頃）、Rosterをアクセスし、情報を取得し、作業を開始する。 | O46: 5営業日 | P46: 無 | Q46: ・記事作成：記事公開 | S46: 手動 | T46: メール | U46: × | V46: 〇 Wordpress,Roster (ACN.Collaboration.Services.Japan@accenture.comへメールにて依頼) | W46: OD＆KS | X46: 米山さん（mizuki.yoneyama） | Z46: サービス停止 | AA46: 44204 | AB46: ー | AC46: FY24以前 | AD46: ー | AI46: ー | AJ46: ー | AK46: ー | AL46: ー | AM46: 45674 | AN46: Rosterへの権限設定が必要（SVのみ） | AO46: - | AS46: (サービス停止) | AT46: 9.対応不要 | AV46: 45785 | AY46: =IF(D46="受託",IF(COUNTA(B46,F46,G46:J46,Z46:AA46)=8,"OK","NG"),"確認対象外") -> NG | AZ46: =ISNUMBER(AJ46) -> FALSE | BA46: =ROW()-7 -> 39 | BB46: e
A47: =IF(Z47="サービス停止",Z47,"") -> サービス停止 | B47: A2007 | C47: =IF(B47="","-",IF(COUNTIF($B$8:B47,B47)=1,"〇","×")) -> 〇 | D47: 受託 | E47: ST_0007 | F47: 01調査・結果纏め | G47: PRD_中計・決算発表チェック&レポート作成(優先50社） | H47: クライアントの決算、及び中期経営計画(中計)の発表状況を一覧化したリストを作成し、メールでPRD内に周知する。 | I47: 立川 | J47: 立川Y | K47: nobuyuki.ushikubo | L47: 無 | M47: 週次 | N47: 週次でクライアントのIRページからIR情報を取得し作業を開始する。 | O47: 5営業日 | P47: 有 レビューバック反映も実施する | Q47: 作業結果をTeamsにて報告 | R47: 1か月 | S47: 手動 | T47: Teams | U47: × | V47: × | W47: PRD | X47: 山口さん（kunishige.yamaguchi） | Z47: サービス停止 | AA47: 44208 | AB47: ー | AC47: FY24以前 | AD47: ー | AI47: ー | AJ47: ー | AK47: ー | AL47: ー | AM47: 45674 | AN47: 2023/11/22：担当Tが「立川Y」→「立川Y2」へ変更に伴い、旧サービスの停止及び新規サービス番号を採番。 新規サービス番号：A0025 | AO47: - | AS47: (サービス停止) | AT47: 9.対応不要 | AV47: 45785 | AY47: =IF(D47="受託",IF(COUNTA(B47,F47,G47:J47,Z47:AA47)=8,"OK","NG"),"確認対象外") -> OK | AZ47: =ISNUMBER(AJ47) -> FALSE | BA47: =ROW()-7 -> 40 | BB47: e
A48: =IF(Z48="サービス停止",Z48,"") -> サービス停止 | B48: A2008 | C48: =IF(B48="","-",IF(COUNTIF($B$8:B48,B48)=1,"〇","×")) -> 〇 | D48: 受託 | E48: ST_0008 | F48: 07入力・登録代行 | G48: RES_出張申請 | H48: クライアントサイトに出向している中部電力アカウントのPJTメンバーの出張申請業務をツール上で入力を代行する。 | I48: 立川 | J48: 立川X | K48: akiko.a.hirano | L48: 無 | M48: 週次 | N48: 週次で依頼元に出張情報の記入を依頼する。 | O48: 依頼～完了まで２営業日 | P48: 無 | Q48: Pre-Trip Approval Toolへの出張情報入力。 | R48: 1か月 | S48: 手動 | T48: メールにて完了連絡 | U48: × | V48: × | W48: RES | X48: 田野さん <yuko.tano@accenture.com> 正木さん <mutsumi.a.masaki@accenture.com> | Z48: サービス停止 | AA48: 44216 | AB48: ー | AC48: FY24以前 | AD48: ー | AI48: ー | AJ48: ー | AK48: ー | AL48: ー | AM48: 45674 | AN48: 2023/12/22：立川Xチームの分割により担当チーム移行のためサービス停止扱いとする | AO48: - | AS48: (サービス停止) | AT48: 9.対応不要 | AV48: 45785 | AY48: =IF(D48="受託",IF(COUNTA(B48,F48,G48:J48,Z48:AA48)=8,"OK","NG"),"確認対象外") -> OK | AZ48: =ISNUMBER(AJ48) -> FALSE | BA48: =ROW()-7 -> 41 | BB48: e
A49: =IF(Z49="サービス停止",Z49,"") -> サービス停止 | C49: =IF(B49="","-",IF(COUNTIF($B$8:B49,B49)=1,"〇","×")) -> - | D49: 受託 | E49: ST_0009 | G49: RES_契約管理 | H49: 中部電力向けITサービス関連の契約書・見積書作成、CM(Contract Management)への契約書レビュー依頼、契約書・見積書の捺印申請を代行する。 | I49: 立川 | K49: nobuyuki.ushikubo | L49: 無 | M49: 月次 | N49: 月の中旬にリクエストフォーム | O49: ①契約書レビュー依頼：依頼日の翌営業日 ②捺印申請：依頼日の翌営業日 | P49: 無 | Q49: ①レビュー依頼をメールで送信 ②捺印申請をメールで送信 | S49: 手動 | T49: メール | U49: 〇 | V49: × | W49: RES | X49: 田野さん <yuko.tano@accenture.com> | Z49: サービス停止 | AA49: 44284 | AB49: ー | AC49: FY24以前 | AD49: ー | AI49: ー | AJ49: ー | AK49: ー | AL49: ー | AM49: 45674 | AN49: 2021年3月運用テスト 2021年12月サービス停止 | AO49: - | AS49: (サービス停止) | AT49: 9.対応不要 | AV49: 45785 | AY49: =IF(D49="受託",IF(COUNTA(B49,F49,G49:J49,Z49:AA49)=8,"OK","NG"),"確認対象外") -> NG | AZ49: =ISNUMBER(AJ49) -> FALSE | BA49: =ROW()-7 -> 42 | BB49: e
A50: =IF(Z50="サービス停止",Z50,"") -> サービス停止 | B50: A2010 | C50: =IF(B50="","-",IF(COUNTIF($B$8:B50,B50)=1,"〇","×")) -> 〇 | D50: 受託 | E50: ST_0010 | F50: 05配信記事編集 | G50: ACS_technology記事配信(各DTE) | H50: 各部署(DTE)の配信用記事のArticleのMedia Reportを作成する。 | I50: 立川 | J50: 立川X | K50: akiko.a.hirano | L50: 無 | M50: 随時 | N50: リクエストフォーム | O50: 作成：5-10営業日 (最大10営業日：担当者の稼働状況に応じてリクエストフォームで納期提示する) | P50: 有(メール) レビューバック反映も実施する | Q50: 編集画面URLと画面キャプチャをメールで担当者に送付(公開したい方はURL、レビューのみしたい方はキャプチャでご確認頂く) | R50: 6か月 | S50: 手動 | T50: 公開後にその旨メールで担当者にお知らせ(公開がご担当者の場合はレビュー後に完了) | U50: × | V50: 〇 Wordpress (ACN.Collaboration.Services.Japan@accenture.comへメールにて依頼) | W50: サービス依頼元：OK&DS 各記事の依頼元：Technology内の全組織 | X50: 米山さん（mizuki.yoneyama） ACN.Collaboration.Services.Japan@accenture.com | Z50: サービス停止 | AA50: 44200 | AB50: ー | AC50: FY24以前 | AD50: ー | AI50: ー | AJ50: ー | AK50: ー | AL50: ー | AM50: 45674 | AN50: 2021年1月4日よりサービス開始 2023/12/22：立川Xチームの分割により担当チーム移行のためサービス停止扱いとする | AO50: - | AS50: (サービス停止) | AT50: 9.対応不要 | AV50: 45785 | AY50: =IF(D50="受託",IF(COUNTA(B50,F50,G50:J50,Z50:AA50)=8,"OK","NG"),"確認対象外") -> OK | AZ50: =ISNUMBER(AJ50) -> FALSE | BA50: =ROW()-7 -> 43 | BB50: e
A51: =IF(Z51="サービス停止",Z51,"") -> サービス停止 | C51: =IF(B51="","-",IF(COUNTIF($B$8:B51,B51)=1,"〇","×")) -> - | D51: 受託 | E51: ST_0011 | G51: RES_MMS新規登録業務 | H51: RESチームにて新規案件や契約の機会が発生した際のMMS(Manage mysales・アクセンチュアの案件管理システム)への情報登録作業を実施する。 | I51: 立川 | K51: shinichi.fukasawa | L51: 無 | M51: 随時 | N51: リクエストフォーム | O51: 依頼の翌営業日 | P51: 有 レビューバック反映も実施する | Q51: メールにてopportunityIDを共有 | R51: 1か月 | S51: 手動 | T51: メール | U51: 〇 | V51: 〇 | W51: RES | Z51: サービス停止 | AA51: 44265 | AB51: ー | AC51: FY24以前 | AD51: ー | AI51: ー | AJ51: ー | AK51: ー | AL51: ー | AM51: 45674 | AN51: 2021年3月10日よりテスト運用 2022年4月サービス停止(2022/4/19田野様よりメール連絡 深澤記) | AO51: - | AS51: (サービス停止) | AT51: 9.対応不要 | AV51: 45785 | AY51: =IF(D51="受託",IF(COUNTA(B51,F51,G51:J51,Z51:AA51)=8,"OK","NG"),"確認対象外") -> NG | AZ51: =ISNUMBER(AJ51) -> FALSE | BA51: =ROW()-7 -> 44 | BB51: e
A52: =IF(Z52="サービス停止",Z52,"") -> サービス停止 | B52: A2012 | C52: =IF(B52="","-",IF(COUNTIF($B$8:B52,B52)=1,"〇","×")) -> 〇 | D52: 受託 | E52: ST_0012 | F52: 07入力・登録代行 | G52: Interactive_Fjord名刺発注業務 | H52: Interactive内部門の1つであるFjordの名刺作成業務をサポートする。新入社員入社時や、個人の名刺が不足した時点でFjordメンバーからリクエストフォーム経由で依頼を受け、名刺の発注・納品先登録依頼対応を行う。 | I52: 立川 | J52: 立川X | K52: akiko.a.hirano | L52: 無 | M52: 随時 | N52: リクエストフォーム | O52: 5営業日 | P52: 無 | Q52: メールでの発注依頼を行うもので、提出物なし | R52: 6か月 | S52: 手動 | T52: メールにて完了報告(発注依頼、住所入力依頼の各メール） | U52: × | V52: × | W52: Interactive | X52: 野村さん（akiko.nomura) | Z52: サービス停止 | AA52: 44242 | AB52: ー | AC52: FY24以前 | AD52: ー | AI52: ー | AJ52: ー | AK52: ー | AL52: ー | AM52: 45674 | AN52: 2023/12/22：立川Xチームの分割により担当チーム移行のためサービス停止扱いとする | AO52: - | AS52: (サービス停止) | AT52: 9.対応不要 | AV52: 45785 | AY52: =IF(D52="受託",IF(COUNTA(B52,F52,G52:J52,Z52:AA52)=8,"OK","NG"),"確認対象外") -> OK | AZ52: =ISNUMBER(AJ52) -> FALSE | BA52: =ROW()-7 -> 45 | BB52: e
A53: =IF(Z53="サービス停止",Z53,"") -> サービス停止 | C53: =IF(B53="","-",IF(COUNTIF($B$8:B53,B53)=1,"〇","×")) -> - | D53: 受託 | E53: SN_0034 | G53: RES_ボイスボット導入サポート | H53: コールセンターにて、ボイスボットを利用したカスタマーサービス支援として、ボイスボットの精度向上及び今後のシナリオ拡張のため、録音を聞きボイスボットが正しく応答しているか、確認する作業。 | I53: 生麦 | K53: hiroshi.a.harashima | L53: 無 | M53: 週次 | N53: Teamsチャネルにて依頼 | O53: 5営業日 | P53: 有(Teams) レビューバック反映も実施する | Q53: Teams上に格納し、Teamsにて完了報告。 | R53: 納品後、1週間以内に削除 | S53: 手動 | T53: Teams | U53: 〇 | V53: 〇 | W53: RES | X53: 千代崎さん (toga.chiyozaki) 中村さん (yukie.nakamura) | Z53: サービス停止 | AA53: 44249 | AB53: ー | AC53: FY24以前 | AD53: ー | AI53: ー | AJ53: ー | AK53: ー | AL53: ー | AM53: 45674 | AN53: 2021年2月22日よりサービス開始 2021年4月でサービス終了 | AO53: - | AS53: (サービス停止) | AT53: 9.対応不要 | AV53: 45785 | AY53: =IF(D53="受託",IF(COUNTA(B53,F53,G53:J53,Z53:AA53)=8,"OK","NG"),"確認対象外") -> NG | AZ53: =ISNUMBER(AJ53) -> FALSE | BA53: =ROW()-7 -> 46 | BB53: e
A54: =IF(Z54="サービス停止",Z54,"") -> サービス停止 | B54: A2013 | C54: =IF(B54="","-",IF(COUNTIF($B$8:B54,B54)=1,"〇","×")) -> 〇 | D54: 受託 | E54: ST_0013 | F54: 01調査・結果纏め | G54: Interactive_プレスリリース配信 | H54: 競合他社の情報収集とTeamsへの投稿 | I54: 立川 | J54: 立川X | K54: akiko.a.hirano | L54: 無 | M54: 週次 | N54: 週次で各企業のニュースページから情報を取得し作業を開始する。 | O54: 月曜開始、水曜投稿 | P54: 無 | Q54: Teamsで投稿 | R54: 保持データなし | S54: 手動 | T54: Teams投稿をもって完了 | U54: 〇 | V54: × | W54: Interactive | X54: Nakamura, Yuki A. <yuki.a.nakamura@accenture.com> | Z54: サービス停止 | AA54: 44256 | AB54: ー | AC54: FY24以前 | AD54: ー | AI54: ー | AJ54: ー | AK54: ー | AL54: ー | AM54: 45674 | AN54: 2021/3/1よりサービス開始 2022/12/14：依頼元都合によりサービス停止 メールタイトル：プレスリリース記事選定案件 ヒアリング | AO54: - | AS54: (サービス停止) | AT54: 9.対応不要 | AV54: 45785 | AY54: =IF(D54="受託",IF(COUNTA(B54,F54,G54:J54,Z54:AA54)=8,"OK","NG"),"確認対象外") -> OK | AZ54: =ISNUMBER(AJ54) -> FALSE | BA54: =ROW()-7 -> 47 | BB54: e
A55: =IF(Z55="サービス停止",Z55,"") -> サービス停止 | C55: =IF(B55="","-",IF(COUNTIF($B$8:B55,B55)=1,"〇","×")) -> - | D55: 受託 | E55: SN_0035 | G55: RPAツール(UiPath)開発・導入サポート | H55: ■アクセンチュアサテライト内部サービス 各チームで実施しているチェックや検索業務を自動化する、RPAツールの開発を実施する。または、作成したツールを各チームへ展開、サポートをする。 | I55: 生麦 | K55: emiko.maeyama | L55: 無 | M55: 随時 | N55: 内部での連絡 (メール、Teams等) | O55: 都度設定 ※約1ヶ月程度での作成を目安にする | P55: 無 ※導入後のチームからの質問に回答することは有 | S55: 手動 | T55: 内部での連絡 (メール、Teams等) | U55: 対象サービスによって変わる | V55: × | W55: アクセンチュアサテライト内部 | X55: 対象サービスを担当しているチームのSV | Z55: サービス停止 | AA55: ー | AB55: ー | AC55: FY24以前 | AD55: ー | AI55: ー | AJ55: ー | AK55: ー | AL55: ー | AM55: 45674 | AN55: 2021/7/12 AS_0001に統合 | AO55: - | AS55: (サービス停止) | AT55: 9.対応不要 | AV55: 45785 | AY55: =IF(D55="受託",IF(COUNTA(B55,F55,G55:J55,Z55:AA55)=8,"OK","NG"),"確認対象外") -> NG | AZ55: =ISNUMBER(AJ55) -> FALSE | BA55: =ROW()-7 -> 48 | BB55: e
A56: =IF(Z56="サービス停止",Z56,"") -> サービス停止 | B56: A2014 | C56: =IF(B56="","-",IF(COUNTIF($B$8:B56,B56)=1,"〇","×")) -> 〇 | D56: 受託 | E56: ST_0014 | F56: 07入力・登録代行 | G56: GA契約書類登録・アラートメール送信 | H56: GAが管理する契約書類の整理・フォルダ格納・リスト化およびライセンス契約更新期限のアラートメール送信 | I56: 立川 | J56: 立川X | K56: akiko.a.hirano | L56: 無 | M56: 随時 | N56: メール | O56: 依頼日＋8営業日 | P56: 無 | Q56: Teamsへ格納し、メールにて完了報告 | R56: 1か月 | S56: 手動 | T56: メール | U56: 〇 | V56: 〇 | W56: TechnologyGA | X56: Nakamizo, Tomoko <tomoko.nakamizo@accenture.com> | Z56: サービス停止 | AA56: 44287 | AB56: ー | AC56: FY24以前 | AD56: ー | AI56: ー | AJ56: ー | AK56: ー | AL56: ー | AM56: 45674 | AN56: 2021/3/10よりテスト開始予定 →2021年10月より、担当SV変更：Ito→Harashima 2023/12/22：立川Xチームの分割により担当チーム移行のためサービス停止扱いとする | AO56: - | AS56: (サービス停止) | AT56: 9.対応不要 | AV56: 45785 | AY56: =IF(D56="受託",IF(COUNTA(B56,F56,G56:J56,Z56:AA56)=8,"OK","NG"),"確認対象外") -> OK | AZ56: =ISNUMBER(AJ56) -> FALSE | BA56: =ROW()-7 -> 49 | BB56: e
A57: =IF(Z57="サービス停止",Z57,"") -> サービス停止 | B57: A2015 | C57: =IF(B57="","-",IF(COUNTIF($B$8:B57,B57)=1,"〇","×")) -> 〇 | D57: 受託 | E57: ST_0015 | F57: 01調査・結果纏め | G57: 【全体】ニュースクリップ | H57: 最新のビジネストレンドに関する情報をキャッチアップするため。ニュースクリップをTMGアカウントへメール配信する | I57: 立川 | J57: 立川Y | K57: nobuyuki.ushikubo | L57: 無 | M57: 随時 | N57: 依頼はなし | O57: 1営業日ごとに作成・配信 | P57: 無 | Q57: メール配信 | R57: 保持データなし | S57: 手動 | T57: ニュース配信をもって完了 | U57: × | V57: 〇 | W57: HPS | X57: Tsubone,Kohei kohei.tsubone@accenture.com | Z57: サービス停止 | AA57: 44382 | AB57: ー | AC57: FY24以前 | AD57: ー | AI57: ー | AJ57: ー | AK57: ー | AL57: ー | AM57: 45674 | AN57: 2021/7/5よりサービス開始 2022/11/18：依頼元担当者を変更 2023/11/22：担当Tが「立川Y」→「立川Y1」へ変更に伴い、旧サービスの停止及び新規サービス番号を採番。 新規サービス番号：A0021 | AO57: - | AS57: (サービス停止) | AT57: 9.対応不要 | AV57: 45785 | AY57: =IF(D57="受託",IF(COUNTA(B57,F57,G57:J57,Z57:AA57)=8,"OK","NG"),"確認対象外") -> OK | AZ57: =ISNUMBER(AJ57) -> FALSE | BA57: =ROW()-7 -> 50 | BB57: e
A58: =IF(Z58="サービス停止",Z58,"") -> サービス停止 | C58: =IF(B58="","-",IF(COUNTIF($B$8:B58,B58)=1,"〇","×")) -> - | D58: 受託 | E58: ST_0016 | G58: 【TMG】発掘済企業の詳細確認 | H58: 外国企業の情報をWEBから取得し、リスト化する | I58: 立川 | K58: kaori.ito | L58: 無 | M58: 月次 | N58: メール | O58: 月末納品 | P58: 有 レビューバック反映も実施する | Q58: メールにてファイルを送付 | R58: 1か月 | S58: 手動 | T58: メール | U58: 〇 | V58: × | W58: HPS | X58: Tsunetsugu, Ayane <ayane.tsunetsugu@accenture.com> | Z58: サービス停止 | AB58: ー | AC58: FY24以前 | AD58: ー | AI58: ー | AJ58: ー | AK58: ー | AL58: ー | AM58: 45674 | AN58: 2021/9で終了 | AO58: - | AS58: (サービス停止) | AT58: 9.対応不要 | AV58: 45785 | AY58: =IF(D58="受託",IF(COUNTA(B58,F58,G58:J58,Z58:AA58)=8,"OK","NG"),"確認対象外") -> NG | AZ58: =ISNUMBER(AJ58) -> FALSE | BA58: =ROW()-7 -> 51 | BB58: e
A59: =IF(Z59="サービス停止",Z59,"") -> サービス停止 | B59: A2017 | C59: =IF(B59="","-",IF(COUNTIF($B$8:B59,B59)=1,"〇","×")) -> 〇 | D59: 受託 | E59: ST_0017 | F59: 01調査・結果纏め | G59: 【TMG】誘致企業の登記情報確認 | H59: 東京都が誘致している企業の登記の状況を（登記済み、未登記、廃止等）を調査し報告する | I59: 立川 | J59: 立川Y | K59: nobuyuki.ushikubo | L59: 無 | M59: 月次 | N59: 月次で「登記ねっと」ページから企業の登記情報を取得し作業を開始する。 | O59: 月間だが第1週内を基本として作業 | P59: 有 レビューバック反映も実施する | Q59: メールにてファイルを送付 | R59: 保持データなし | S59: 手動 | T59: メール | U59: × | V59: × | W59: HPS | X59: shuhei.matsuda <shuhei.matsuda@accenture.com> | Z59: サービス停止 | AA59: 44322 | AB59: ー | AC59: FY24以前 | AD59: ー | AI59: ー | AJ59: ー | AK59: ー | AL59: ー | AM59: 45674 | AN59: 2022/4末でサービス停止 | AO59: - | AS59: (サービス停止) | AT59: 9.対応不要 | AV59: 45785 | AY59: =IF(D59="受託",IF(COUNTA(B59,F59,G59:J59,Z59:AA59)=8,"OK","NG"),"確認対象外") -> OK | AZ59: =ISNUMBER(AJ59) -> FALSE | BA59: =ROW()-7 -> 52 | BB59: e
A60: =IF(Z60="サービス停止",Z60,"") -> サービス停止 | B60: A2018 | C60: =IF(B60="","-",IF(COUNTIF($B$8:B60,B60)=1,"〇","×")) -> 〇 | D60: 受託 | E60: ST_0018 | F60: 06連絡・確認代行 | G60: 【TMG】公示案件の確認 | H60: 東京都が新規に公表した公示案件の週次調査・報告を代行する。要求があれば関連資料を取得し送付する。 | I60: 立川 | J60: 立川X | K60: akiko.a.hirano | L60: 無 | M60: 日次 | N60: 月水金にTMGページから公示情報を取得し作業を開始する。 2021/12までは水のみ。 | O60: 調査日当日に報告 | P60: 有(メール) レビューバック反映も実施する | Q60: メール配信およびファイルをSPに格納 | R60: 1か月 | S60: 手動 | T60: 公示案件配信をもって完了 | U60: × | V60: × | W60: HPS | X60: Tsunetsugu, Ayane <ayane.tsunetsugu@accenture.com> | Z60: サービス停止 | AA60: 44284 | AB60: ー | AC60: FY24以前 | AD60: ー | AI60: ー | AJ60: ー | AK60: ー | AL60: ー | AM60: 45674 | AN60: 2021/9 Ushikubo→Fukasawa 2023/12/22：立川Xチームの分割により担当チーム移行のためサービス停止扱いとする | AO60: - | AS60: (サービス停止) | AT60: 9.対応不要 | AV60: 45785 | AY60: =IF(D60="受託",IF(COUNTA(B60,F60,G60:J60,Z60:AA60)=8,"OK","NG"),"確認対象外") -> OK | AZ60: =ISNUMBER(AJ60) -> FALSE | BA60: =ROW()-7 -> 53 | BB60: e
A61: =IF(Z61="サービス停止",Z61,"") -> サービス停止 | C61: =IF(B61="","-",IF(COUNTIF($B$8:B61,B61)=1,"〇","×")) -> - | D61: 受託 | E61: SN_0036 | G61: Offering_Wordlist作成作業(KXサニタイズ代行) | H61: SN_0004と同じ | I61: 生麦 | K61: kaori.ito | L61: 無 | M61: 随時 | N61: 依頼元が指定のフォルダに格納し、メールにて依頼 | O61: Wordlist作成・サニタイズ作業合わせて 5営業日 | P61: 有(Teams) レビューバック反映も実施する | Q61: SharePoint上の個別フォルダ (権限設定有り) | S61: 自動 | T61: ステータスを更新すると自動でKMにメール通知 | U61: 〇 | V61: 〇 | W61: CF_KM | X61: Kumai, Hitomi | Z61: サービス停止 | AA61: 44257 | AB61: ー | AC61: FY24以前 | AD61: ー | AI61: ー | AJ61: ー | AK61: ー | AL61: ー | AM61: 45674 | AN61: KMのSharePoint、KMリクエストフォーム(ステータス更新のため）への権限設定が必要 2021/10/1より、担当SV変更：Maeyama→（Takahashi,Airi)→Ito 2022/8/18 サービス停止に変更 | AO61: - | AS61: (サービス停止) | AT61: 9.対応不要 | AV61: 45785 | AY61: =IF(D61="受託",IF(COUNTA(B61,F61,G61:J61,Z61:AA61)=8,"OK","NG"),"確認対象外") -> NG | AZ61: =ISNUMBER(AJ61) -> FALSE | BA61: =ROW()-7 -> 54 | BB61: e
A62: =IF(Z62="サービス停止",Z62,"") -> サービス停止 | C62: =IF(B62="","-",IF(COUNTIF($B$8:B62,B62)=1,"〇","×")) -> - | D62: 受託 | E62: SN_0037 | G62: Offering_KXサニタイズ代行 | H62: SN_0003と同じ | I62: 生麦 | K62: kaori.ito | L62: 無 | M62: 随時 | N62: 依頼元が指定のフォルダに格納し、メールにて依頼 | O62: Wordlist作成・サニタイズ作業合わせて 5営業日 | P62: 有(Teams) レビューバック反映も実施する | Q62: SharePoint上の個別フォルダ (権限設定有り) | S62: 自動 | T62: ステータスを更新すると自動でKMにメール通知 | U62: 〇 | V62: 〇 | W62: CF_KM | X62: Kumai, Hitomi | Z62: サービス停止 | AA62: 44257 | AB62: ー | AC62: FY24以前 | AD62: ー | AI62: ー | AJ62: ー | AK62: ー | AL62: ー | AM62: 45674 | AN62: KMのSharePoint、KMリクエストフォーム(ステータス更新のため）への権限設定が必要 2021/10/1より、担当SV変更：Maeyama→（Takahashi,Airi)→Ito 2022/8/18 サービス停止に変更 | AO62: - | AS62: (サービス停止) | AT62: 9.対応不要 | AV62: 45785 | AY62: =IF(D62="受託",IF(COUNTA(B62,F62,G62:J62,Z62:AA62)=8,"OK","NG"),"確認対象外") -> NG | AZ62: =ISNUMBER(AJ62) -> FALSE | BA62: =ROW()-7 -> 55 | BB62: e
A63: =IF(Z63="サービス停止",Z63,"") -> サービス停止 | B63: A1038 | C63: =IF(B63="","-",IF(COUNTIF($B$8:B63,B63)=1,"〇","×")) -> 〇 | D63: 受託 | E63: SN_0038 | F63: 02サニタイズ編集要件 | G63: Technology_KXサニタイズ代行（Ｗordlist作成） | H63: KXサニタイズに必要なWordListを作成する。 | I63: 生麦 | J63: 生麦Y | K63: emiko.maeyama | L63: 無 | M63: 指定Period | N63: Teamsチャネルにて依頼 | O63: 約5営業日 | P63: 有(Teams) レビューバック反映も実施する | Q63: 依頼元とのTeams上の個別フォルダ | R63: 依頼元：指定なし | S63: 手動 | T63: Teamsにて完了連絡 | U63: 〇 | V63: × | W63: Technology | X63: SAP on Cloud／Kanno, Kiyotaka Cloud CoE_Modern Infra／Jun.Nagamine | Z63: =IF(AC63="",IF(AA63="","",IF(TODAY()>=AA63,"サービス開始",IF(TODAY()<AA63,"本稼働前",""))),IF(TODAY()>=AC63,"サービス停止",IF(AA63="","",IF(TODAY()>=AA63,"サービス開始",IF(TODAY()<AA63,"本稼働前",""))))) -> サービス停止 | AA63: 44256 | AB63: ー | AC63: 45443 | AD63: ー | AG63: Technology_KXサニタイズ代行 | AH63: 1 | AI63: ー | AJ63: ー | AK63: ー | AL63: ー | AM63: 45674 | AN63: 2024/5/31：TFチームへの移管に伴いサービス停止（新規サービス番号A0058） | AO63: - | AS63: (サービス停止) | AT63: 9.対応不要 | AV63: 45785 | AY63: =IF(D63="受託",IF(COUNTA(B63,F63,G63:J63,Z63:AA63)=8,"OK","NG"),"確認対象外") -> OK | AZ63: =ISNUMBER(AJ63) -> FALSE | BA63: =ROW()-7 -> 56 | BB63: e
A64: =IF(Z64="サービス停止",Z64,"") -> サービス停止 | B64: A1039 | C64: =IF(B64="","-",IF(COUNTIF($B$8:B64,B64)=1,"〇","×")) -> 〇 | D64: 受託 | E64: SN_0039 | F64: 03サニタイズ編集 | G64: Technology_KXサニタイズ代行（最終化） | H64: 依頼されたドキュメントをKXに登録可能なフォーマットに修正する。 | I64: 生麦 | J64: 生麦Y | K64: emiko.maeyama | L64: 無 | M64: 指定Period | N64: Teamsチャネルにて依頼 | O64: 約5営業日 | P64: 有(Teams) レビューバック反映も実施する | Q64: 依頼元とのTeams上の個別フォルダ | R64: 依頼元：指定なし | S64: 手動 | T64: Teamsにて完了連絡 | U64: 〇 | V64: × | W64: Technology | X64: SAP on Cloud／Kanno, Kiyotaka Cloud CoE_Modern Infra／Jun.Nagamine | Z64: =IF(AC64="",IF(AA64="","",IF(TODAY()>=AA64,"サービス開始",IF(TODAY()<AA64,"本稼働前",""))),IF(TODAY()>=AC64,"サービス停止",IF(AA64="","",IF(TODAY()>=AA64,"サービス開始",IF(TODAY()<AA64,"本稼働前",""))))) -> サービス停止 | AA64: 44256 | AB64: ー | AC64: 45443 | AD64: ー | AG64: Technology_KXサニタイズ代行 | AH64: 2 | AI64: ー | AJ64: ー | AK64: ー | AL64: ー | AM64: 45674 | AN64: 2024/5/31：TFチームへの移管に伴いサービス停止（新規サービス番号A0059） | AO64: - | AS64: (サービス停止) | AT64: 9.対応不要 | AV64: 45785 | AY64: =IF(D64="受託",IF(COUNTA(B64,F64,G64:J64,Z64:AA64)=8,"OK","NG"),"確認対象外") -> OK | AZ64: =ISNUMBER(AJ64) -> FALSE | BA64: =ROW()-7 -> 57 | BB64: e
A65: =IF(Z65="サービス停止",Z65,"") | B65: A1040 | C65: =IF(B65="","-",IF(COUNTIF($B$8:B65,B65)=1,"〇","×")) -> 〇 | D65: 受託 | E65: SN_0040 | F65: 01調査・結果纏め | G65: PLWアカウントのニュースレターの作成・配信 | H65: グーグルアラート、指定ＨＰからキーワード情報を抽出し、抽出した情報を配信する。 | I65: 生麦 | J65: 生麦Y | K65: atsushi.b.yamamoto | L65: 無 | M65: 週次 | N65: 週次で情報を取得し作業を開始する。 | O65: 毎週金曜日に依頼元にメール配信する。 | P65: 無し | Q65: メール | R65: 1カ月 | S65: 手動 | T65: メール | U65: × | V65: × | W65: Ph2 | X65: Senba, Ryohei | Z65: =IF(AC65="",IF(AA65="","",IF(TODAY()>=AA65,"サービス開始",IF(TODAY()<AA65,"本稼働前",""))),IF(TODAY()>=AC65,"サービス停止",IF(AA65="","",IF(TODAY()>=AA65,"サービス開始",IF(TODAY()<AA65,"本稼働前",""))))) -> サービス開始 | AA65: 44348 | AB65: ー | AI65: Technology | AJ65: 1 | AK65: ー | AL65: ー | AM65: 45674 | AN65: 依頼元との確認は、Teamsで行う。【ＰＬＷアカウントニュースレター作成配信業務】 2024/7/1：担当SV変更＞emiko.maeyama ➡ atsushi.b.yamamoto | AO65: - | AQ65: A_通常_決定(登録可) | AS65: 登録済_本登録 | AT65: 4b.本登録_計測方法確定(FY24以前) | AV65: 45785 | AY65: =IF(D65="受託",IF(COUNTA(B65,F65,G65:J65,Z65:AA65)=8,"OK","NG"),"確認対象外") -> OK | AZ65: =ISNUMBER(AJ65) -> TRUE | BA65: =ROW()-7 -> 58 | BB65: e
A66: =IF(Z66="サービス停止",Z66,"") -> サービス停止 | B66: A2019 | C66: =IF(B66="","-",IF(COUNTIF($B$8:B66,B66)=1,"〇","×")) -> 〇 | D66: 受託 | E66: ST_0019 | F66: 01調査・結果纏め | G66: 企業情報検索・更新 | H66: アクセンチュアで管理している企業情報DBの情報確認・更新を実施するものである。アクセンチュアのクライアント企業や、その子会社企業の役員情報を、企業のWebサイトを確認しアップデートを行う。 | I66: 立川 | J66: 立川Y | K66: nobuyuki.ushikubo | L66: 無 | M66: 月次 | N66: 2か月で1回分の作業であり、サテライトにて着手する | O66: 約1500社の情報を2か月で検索・更新する | P66: 無し | Q66: 依頼元のDBを更新 | R66: 成果物は依頼元DBのため削除不可。作業用ファイル(管理用）は継続使用のため削除しない。 | S66: 手動 | T66: メール | U66: × | V66: 〇 | W66: Technology | X66: 元村さん<miho.motomura@accenture.com> | Z66: サービス停止 | AA66: 44287 | AB66: ー | AC66: FY24以前 | AD66: ー | AI66: ー | AJ66: ー | AK66: ー | AL66: ー | AM66: 45674 | AN66: 2021/4よりサービス開始 2023/11/22：担当Tが「立川Y」→「立川Y2」へ変更に伴い、旧サービスの停止及び新規サービス番号を採番。 新規サービス番号：A0026 | AO66: - | AS66: (サービス停止) | AT66: 9.対応不要 | AV66: 45785 | AY66: =IF(D66="受託",IF(COUNTA(B66,F66,G66:J66,Z66:AA66)=8,"OK","NG"),"確認対象外") -> OK | AZ66: =ISNUMBER(AJ66) -> FALSE | BA66: =ROW()-7 -> 59 | BB66: e
A67: =IF(Z67="サービス停止",Z67,"") -> サービス停止 | B67: A1041 | C67: =IF(B67="","-",IF(COUNTIF($B$8:B67,B67)=1,"〇","×")) -> 〇 | D67: 受託 | E67: SN_0041 | F67: 05配信記事編集 | G67: MCOM_記事配信(JapanBestProject) | H67: MCOMの配信用のJapanBestProject記事を作成する。 | I67: 生麦 | J67: 生麦Z | K67: hiroshi.a.harashima | L67: 無 | M67: 月次 | N67: リクエストフォーム ※毎月第2週頃 | O67: 作成：５営業日(長編記事と同様)→６営業日(2021.12.10～) | P67: 無 (メールにてレビューバックはあるが、指摘反映は不要) | Q67: レビューURLをメールにて送付 | R67: 1カ月 | S67: 手動 | T67: 作業提出メールと同時に完了報告を行う | U67: × | V67: 〇 Wordpress （指定の申請書に直接記入で申請メールなし：備考欄参照） | W67: CF_MCOM | X67: 魚住さん（azusa.uozumi） | Z67: サービス停止 | AA67: 44287 | AB67: ー | AC67: FY24以前 | AD67: ー | AI67: ー | AJ67: ー | AK67: ー | AL67: ー | AM67: 45674 | AN67: IMJのページを編集 依頼は毎月第２週目頃 ①原稿から画像を抽出して保存 ②画像とテキストの更新をして新しい記事を作成する作業イメージです。（前回の同様の記事が入っていますので、このフォーマットに沿って更新していただく様な進め方になると思います） 2021.12.10 依頼元から毎回テンプレートの提供を廃止。前に作成した記事を元に作成することになった。追加作業の工数は、0.5H 2023/2/7：依頼元よりサービス停止の連絡 | AO67: - | AS67: (サービス停止) | AT67: 9.対応不要 | AV67: 45785 | AY67: =IF(D67="受託",IF(COUNTA(B67,F67,G67:J67,Z67:AA67)=8,"OK","NG"),"確認対象外") -> OK | AZ67: =ISNUMBER(AJ67) -> FALSE | BA67: =ROW()-7 -> 60 | BB67: e
A68: =IF(Z68="サービス停止",Z68,"") -> サービス停止 | C68: =IF(B68="","-",IF(COUNTIF($B$8:B68,B68)=1,"〇","×")) -> - | D68: 受託 | E68: ST_0020 | G68: RES_ボイスボット導入サポート | H68: コールセンターにて、ボイスボットを利用したカスタマーサービス支援として、ボイスボットの精度向上及び今後のシナリオ拡張のため、録音を聞きボイスボットが正しく応答しているか、確認する作業。 | I68: 立川 | K68: kaori.ito | L68: 無 | M68: 週次 | N68: Teamsチャネルにて依頼 | O68: 5営業日 | P68: 有(Teams) レビューバック反映も実施する | Q68: Teams上に格納し、Teamsにて完了報告。 | R68: 納品後、1週間以内に削除 | S68: 手動 | T68: Teams | U68: 〇 | V68: 〇 | W68: RES | X68: 千代崎さん (toga.chiyozaki) 中村さん (yukie.nakamura) | Z68: サービス停止 | AA68: 44270 | AB68: ー | AC68: FY24以前 | AD68: ー | AI68: ー | AJ68: ー | AK68: ー | AL68: ー | AM68: 45674 | AN68: 2021年3月15日よりサービス開始 2021年4月末で終了 | AO68: - | AS68: (サービス停止) | AT68: 9.対応不要 | AV68: 45785 | AY68: =IF(D68="受託",IF(COUNTA(B68,F68,G68:J68,Z68:AA68)=8,"OK","NG"),"確認対象外") -> NG | AZ68: =ISNUMBER(AJ68) -> FALSE | BA68: =ROW()-7 -> 61 | BB68: e
A69: =IF(Z69="サービス停止",Z69,"") -> サービス停止 | B69: A1042 | C69: =IF(B69="","-",IF(COUNTIF($B$8:B69,B69)=1,"〇","×")) -> 〇 | D69: 受託 | E69: SN_0042 | F69: 08データ集計・整形 | G69: HPS_JPiT月次基盤資料作成 | H69: 毎月の月初に前月の基盤データに基づいて、運用されているマクロを使って集計を実施し、毎月第二週の火曜日に行う月次会議で報告する資料を作成。 | I69: 生麦 | J69: 生麦Y | K69: atsushi.b.yamamoto | L69: 無 | M69: 月次 | N69: Teamsチャネルにて依頼 ※月初 | O69: 一次提出：2営業日 レビュー指摘反映：1営業日 | P69: 有(Teams) レビューバック反映も実施する | Q69: SharePoint上の個別フォルダ (権限設定有り) | R69: 1カ月 | S69: 手動 | T69: Teamsにて完了連絡 | U69: 〇 | V69: 〇 | W69: HPS | X69: 和田さん（Wada,Ikumii） 牧野さん（Makino, Mari） | Z69: =IF(AC69="",IF(AA69="","",IF(TODAY()>=AA69,"サービス開始",IF(TODAY()<AA69,"本稼働前",""))),IF(TODAY()>=AC69,"サービス停止",IF(AA69="","",IF(TODAY()>=AA69,"サービス開始",IF(TODAY()<AA69,"本稼働前",""))))) -> サービス停止 | AA69: 44286 | AB69: ー | AC69: 45565 | AD69: ー | AI69: Client Service Group | AJ69: 1 | AK69: ー | AL69: ー | AM69: 45674 | AN69: 3月次テスト運用⇒3/31本稼働判定あり 2024/7/1：担当SV変更＞emiko.maeyama ➡ atsushi.b.yamamoto 2024/9/30：サービス停止 | AO69: - | AQ69: C_通常_未定(仮登録可) | AS69: (サービス停止) | AT69: 9.対応不要 | AV69: 45785 | AY69: =IF(D69="受託",IF(COUNTA(B69,F69,G69:J69,Z69:AA69)=8,"OK","NG"),"確認対象外") -> OK | AZ69: =ISNUMBER(AJ69) -> TRUE | BA69: =ROW()-7 -> 62 | BB69: e
A70: =IF(Z70="サービス停止",Z70,"") -> サービス停止 | B70: A1043 | C70: =IF(B70="","-",IF(COUNTIF($B$8:B70,B70)=1,"〇","×")) -> 〇 | D70: 受託 | E70: SN_0043 | F70: 08データ集計・整形 | G70: HPS_JPiT月次資料作成 | H70: 毎月の月初に前月分に発生したインシデント・工数に基づいて、運用されているマクロを使って集計を実施し、毎月第二週の火曜日に行う月次会議で報告する資料を作成。 | I70: 生麦 | J70: 生麦Y | K70: atsushi.b.yamamoto | L70: 無 | M70: 月次 | N70: Teamsチャネルにて依頼 ※月初 | O70: 一次提出：2営業日 レビュー指摘反映：1営業日 | P70: 有(Teams) レビューバック反映も実施する | Q70: SharePoint上の個別フォルダ (権限設定有り) | R70: 1カ月 | S70: 手動 | T70: Teamsにて完了連絡 | U70: 〇 | V70: 〇 | W70: HPS | X70: 和田さん（Wada,Ikumii） 牧野さん（Makino, Mari） | Z70: =IF(AC70="",IF(AA70="","",IF(TODAY()>=AA70,"サービス開始",IF(TODAY()<AA70,"本稼働前",""))),IF(TODAY()>=AC70,"サービス停止",IF(AA70="","",IF(TODAY()>=AA70,"サービス開始",IF(TODAY()<AA70,"本稼働前",""))))) -> サービス停止 | AA70: 44287 | AB70: ー | AC70: 45565 | AD70: ー | AI70: Client Service Group | AJ70: 1 | AK70: ー | AL70: ー | AM70: 45674 | AN70: SN_0042「HPS_JPiT月次基盤資料作成」の内容がマージされる 2024/7/1：担当SV変更＞emiko.maeyama ➡ atsushi.b.yamamoto 2024/9/30：サービス停止 | AO70: - | AS70: (サービス停止) | AT70: 9.対応不要 | AV70: 45785 | AY70: =IF(D70="受託",IF(COUNTA(B70,F70,G70:J70,Z70:AA70)=8,"OK","NG"),"確認対象外") -> OK | AZ70: =ISNUMBER(AJ70) -> TRUE | BA70: =ROW()-7 -> 63 | BB70: e
A71: =IF(Z71="サービス停止",Z71,"") -> サービス停止 | B71: A1044 | C71: =IF(B71="","-",IF(COUNTIF($B$8:B71,B71)=1,"〇","×")) -> 〇 | D71: 受託 | E71: SN_0044 | F71: 08データ集計・整形 | G71: HPS_JPiT請求書内訳作成 | H71: 毎月の月末に運用されているマクロを使って、翌月初の第一営業日にクライアントに提出用の提出請求書内訳を作成。 | I71: 生麦 | J71: 生麦Y | K71: atsushi.b.yamamoto | L71: 無 | M71: 月次 | N71: Teamsチャネルにて依頼 ※月初 | O71: 一次提出：2営業日 レビュー指摘反映：1営業日 | P71: 有(Teams) レビューバック反映も実施する | Q71: メール | R71: 1カ月 | S71: 手動 | T71: Teamsにて完了連絡 | U71: 〇 | V71: 〇 | W71: HPS | X71: 和田さん（Wada,Ikumii） 牧野さん（Makino, Mari） | Z71: =IF(AC71="",IF(AA71="","",IF(TODAY()>=AA71,"サービス開始",IF(TODAY()<AA71,"本稼働前",""))),IF(TODAY()>=AC71,"サービス停止",IF(AA71="","",IF(TODAY()>=AA71,"サービス開始",IF(TODAY()<AA71,"本稼働前",""))))) -> サービス停止 | AA71: 44287 | AB71: ー | AC71: 45565 | AD71: ー | AE71: A0112 | AI71: Client Service Group | AJ71: 1 | AK71: ー | AL71: ー | AM71: 45674 | AN71: 2024/7/1：担当SV変更＞emiko.maeyama ➡ atsushi.b.yamamoto 2024/9/30：生麦Yから生麦Xへ移管に伴い、サービス停止 | AO71: - | AS71: (サービス停止) | AT71: 9.対応不要 | AV71: 45785 | AY71: =IF(D71="受託",IF(COUNTA(B71,F71,G71:J71,Z71:AA71)=8,"OK","NG"),"確認対象外") -> OK | AZ71: =ISNUMBER(AJ71) -> TRUE | BA71: =ROW()-7 -> 64 | BB71: e
A72: =IF(Z72="サービス停止",Z72,"") -> サービス停止 | B72: A1045 | C72: =IF(B72="","-",IF(COUNTIF($B$8:B72,B72)=1,"〇","×")) -> 〇 | D72: 受託 | E72: SN_0045 | F72: 01調査・結果纏め | G72: CMT_SONY定期リサーチ | H72: 週２回、グーグルでソニーの関連ニュースを検索して検索結果を提供する。 | I72: 生麦 | J72: 生麦Y | K72: atsushi.b.yamamoto | L72: 無 | M72: 日次 | N72: Teamsチャネルにて依頼 | O72: 月曜と木曜日に提供 | P72: なし | Q72: Teams | R72: 3か月 | S72: 手動 | T72: Teamsにて完了連絡 | U72: × | V72: × | W72: CMT | X72: 高平さん（Takahira, Koichiro） → 梅原さん(Umehara, Daiki) | Z72: =IF(AC72="",IF(AA72="","",IF(TODAY()>=AA72,"サービス開始",IF(TODAY()<AA72,"本稼働前",""))),IF(TODAY()>=AC72,"サービス停止",IF(AA72="","",IF(TODAY()>=AA72,"サービス開始",IF(TODAY()<AA72,"本稼働前",""))))) -> サービス停止 | AA72: 44368 | AB72: ー | AC72: 45996 | AD72: ー | AE72: A0135 | AI72: Client Service Group | AJ72: 1 | AK72: ー | AL72: ー | AM72: 45674 | AN72: 確認と提供でTeamsのチャネルが異なる。 確認用は、生麦でメンバー登録/削除が出来るが、提供用は依頼元管理のチャネルのため、依頼元にメンバー登録/削除依頼が必要。 2024/7/1：担当SV変更＞emiko.maeyama ➡ atsushi.b.yamamoto 2025/12/5：生麦Yから弁天町Y2へ移管に伴い、サービス停止 | AO72: - | AQ72: A_通常_決定(登録可) | AS72: 登録済_本登録 | AT72: 4b.本登録_計測方法確定(FY24以前) | AV72: 45785 | AY72: =IF(D72="受託",IF(COUNTA(B72,F72,G72:J72,Z72:AA72)=8,"OK","NG"),"確認対象外") -> OK | AZ72: =ISNUMBER(AJ72) -> TRUE | BA72: =ROW()-7 -> 65 | BB72: e
A73: =IF(Z73="サービス停止",Z73,"") | B73: A1046 | C73: =IF(B73="","-",IF(COUNTIF($B$8:B73,B73)=1,"〇","×")) -> 〇 | D73: 受託 | E73: SN_0046 | F73: 01調査・結果纏め | G73: CMT_SONYメディアリリース情報確認 | H73: 毎週ソニーグループの人事情報、企業情報を検索し検索結果を提供する。 | I73: 生麦 | J73: 生麦X | K73: shigeki.ohtake | L73: 無 | M73: 週次 | N73: Teamsチャネルにて依頼 | O73: 5営業日 | P73: なし | Q73: Teams | R73: なし | S73: 手動 | T73: Teamsにて完了連絡 | U73: × | V73: × | W73: CMT | X73: 高平さん（Takahira, Koichiro） | Z73: =IF(AC73="",IF(AA73="","",IF(TODAY()>=AA73,"サービス開始",IF(TODAY()<AA73,"本稼働前",""))),IF(TODAY()>=AC73,"サービス停止",IF(AA73="","",IF(TODAY()>=AA73,"サービス開始",IF(TODAY()<AA73,"本稼働前",""))))) -> サービス開始 | AA73: 44295 | AB73: ー | AG73: CMT_SONYメディアリリース情報確認 | AI73: Client Service Group | AJ73: 1 | AK73: ー | AL73: ー | AM73: 45674 | AO73: - | AQ73: A_通常_決定(登録可) | AS73: 登録済_本登録 | AT73: 4b.本登録_計測方法確定(FY24以前) | AV73: 45785 | AY73: =IF(D73="受託",IF(COUNTA(B73,F73,G73:J73,Z73:AA73)=8,"OK","NG"),"確認対象外") -> OK | AZ73: =ISNUMBER(AJ73) -> TRUE | BA73: =ROW()-7 -> 66 | BB73: e
A74: =IF(Z74="サービス停止",Z74,"") -> サービス停止 | C74: =IF(B74="","-",IF(COUNTIF($B$8:B74,B74)=1,"〇","×")) -> - | D74: 受託 | E74: ST_0021 | G74: RPAツール(UiPath)開発・導入サポート＜立川＞ | H74: ■アクセンチュアサテライト内部サービス 各チームで実施しているチェックや検索業務を自動化する、RPAツールの開発を実施する。または、作成したツールを各チームへ展開、サポートをする。 | I74: 立川 | K74: nobuyuki.ushikubo | L74: 無 | M74: 随時 | N74: 内部での連絡 (メール、Teams等) | O74: 都度設定 ※約1ヶ月程度での作成を目安にする | P74: 無 ※導入後のチームからの質問に回答することは有 | S74: 手動 | T74: 内部での連絡 (メール、Teams等) | U74: 対象サービスによって変わる | V74: × | W74: アクセンチュアサテライト内部 | X74: 対象サービスを担当しているチームのSV | Z74: サービス停止 | AA74: ー | AB74: ー | AC74: FY24以前 | AD74: ー | AI74: ー | AJ74: ー | AK74: ー | AL74: ー | AM74: 45674 | AN74: 2021/7/12 AS_0001に統合 | AO74: - | AS74: (サービス停止) | AT74: 9.対応不要 | AV74: 45785 | AY74: =IF(D74="受託",IF(COUNTA(B74,F74,G74:J74,Z74:AA74)=8,"OK","NG"),"確認対象外") -> NG | AZ74: =ISNUMBER(AJ74) -> FALSE | BA74: =ROW()-7 -> 67 | BB74: e
A75: =IF(Z75="サービス停止",Z75,"") -> サービス停止 | B75: A1047 | C75: =IF(B75="","-",IF(COUNTIF($B$8:B75,B75)=1,"〇","×")) -> 〇 | D75: 受託 | E75: SN_0047 | F75: 04資料編集 | G75: Security_セールスDeckメンテナンス | H75: 各クライアントへ持参したDeckとマスターDeckの内容を比較・確認し、変更しているスライドがあればクライアントへ持参したDeckを正として、マスターDeckを入れ替える(更新する)業務。 | I75: 生麦 | J75: 生麦Z | K75: hiroshi.a.harashima | L75: 無 | M75: 随時 | N75: 2週間に1回(月曜日時点)、Teamsフォルダで更新分を確認し、前回より更新分があれば実施する →随時依頼 | O75: 5営業日 （5営業日で更新し、その後1週間で依頼元レビューおよび修正） →作業内容により、調整 | P75: 有(Teams) レビューバック反映も実施する | Q75: 依頼元Teams上の個別フォルダ（権限は依頼元が設定） | R75: 1か月 | S75: 手動 | T75: Teamsにて完了連絡 | U75: 〇 | V75: 〇 | W75: Security | X75: 井上さん（Inoue, Yosuke B.）、 ナカムラさん（Nakamura, Keina）、 トマツさん（Tomatsu, Yuki）、 サトウさん（Sato, Hideaki A.） | Z75: サービス停止 | AA75: 44317 | AB75: ー | AC75: FY24以前 | AD75: ー | AI75: ー | AJ75: ー | AK75: ー | AL75: ー | AM75: 45674 | AN75: 2021年5月31日よりサービス開始 2023年7月20日 : サービス停止 | AO75: - | AS75: (サービス停止) | AT75: 9.対応不要 | AV75: 45785 | AY75: =IF(D75="受託",IF(COUNTA(B75,F75,G75:J75,Z75:AA75)=8,"OK","NG"),"確認対象外") -> OK | AZ75: =ISNUMBER(AJ75) -> FALSE | BA75: =ROW()-7 -> 68 | BB75: e
A76: =IF(Z76="サービス停止",Z76,"") -> サービス停止 | B76: A1048 | C76: =IF(B76="","-",IF(COUNTIF($B$8:B76,B76)=1,"〇","×")) -> 〇 | D76: 受託 | E76: SN_0048 | F76: 01調査・結果纏め | G76: Security_リサーチ | H76: V&A企業買収、候補企業の売上、従業員数など基本情報を確認する。企業情報を更新するわけではなく、ゼロから企業の基本情報を調べる。 | I76: 生麦 | J76: 生麦Z | K76: hiroshi.a.harashima | L76: 無 | M76: 随時 | N76: Teamsチャネルにて依頼。依頼時、最終提出日をTeamsチャネルにて報告。週次25件で計算。 | O76: 5営業日。25件/週を目安。週次で提出 （5営業日分を10から20件を想定し、それ以上の場合は、納期を連絡し、1週間毎に状況報告） | P76: 有(Teams) レビューバック反映も実施する | Q76: サテライトTeams | R76: 1か月 | S76: 手動 | T76: Teamsにて完了連絡 | U76: × | V76: × | W76: Security | X76: 坂本さん（Sakamoto, Keisuke） 福井さん（Fukui, Issei） 井上さん（Inoue, Yosuke B.） | Z76: サービス停止 | AA76: 44317 | AB76: ー | AC76: FY24以前 | AD76: ー | AI76: ー | AJ76: ー | AK76: ー | AL76: ー | AM76: 45674 | AN76: 2021年5月31日よりサービス開始 2023年6月2日：サービス停止 | AO76: - | AS76: (サービス停止) | AT76: 9.対応不要 | AV76: 45785 | AY76: =IF(D76="受託",IF(COUNTA(B76,F76,G76:J76,Z76:AA76)=8,"OK","NG"),"確認対象外") -> OK | AZ76: =ISNUMBER(AJ76) -> FALSE | BA76: =ROW()-7 -> 69 | BB76: e
A77: =IF(Z77="サービス停止",Z77,"") -> サービス停止 | C77: =IF(B77="","-",IF(COUNTIF($B$8:B77,B77)=1,"〇","×")) -> - | D77: 受託 | E77: ST_0022 | G77: SONY GLOBAL_MMS新規登録業務 | H77: SONY GLOBALチームにて新規案件や契約の機会が発生した際のMMS(Manage mysales・アクセンチュアの案件管理システム)への情報登録作業を実施する。 | I77: 立川 | K77: shinichi.fukasawa | L77: 無 | M77: 随時 | N77: リクエストフォーム | O77: 依頼日＋１営業日 | P77: 有 | Q77: メールにてopportunityIDを共有 | R77: 1か月 | S77: 手動 | T77: メール | U77: 〇 | V77: 〇 | W77: CMT | X77: Butsuen, Miwa <miwa.butsuen@accenture.com> | Z77: サービス停止 | AA77: 44350 | AB77: ー | AC77: FY24以前 | AD77: ー | AI77: ー | AJ77: ー | AK77: ー | AL77: ー | AM77: 45674 | AN77: 2021/6/3 本稼働判定フォームへ記入あり。 （2022/7/1）サービス停止 メールタイトル：RE: <再送>: 【ご確認依頼】SONY GLOBAL_MMS新規登録業務について | AO77: - | AS77: (サービス停止) | AT77: 9.対応不要 | AV77: 45785 | AY77: =IF(D77="受託",IF(COUNTA(B77,F77,G77:J77,Z77:AA77)=8,"OK","NG"),"確認対象外") -> NG | AZ77: =ISNUMBER(AJ77) -> FALSE | BA77: =ROW()-7 -> 70 | BB77: e
A78: =IF(Z78="サービス停止",Z78,"") -> サービス停止 | B78: A2023 | C78: =IF(B78="","-",IF(COUNTIF($B$8:B78,B78)=1,"〇","×")) -> 〇 | D78: 受託 | E78: ST_0023 | F78: 07入力・登録代行 | G78: Interactive_請求書発行 | H78: 請求書発行の代行 | I78: 立川 | J78: 立川X | K78: akiko.a.hirano | L78: 無 | M78: 指定Period | N78: teams | O78: 25日締め | P78: 有 | Q78: DocuSignへの登録をもって完了 | R78: 1か月 | S78: 自動 | T78: メール | U78: 〇 | V78: 〇 | W78: Interactive | X78: Ihara, Hiroyuki <hiroyuki.ihara@accenture.com> | Z78: サービス停止 | AA78: 44409 | AB78: ー | AC78: FY24以前 | AD78: ー | AI78: ー | AJ78: ー | AK78: ー | AL78: ー | AM78: 45674 | AN78: 2023/3/17：サービス停止 | AO78: - | AS78: (サービス停止) | AT78: 9.対応不要 | AV78: 45785 | AY78: =IF(D78="受託",IF(COUNTA(B78,F78,G78:J78,Z78:AA78)=8,"OK","NG"),"確認対象外") -> OK | AZ78: =ISNUMBER(AJ78) -> FALSE | BA78: =ROW()-7 -> 71 | BB78: e
A79: =IF(Z79="サービス停止",Z79,"") -> サービス停止 | C79: =IF(B79="","-",IF(COUNTIF($B$8:B79,B79)=1,"〇","×")) -> - | D79: 受託 | E79: ST_0024 | G79: Interactive_契約見積書類作成・捺印申請 | H79: クラウド上で電子捺印を申請するにあたり、シェアポイント上での捺印申請及び、DocuSignへの登録を実施する | I79: 立川 | K79: kaori.ito | L79: 無 | M79: 指定Period | N79: teams | O79: 25日締め | P79: 有 | Q79: Teamsにて完了報告 | S79: 手動 | T79: teams | U79: 〇 | V79: 〇 | W79: Interactive | X79: Ihara, Hiroyuki <hiroyuki.ihara@accenture.com> Sakagami,Yuko<yuko.sakagami@imjp.co.jp> | Z79: サービス停止 | AB79: ー | AC79: FY24以前 | AD79: ー | AI79: ー | AJ79: ー | AK79: ー | AL79: ー | AM79: 45674 | AN79: (2021/9/13)システム変更のため、各種変更があり実施未定。 →CCJ側に確認し、ペンディングとなったため、一旦削除し、再開時に別途サービス起票することとする。 | AO79: - | AS79: (サービス停止) | AT79: 9.対応不要 | AV79: 45785 | AY79: =IF(D79="受託",IF(COUNTA(B79,F79,G79:J79,Z79:AA79)=8,"OK","NG"),"確認対象外") -> NG | AZ79: =ISNUMBER(AJ79) -> FALSE | BA79: =ROW()-7 -> 72 | BB79: e
A80: =IF(Z80="サービス停止",Z80,"") -> サービス停止 | C80: =IF(B80="","-",IF(COUNTIF($B$8:B80,B80)=1,"〇","×")) -> - | D80: 受託 | E80: ST_0025 | G80: Interactive_MMS新規登録業務 | H80: Interactiveチームにて新規案件や契約の機会が発生した際のMMS(Manage mysales・アクセンチュアの案件管理システム)への情報登録作業を実施する。 | I80: 立川 | K80: shinichi.fukasawa | L80: 無 | M80: 随時 | N80: リクエストフォーム | O80: 依頼日＋３営業日 | P80: 有 | Q80: メールにてopportunityIDを共有 | R80: 1か月 | S80: 手動 | T80: メール | U80: 〇 | V80: 〇 | W80: Interactive | X80: Ihara, Hiroyuki <hiroyuki.ihara@accenture.com> Sakagami,Yuko<yuko.sakagami@imjp.co.jp> | Z80: サービス停止 | AB80: ー | AC80: FY24以前 | AD80: ー | AI80: ー | AJ80: ー | AK80: ー | AL80: ー | AM80: 45674 | AN80: (2022/6/24)サービス停止 メールタイトル：RE: 【ご確認依頼】Interactive_MMS新規登録業務について | AO80: - | AS80: (サービス停止) | AT80: 9.対応不要 | AV80: 45785 | AY80: =IF(D80="受託",IF(COUNTA(B80,F80,G80:J80,Z80:AA80)=8,"OK","NG"),"確認対象外") -> NG | AZ80: =ISNUMBER(AJ80) -> FALSE | BA80: =ROW()-7 -> 73 | BB80: e
A81: =IF(Z81="サービス停止",Z81,"") | B81: A1049 | C81: =IF(B81="","-",IF(COUNTIF($B$8:B81,B81)=1,"〇","×")) -> 〇 | D81: 受託 | E81: SN_0049 | F81: 01調査・結果纏め | G81: Procurement_Supplier基本情報更新/ウェブサイト弊社名・ロゴ無断使用確認 | H81: supplierの会社情報(住所、URL、資本金、従業員数、アクセンチュアロゴ使用有無等)の調査 | I81: 生麦 | J81: 生麦X | K81: shigeki.ohtake | L81: 無 | M81: 半期 | N81: Sharepoint | O81: 3週間 | P81: 無 (提供後１カ月経過後、指摘がなければ無しとみなす) | Q81: シェアポイント | R81: 3か月 | S81: 手動 | T81: シェアポイントに格納 | U81: 〇 | V81: 〇 | W81: Procurement | X81: 上ノ山 Uenoyama, Kenichi <kenichi.uenoyama@accenture.com> 太田 Ohta, Wakako <wakako.ohta@accenture.com> | Z81: =IF(AC81="",IF(AA81="","",IF(TODAY()>=AA81,"サービス開始",IF(TODAY()<AA81,"本稼働前",""))),IF(TODAY()>=AC81,"サービス停止",IF(AA81="","",IF(TODAY()>=AA81,"サービス開始",IF(TODAY()<AA81,"本稼働前",""))))) -> サービス開始 | AA81: 44317 | AB81: ー | AE81: A0145(業務の一部) | AI81: Corporate Function | AJ81: 1 | AK81: ー | AL81: ー | AM81: 45674 | AN81: シェアポイントの権限は、accenture_satellite <accenture_satellite@accenture.com>で付与 ・2022/10/31：運用変更に伴い、頻度と納期（リードタイム）を修正 1月を目安に400件調査⇒半年に1度250件調査、作業期間：3週間 ・2025/12/10:一部業務内容をA0145(2026/1/1開始)へ移管 | AO81: - | AQ81: A_通常_決定(登録可) | AS81: 登録済_本登録 | AT81: 4b.本登録_計測方法確定(FY24以前) | AV81: 45785 | AY81: =IF(D81="受託",IF(COUNTA(B81,F81,G81:J81,Z81:AA81)=8,"OK","NG"),"確認対象外") -> OK | AZ81: =ISNUMBER(AJ81) -> TRUE | BA81: =ROW()-7 -> 74 | BB81: e
A82: =IF(Z82="サービス停止",Z82,"") | B82: A1050 | C82: =IF(B82="","-",IF(COUNTIF($B$8:B82,B82)=1,"〇","×")) -> 〇 | D82: 受託 | E82: SN_0050 | F82: 07入力・登録代行 | G82: CF_BI情報更新 | H82: 依頼元は対応案件を検討するため、依頼元で各SupplierのBI情報(＝Business Intermediary)をSharepoint上で一括管理していた。本業務は依頼元の代わりに、各Supplierの最新のBI情報を取得し、情報の更新を行う。 | I82: 生麦 | J82: 生麦Z | K82: =IFERROR(VLOOKUP([9]サービス一覧!J82,[9]List!$M$3:$N$24,2,FALSE)&"","") -> hiroyuki.yoshida | L82: 無 | M82: 月次 | N82: 依頼なしで、第一営業日に開始 また、作業開始をメール連絡 →2022/4時点：作業開始の報告はせず、完了報告のみ | O82: 1ヶ月（ほぼ20営業日） 2021/6/3時点での件数：1063件目標 2021/6/23時点での件数：最低600件 2022/4/8時点での件数：約350件前後 | P82: 無 | Q82: シェアポイント | R82: 依頼元が蓄積するデータで、サテライト側では関与しない （依頼元のシェアポイントで情報を管理し、随時更新するため） | S82: 手動 | T82: メール | U82: 〇 | V82: × | W82: CF | X82: 佐々木さん(aimi.sasaki) 報告メールのアドレス：PBPO_Japan_Cx@accenture.com | Z82: =IF(AC82="",IF(AA82="","",IF(TODAY()>=AA82,"サービス開始",IF(TODAY()<AA82,"本稼働前",""))),IF(TODAY()>=AC82,"サービス停止",IF(AA82="","",IF(TODAY()>=AA82,"サービス開始",IF(TODAY()<AA82,"本稼働前",""))))) -> サービス開始 | AA82: 44378 | AB82: ー | AI82: Corporate Function | AJ82: 1 | AK82: ー | AL82: ー | AM82: 45674 | AN82: 2021年6月28日よりサービス開始 (第1営業日開始のため、2021年7月よりサービス開始) 2026/3/1：担当SV変更（hiroshi.a.harashima → hiroyuki.yoshida） | AO82: - | AQ82: A_通常_決定(登録可) | AS82: 登録済_本登録 | AT82: 4b.本登録_計測方法確定(FY24以前) | AV82: 45785 | AY82: =IF(D82="受託",IF(COUNTA(B82,F82,G82:J82,Z82:AA82)=8,"OK","NG"),"確認対象外") -> OK | AZ82: =ISNUMBER(AJ82) -> TRUE | BA82: =ROW()-7 -> 75 | BB82: e
A83: =IF(Z83="サービス停止",Z83,"") | B83: A1051 | C83: =IF(B83="","-",IF(COUNTIF($B$8:B83,B83)=1,"〇","×")) -> 〇 | D83: 受託 | E83: SN_0051 | F83: 07入力・登録代行 | G83: CF_提案要員のスキルデータ登録 | H83: 依頼元にて提案要員情報・履歴書をsharepoint上に登録し、プロジェクト担当者に提案があった旨を共有している。 本業務では、提案要員のスキルデータをsharepoint上に登録し直すことで、依頼元で今までの提案要員のスキル情報を整理しやすくすることが可能となる業務。 | I83: 生麦 | J83: 生麦Z | K83: =IFERROR(VLOOKUP([9]サービス一覧!J83,[9]List!$M$3:$N$24,2,FALSE)&"","") -> hiroyuki.yoshida | L83: 無 | M83: 週次 | N83: 依頼なしで、新規要員を確認 作業対象をメール連絡 | O83: 5営業日 （報告週の前週火曜日～報告週月曜日登録分を、木曜日11時までに完了・進捗報告） | P83: 無 | Q83: シェアポイント | R83: 依頼元が蓄積するデータで、サテライト側では関与しない （依頼元のシェアポイントで情報を管理し、随時更新するため） | S83: 手動 | T83: メール | U83: 〇 | V83: 〇 sharepoint(Proposal List)へのアクセスが必要。メールorチャットにて佐々木さんに依頼 | W83: CF | X83: 佐々木さん(aimi.sasaki) 報告メールのアドレス：PBPO_Japan_Cx@accenture.com | Z83: =IF(AC83="",IF(AA83="","",IF(TODAY()>=AA83,"サービス開始",IF(TODAY()<AA83,"本稼働前",""))),IF(TODAY()>=AC83,"サービス停止",IF(AA83="","",IF(TODAY()>=AA83,"サービス開始",IF(TODAY()<AA83,"本稼働前",""))))) -> サービス開始 | AA83: 44378 | AB83: ー | AI83: Corporate Function | AJ83: 1 | AK83: ー | AL83: ー | AM83: 45674 | AN83: 2021年7月5日よりサービス開始 2026/3/1：担当SV変更（hiroshi.a.harashima → hiroyuki.yoshida） | AO83: - | AQ83: A_通常_決定(登録可) | AS83: 登録済_本登録 | AT83: 4b.本登録_計測方法確定(FY24以前) | AV83: 45785 | AY83: =IF(D83="受託",IF(COUNTA(B83,F83,G83:J83,Z83:AA83)=8,"OK","NG"),"確認対象外") -> OK | AZ83: =ISNUMBER(AJ83) -> TRUE | BA83: =ROW()-7 -> 76 | BB83: e
A84: =IF(Z84="サービス停止",Z84,"") | B84: P3001 | C84: =IF(B84="","-",IF(COUNTIF($B$8:B84,B84)=1,"〇","×")) -> 〇 | D84: 運営・改善 | E84: AS_0001 | F84: 運営・改善（データ計測未定） | G84: 業務改善ツール開発_立川Z | H84: 業務改善ツール開発チームで対応するタスク用のサービス。 詳細は、業務改善ツール開発チームのルールを参照。 | I84: 共通 | J84: 立川Z | K84: emiko.maeyama | L84: 無 | M84: 随時 | N84: 業務改善ツール開発チームのルールを順守 | O84: 業務改善ツール開発チームのルールを順守 | P84: ー | Q84: ー | R84: ー | S84: ー | T84: ー | U84: × | V84: × | W84: 内部対応のため、なし | X84: 内部対応のため、なし | Z84: =IF(AC84="",IF(AA84="","",IF(TODAY()>=AA84,"サービス開始",IF(TODAY()<AA84,"本稼働前",""))),IF(TODAY()>=AC84,"サービス停止",IF(AA84="","",IF(TODAY()>=AA84,"サービス開始",IF(TODAY()<AA84,"本稼働前",""))))) -> サービス開始 | AA84: 44383 | AB84: ー | AG84: 以下は同サービス内容 P3001,P3008,P3010,P3012,P3014,P3016,P3018 | AI84: ー | AJ84: ー | AK84: ー | AL84: ー | AM84: 45674 | AN84: 2021年7月から運用開始。 | AO84: - | AQ84: A_通常_決定(登録可) | AS84: 登録済_本登録 | AT84: 4b.本登録_計測方法確定(FY24以前) | AV84: 45785 | AY84: =IF(D84="受託",IF(COUNTA(B84,F84,G84:J84,Z84:AA84)=8,"OK","NG"),"確認対象外") -> 確認対象外 | AZ84: =ISNUMBER(AJ84) -> FALSE | BA84: =ROW()-7 -> 77 | BB84: e
A85: =IF(Z85="サービス停止",Z85,"") | B85: P3008 | C85: =IF(B85="","-",IF(COUNTIF($B$8:B85,B85)=1,"〇","×")) -> 〇 | D85: 運営・改善 | E85: AS_0001 | F85: 運営・改善（データ計測未定） | G85: 業務改善ツール開発_生麦X | H85: 業務改善ツール開発チームで対応するタスク用のサービス。 詳細は、業務改善ツール開発チームのルールを参照。 | I85: 共通 | J85: 生麦X | K85: emiko.maeyama | L85: 無 | M85: 随時 | N85: 業務改善ツール開発チームのルールを順守 | O85: 業務改善ツール開発チームのルールを順守 | P85: ー | Q85: ー | R85: ー | S85: ー | T85: ー | U85: × | V85: × | W85: 内部対応のため、なし | X85: 内部対応のため、なし | Z85: =IF(AC85="",IF(AA85="","",IF(TODAY()>=AA85,"サービス開始",IF(TODAY()<AA85,"本稼働前",""))),IF(TODAY()>=AC85,"サービス停止",IF(AA85="","",IF(TODAY()>=AA85,"サービス開始",IF(TODAY()<AA85,"本稼働前",""))))) -> 本稼働前 | AA85: 2026//71 | AB85: ー | AG85: 以下は同サービス内容 P3001,P3008,P3010,P3012,P3014,P3016,P3018 | AI85: ー | AJ85: ー | AK85: ー | AL85: ー | AM85: 45674 | AN85: 2021年7月から運用開始。 2026/6/5：2026年7月からの新運用に向けチーム個別のサービス管理番号を新たに設定。 | AO85: - | AQ85: A_通常_決定(登録可) | AS85: 登録済_本登録 | AT85: 4b.本登録_計測方法確定(FY24以前) | AV85: 45785 | AY85: =IF(D85="受託",IF(COUNTA(B85,F85,G85:J85,Z85:AA85)=8,"OK","NG"),"確認対象外") -> 確認対象外 | AZ85: =ISNUMBER(AJ85) -> FALSE | BA85: =ROW()-7 -> 78 | BB85: e
A86: =IF(Z86="サービス停止",Z86,"") | B86: P3010 | C86: =IF(B86="","-",IF(COUNTIF($B$8:B86,B86)=1,"〇","×")) -> 〇 | D86: 運営・改善 | E86: AS_0001 | F86: 運営・改善（データ計測未定） | G86: 業務改善ツール開発_生麦Y | H86: 業務改善ツール開発チームで対応するタスク用のサービス。 詳細は、業務改善ツール開発チームのルールを参照。 | I86: 共通 | J86: 生麦Y | K86: emiko.maeyama | L86: 無 | M86: 随時 | N86: 業務改善ツール開発チームのルールを順守 | O86: 業務改善ツール開発チームのルールを順守 | P86: ー | Q86: ー | R86: ー | S86: ー | T86: ー | U86: × | V86: × | W86: 内部対応のため、なし | X86: 内部対応のため、なし | Z86: =IF(AC86="",IF(AA86="","",IF(TODAY()>=AA86,"サービス開始",IF(TODAY()<AA86,"本稼働前",""))),IF(TODAY()>=AC86,"サービス停止",IF(AA86="","",IF(TODAY()>=AA86,"サービス開始",IF(TODAY()<AA86,"本稼働前",""))))) -> 本稼働前 | AA86: 2026//71 | AB86: ー | AG86: 以下は同サービス内容 P3001,P3008,P3010,P3012,P3014,P3016,P3018 | AI86: ー | AJ86: ー | AK86: ー | AL86: ー | AM86: 45674 | AN86: 2021年7月から運用開始。 2026/6/5：2026年7月からの新運用に向けチーム個別のサービス管理番号を新たに設定。 | AO86: - | AQ86: A_通常_決定(登録可) | AS86: 登録済_本登録 | AT86: 4b.本登録_計測方法確定(FY24以前) | AV86: 45785 | AY86: =IF(D86="受託",IF(COUNTA(B86,F86,G86:J86,Z86:AA86)=8,"OK","NG"),"確認対象外") -> 確認対象外 | AZ86: =ISNUMBER(AJ86) -> FALSE | BA86: =ROW()-7 -> 79 | BB86: e
A87: =IF(Z87="サービス停止",Z87,"") | B87: P3012 | C87: =IF(B87="","-",IF(COUNTIF($B$8:B87,B87)=1,"〇","×")) -> 〇 | D87: 運営・改善 | E87: AS_0001 | F87: 運営・改善（データ計測未定） | G87: 業務改善ツール開発_生麦Z | H87: 業務改善ツール開発チームで対応するタスク用のサービス。 詳細は、業務改善ツール開発チームのルールを参照。 | I87: 共通 | J87: 生麦Z | K87: emiko.maeyama | L87: 無 | M87: 随時 | N87: 業務改善ツール開発チームのルールを順守 | O87: 業務改善ツール開発チームのルールを順守 | P87: ー | Q87: ー | R87: ー | S87: ー | T87: ー | U87: × | V87: × | W87: 内部対応のため、なし | X87: 内部対応のため、なし | Z87: =IF(AC87="",IF(AA87="","",IF(TODAY()>=AA87,"サービス開始",IF(TODAY()<AA87,"本稼働前",""))),IF(TODAY()>=AC87,"サービス停止",IF(AA87="","",IF(TODAY()>=AA87,"サービス開始",IF(TODAY()<AA87,"本稼働前",""))))) -> 本稼働前 | AA87: 2026//71 | AB87: ー | AG87: 以下は同サービス内容 P3001,P3008,P3010,P3012,P3014,P3016,P3018 | AI87: ー | AJ87: ー | AK87: ー | AL87: ー | AM87: 45674 | AN87: 2021年7月から運用開始。 2026/6/5：2026年7月からの新運用に向けチーム個別のサービス管理番号を新たに設定。 | AO87: - | AQ87: A_通常_決定(登録可) | AS87: 登録済_本登録 | AT87: 4b.本登録_計測方法確定(FY24以前) | AV87: 45785 | AY87: =IF(D87="受託",IF(COUNTA(B87,F87,G87:J87,Z87:AA87)=8,"OK","NG"),"確認対象外") -> 確認対象外 | AZ87: =ISNUMBER(AJ87) -> FALSE | BA87: =ROW()-7 -> 80 | BB87: e
A88: =IF(Z88="サービス停止",Z88,"") | B88: P3014 | C88: =IF(B88="","-",IF(COUNTIF($B$8:B88,B88)=1,"〇","×")) -> 〇 | D88: 運営・改善 | E88: AS_0001 | F88: 運営・改善（データ計測未定） | G88: 業務改善ツール開発_立川Y1 | H88: 業務改善ツール開発チームで対応するタスク用のサービス。 詳細は、業務改善ツール開発チームのルールを参照。 | I88: 共通 | J88: 立川Y1 | K88: emiko.maeyama | L88: 無 | M88: 随時 | N88: 業務改善ツール開発チームのルールを順守 | O88: 業務改善ツール開発チームのルールを順守 | P88: ー | Q88: ー | R88: ー | S88: ー | T88: ー | U88: × | V88: × | W88: 内部対応のため、なし | X88: 内部対応のため、なし | Z88: =IF(AC88="",IF(AA88="","",IF(TODAY()>=AA88,"サービス開始",IF(TODAY()<AA88,"本稼働前",""))),IF(TODAY()>=AC88,"サービス停止",IF(AA88="","",IF(TODAY()>=AA88,"サービス開始",IF(TODAY()<AA88,"本稼働前",""))))) -> 本稼働前 | AA88: 2026//71 | AB88: ー | AG88: 以下は同サービス内容 P3001,P3008,P3010,P3012,P3014,P3016,P3018 | AI88: ー | AJ88: ー | AK88: ー | AL88: ー | AM88: 45674 | AN88: 2021年7月から運用開始。 2026/6/5：2026年7月からの新運用に向けチーム個別のサービス管理番号を新たに設定。 | AO88: - | AQ88: A_通常_決定(登録可) | AS88: 登録済_本登録 | AT88: 4b.本登録_計測方法確定(FY24以前) | AV88: 45785 | AY88: =IF(D88="受託",IF(COUNTA(B88,F88,G88:J88,Z88:AA88)=8,"OK","NG"),"確認対象外") -> 確認対象外 | AZ88: =ISNUMBER(AJ88) -> FALSE | BA88: =ROW()-7 -> 81 | BB88: e
A89: =IF(Z89="サービス停止",Z89,"") | B89: P3016 | C89: =IF(B89="","-",IF(COUNTIF($B$8:B89,B89)=1,"〇","×")) -> 〇 | D89: 運営・改善 | E89: AS_0001 | F89: 運営・改善（データ計測未定） | G89: 業務改善ツール開発_立川Y2 | H89: 業務改善ツール開発チームで対応するタスク用のサービス。 詳細は、業務改善ツール開発チームのルールを参照。 | I89: 共通 | J89: 立川Y2 | K89: emiko.maeyama | L89: 無 | M89: 随時 | N89: 業務改善ツール開発チームのルールを順守 | O89: 業務改善ツール開発チームのルールを順守 | P89: ー | Q89: ー | R89: ー | S89: ー | T89: ー | U89: × | V89: × | W89: 内部対応のため、なし | X89: 内部対応のため、なし | Z89: =IF(AC89="",IF(AA89="","",IF(TODAY()>=AA89,"サービス開始",IF(TODAY()<AA89,"本稼働前",""))),IF(TODAY()>=AC89,"サービス停止",IF(AA89="","",IF(TODAY()>=AA89,"サービス開始",IF(TODAY()<AA89,"本稼働前",""))))) -> 本稼働前 | AA89: 2026//71 | AB89: ー | AG89: 以下は同サービス内容 P3001,P3008,P3010,P3012,P3014,P3016,P3018 | AI89: ー | AJ89: ー | AK89: ー | AL89: ー | AM89: 45674 | AN89: 2021年7月から運用開始。 2026/6/5：2026年7月からの新運用に向けチーム個別のサービス管理番号を新たに設定。 | AO89: - | AQ89: A_通常_決定(登録可) | AS89: 登録済_本登録 | AT89: 4b.本登録_計測方法確定(FY24以前) | AV89: 45785 | AY89: =IF(D89="受託",IF(COUNTA(B89,F89,G89:J89,Z89:AA89)=8,"OK","NG"),"確認対象外") -> 確認対象外 | AZ89: =ISNUMBER(AJ89) -> FALSE | BA89: =ROW()-7 -> 82 | BB89: e
A90: =IF(Z90="サービス停止",Z90,"") | B90: P3018 | C90: =IF(B90="","-",IF(COUNTIF($B$8:B90,B90)=1,"〇","×")) -> 〇 | D90: 運営・改善 | E90: AS_0001 | F90: 運営・改善（データ計測未定） | G90: 業務改善ツール開発_中津Y | H90: 業務改善ツール開発チームで対応するタスク用のサービス。 詳細は、業務改善ツール開発チームのルールを参照。 | I90: 共通 | J90: 中津Y | K90: emiko.maeyama | L90: 無 | M90: 随時 | N90: 業務改善ツール開発チームのルールを順守 | O90: 業務改善ツール開発チームのルールを順守 | P90: ー | Q90: ー | R90: ー | S90: ー | T90: ー | U90: × | V90: × | W90: 内部対応のため、なし | X90: 内部対応のため、なし | Z90: =IF(AC90="",IF(AA90="","",IF(TODAY()>=AA90,"サービス開始",IF(TODAY()<AA90,"本稼働前",""))),IF(TODAY()>=AC90,"サービス停止",IF(AA90="","",IF(TODAY()>=AA90,"サービス開始",IF(TODAY()<AA90,"本稼働前",""))))) -> 本稼働前 | AA90: 2026//71 | AB90: ー | AG90: 以下は同サービス内容 P3001,P3008,P3010,P3012,P3014,P3016,P3018 | AI90: ー | AJ90: ー | AK90: ー | AL90: ー | AM90: 45674 | AN90: 2021年7月から運用開始。 2026/6/5：2026年7月からの新運用に向けチーム個別のサービス管理番号を新たに設定。 | AO90: - | AQ90: A_通常_決定(登録可) | AS90: 登録済_本登録 | AT90: 4b.本登録_計測方法確定(FY24以前) | AV90: 45785 | AY90: =IF(D90="受託",IF(COUNTA(B90,F90,G90:J90,Z90:AA90)=8,"OK","NG"),"確認対象外") -> 確認対象外 | AZ90: =ISNUMBER(AJ90) -> FALSE | BA90: =ROW()-7 -> 83 | BB90: e
A91: =IF(Z91="サービス停止",Z91,"") -> サービス停止 | C91: =IF(B91="","-",IF(COUNTIF($B$8:B91,B91)=1,"〇","×")) -> - | D91: 受託 | E91: ST_0026 | G91: HPS_業務概要の要約(仮) | H91: ST_0017 分割分？ →ST_0016 | I91: 立川 | K91: kaori.ito | Z91: サービス停止 | AB91: ー | AC91: FY24以前 | AD91: ー | AI91: ー | AJ91: ー | AK91: ー | AL91: ー | AM91: 45674 | AN91: ST_0016にマージしたため、削除 | AO91: - | AS91: (サービス停止) | AT91: 9.対応不要 | AV91: 45785 | AY91: =IF(D91="受託",IF(COUNTA(B91,F91,G91:J91,Z91:AA91)=8,"OK","NG"),"確認対象外") -> NG | AZ91: =ISNUMBER(AJ91) -> FALSE | BA91: =ROW()-7 -> 84 | BB91: e
A92: =IF(Z92="サービス停止",Z92,"") | B92: A1052 | C92: =IF(B92="","-",IF(COUNTIF($B$8:B92,B92)=1,"〇","×")) -> 〇 | D92: 受託 | E92: SN_0052 | F92: 06連絡代行 | G92: HPS_JPiT_MyTE勤怠予定実績チェック | H92: PJTメンバーがmyTE入力およびExpense封筒を提出するように促すためにアナウンスメールを送付、 およびPJTメンバーがmyTE申請するにあたり、クライアント先での入室ログ・作業実績情報とmyTEの申告が残業時間含め、正しく入力されているかJPiT_PMの代わりに確認する。またExpenseの一部ないよについても確認する。 | I92: 生麦 | J92: 生麦X | K92: shigeki.ohtake | L92: 無 | M92: 隔週 | N92: 依頼なしで、各ピリオドの９営業日前に開始 | O92: 各ピリオドの前営業日 | P92: 無 | Q92: メール、シェアポイント | R92: 依頼元が蓄積するデータで、サテライト側では関与しない （依頼元のシェアポイントで情報を管理し、随時更新するため） | S92: 手動 | T92: メール | U92: 〇 | V92: 〇 | W92: HPS | X92: 和田さん（Wada,Ikumii） | Z92: =IF(AC92="",IF(AA92="","",IF(TODAY()>=AA92,"サービス開始",IF(TODAY()<AA92,"本稼働前",""))),IF(TODAY()>=AC92,"サービス停止",IF(AA92="","",IF(TODAY()>=AA92,"サービス開始",IF(TODAY()<AA92,"本稼働前",""))))) -> サービス開始 | AA92: 44396 | AB92: ー | AI92: Client Service Group | AJ92: 1 | AK92: ー | AL92: ー | AM92: 45674 | AN92: 2024/7/2：サービスカテゴリを連絡・確認代行 → 連絡代行に変更 | AO92: - | AQ92: A_通常_決定(登録可) | AS92: 登録済_本登録 | AT92: 4b.本登録_計測方法確定(FY24以前) | AV92: 45785 | AY92: =IF(D92="受託",IF(COUNTA(B92,F92,G92:J92,Z92:AA92)=8,"OK","NG"),"確認対象外") -> OK | AZ92: =ISNUMBER(AJ92) -> TRUE | BA92: =ROW()-7 -> 85 | BB92: e
A93: =IF(Z93="サービス停止",Z93,"") | B93: A1053 | C93: =IF(B93="","-",IF(COUNTIF($B$8:B93,B93)=1,"〇","×")) -> 〇 | D93: 受託 | E93: SN_0053 | F93: 91TBD_仮登録 | G93: Interactive_Advocate Program受講状況確認 | H93: 本業務では、アクセンチュア社員にとって必須研修であるAdvocate Programの受講状況を確認するためのリスト作成及び、未受講者とPillar leadに対するフォローメールの下書き作成を実施する。リスト及びメールは、期限内にメンバー全員に研修を受講させるために使用される。 | I93: 生麦 | J93: 生麦X | K93: shigeki.ohtake | L93: 無 | M93: 月次 | N93: 依頼なしで、毎月第1営業日に開始 | O93: 10営業日 | P93: 有 | Q93: メール、シェアポイント | R93: 依頼元が蓄積するデータで、サテライト側では関与しない （依頼元のシェアポイントで情報を管理し、随時更新するため） | S93: 手動 | T93: メール | U93: 〇 | V93: 〇 | W93: Interactive | X93: 大河原さん（hisako.ohkawara） | Z93: =IF(AC93="",IF(AA93="","",IF(TODAY()>=AA93,"サービス開始",IF(TODAY()<AA93,"本稼働前",""))),IF(TODAY()>=AC93,"サービス停止",IF(AA93="","",IF(TODAY()>=AA93,"サービス開始",IF(TODAY()<AA93,"本稼働前",""))))) -> サービス開始 | AA93: 44409 | AB93: ー | AI93: Song | AJ93: 1 | AK93: ー | AL93: ー | AM93: 45674 | AN93: 2024/7/2：サービスカテゴリを連絡・確認代行 → 連絡代行に変更 | AO93: - | AQ93: C_通常_未定(仮登録可) | AS93: 登録済_仮登録 | AT93: 2b.仮登録_計測方法未定(FY24以前) | AV93: 45785 | AY93: =IF(D93="受託",IF(COUNTA(B93,F93,G93:J93,Z93:AA93)=8,"OK","NG"),"確認対象外") -> OK | AZ93: =ISNUMBER(AJ93) -> TRUE | BA93: =ROW()-7 -> 86 | BB93: e
A94: =IF(Z94="サービス停止",Z94,"") -> サービス停止 | B94: A1054 | C94: =IF(B94="","-",IF(COUNTIF($B$8:B94,B94)=1,"〇","×")) -> 〇 | D94: 受託 | E94: SN_0054 | F94: 01調査・結果纏め | G94: Security_脆弱性情報 | H94: 本業務では、脆弱性(コンピュータに存在する情報セキュリティ上の欠陥)をいち早く認知するために、依頼元の代わりに定期的に脆弱性の情報をチェックする業務である。チェック結果をもとに、コンピューターセキュリティ面に影響が生じる恐れがある場合は依頼元で必要なアクションを実行する。 | I94: 生麦 | J94: 生麦X | K94: shigeki.ohtake | L94: 無 | M94: 週次 | N94: 依頼なしで、毎週第1営業日に開始 | O94: ５営業日 | P94: 無し | Q94: Teams、メール | R94: 依頼元が蓄積するデータで、サテライト側では関与しない （依頼元のシェアポイントで情報を管理し、随時更新するため） | S94: 手動 | T94: Teams、メール | U94: × | V94: × | W94: Security | X94: 福井さん（Fukui, Issei） | Z94: =IF(AC94="",IF(AA94="","",IF(TODAY()>=AA94,"サービス開始",IF(TODAY()<AA94,"本稼働前",""))),IF(TODAY()>=AC94,"サービス停止",IF(AA94="","",IF(TODAY()>=AA94,"サービス開始",IF(TODAY()<AA94,"本稼働前",""))))) -> サービス停止 | AA94: 44410 | AB94: ー | AC94: 45531 | AD94: ー | AI94: ー | AJ94: ー | AK94: ー | AL94: ー | AM94: 45674 | AN94: 2024/7/2：サービスカテゴリを連絡・確認代行 → 調査・結果纏めに変更 | AO94: - | AS94: (サービス停止) | AT94: 9.対応不要 | AV94: 45785 | AY94: =IF(D94="受託",IF(COUNTA(B94,F94,G94:J94,Z94:AA94)=8,"OK","NG"),"確認対象外") -> OK | AZ94: =ISNUMBER(AJ94) -> FALSE | BA94: =ROW()-7 -> 87 | BB94: e
A95: =IF(Z95="サービス停止",Z95,"") | B95: A1055 | C95: =IF(B95="","-",IF(COUNTIF($B$8:B95,B95)=1,"〇","×")) -> 〇 | D95: 受託 | E95: SN_0055 | F95: 01調査・結果纏め | G95: HPS_ニュースクリップとりまとめ支援 | H95: HPSの関連記事(キーワードに基いて)をFactivaメールから収集し、毎日依頼元に提供する。 | I95: 生麦 | J95: 生麦Y | K95: atsushi.b.yamamoto | L95: 無 | M95: 日次 | N95: 依頼なしで、日々受信するFactivaメール記事を基に開始 | O95: 月～木 その日の17～18時までに納品する。 | P95: 有り | Q95: Teams | R95: １年 データ格納は案件リストも起票日ではなく収集開始日を基準に月別に格納。1/31-2/3の時は１月のフォルダに格納。 | S95: 手動 | T95: Teams | U95: × | V95: × | W95: HPS | X95: 若月さん (Wakatsuki, Takako ）派遣社員 アクセンチュア責任者 岡島ＭＤ(Okajima, Takuto) teamsの権限は若月さんのみで岡島MDのアクセス権限なし。必要に応じて個別対応する。 | Z95: =IF(AC95="",IF(AA95="","",IF(TODAY()>=AA95,"サービス開始",IF(TODAY()<AA95,"本稼働前",""))),IF(TODAY()>=AC95,"サービス停止",IF(AA95="","",IF(TODAY()>=AA95,"サービス開始",IF(TODAY()<AA95,"本稼働前",""))))) -> サービス開始 | AA95: 44466 | AB95: ー | AI95: Client Service Group | AJ95: 1 | AK95: ー | AL95: ー | AM95: 45674 | AN95: 2024/7/1：担当SV変更＞emiko.maeyama ➡ atsushi.b.yamamoto | AO95: - | AQ95: A_通常_決定(登録可) | AS95: 登録済_本登録 | AT95: 4b.本登録_計測方法確定(FY24以前) | AV95: 45785 | AY95: =IF(D95="受託",IF(COUNTA(B95,F95,G95:J95,Z95:AA95)=8,"OK","NG"),"確認対象外") -> OK | AZ95: =ISNUMBER(AJ95) -> TRUE | BA95: =ROW()-7 -> 88 | BB95: e
A96: =IF(Z96="サービス停止",Z96,"") -> サービス停止 | C96: =IF(B96="","-",IF(COUNTIF($B$8:B96,B96)=1,"〇","×")) -> - | D96: 受託 | E96: SN_0056 | G96: Web調査 | H96: 特定の企業のホームページを参照し、必要情報を収集、リスト化する。 | I96: 生麦 | K96: shigeki.ohtake | L96: 無 | M96: 随時 | N96: 調整中 | O96: トライアルのため、調整中 | P96: 無し | Q96: Teams | R96: 1か月 | S96: 手動 | T96: Teams | U96: × | V96: × | X96: 千代崎さん (toga.chiyozaki) | Z96: サービス停止 | AA96: 44445 | AB96: ー | AC96: FY23 8月以前 | AD96: ー | AI96: ー | AJ96: ー | AK96: ー | AL96: ー | AM96: 45674 | AO96: - | AS96: (サービス停止) | AT96: 9.対応不要 | AV96: 45785 | AY96: =IF(D96="受託",IF(COUNTA(B96,F96,G96:J96,Z96:AA96)=8,"OK","NG"),"確認対象外") -> NG | AZ96: =ISNUMBER(AJ96) -> FALSE | BA96: =ROW()-7 -> 89 | BB96: e
A97: =IF(Z97="サービス停止",Z97,"") -> サービス停止 | C97: =IF(B97="","-",IF(COUNTIF($B$8:B97,B97)=1,"〇","×")) -> - | D97: 受託 | E97: SN_0057 | G97: Security_Cyber Fusion Center脆弱性調査業務 | H97: 各社の脆弱性情報を日次で2回チェックする 対象、17ベンダー(2021/9時点) | I97: 生麦 | K97: hiroshi.a.harashima | L97: 無 | M97: 日次 | N97: 依頼なしで、各脆弱性情報サイトをチェック | O97: 日々、午前/午後の2回 | P97: 無 | Q97: メール | R97: ？ | S97: 手動 | T97: メール | U97: × | V97: × | W97: Security | X97: 佐藤さん（tatsuki.sato） | Z97: サービス停止 | AB97: ー | AC97: FY24以前 | AD97: ー | AI97: ー | AJ97: ー | AK97: ー | AL97: ー | AM97: 45674 | AN97: 依頼元都合により、稼働前キャンセル | AO97: - | AS97: (サービス停止) | AT97: 9.対応不要 | AV97: 45785 | AY97: =IF(D97="受託",IF(COUNTA(B97,F97,G97:J97,Z97:AA97)=8,"OK","NG"),"確認対象外") -> NG | AZ97: =ISNUMBER(AJ97) -> FALSE | BA97: =ROW()-7 -> 90 | BB97: e
A98: =IF(Z98="サービス停止",Z98,"") -> サービス停止 | C98: =IF(B98="","-",IF(COUNTIF($B$8:B98,B98)=1,"〇","×")) -> - | D98: 受託 | E98: ST_0027 | G98: Security_Cyber Fusion Center脆弱性調査業務 | H98: SN_0057と同じ | I98: 立川 | K98: hiroshi.a.harashima | S98: 手動 | T98: メール | U98: × | V98: × | W98: Security | X98: 佐藤さん（tatsuki.sato） | Z98: サービス停止 | AB98: ー | AC98: FY24以前 | AD98: ー | AI98: ー | AJ98: ー | AK98: ー | AL98: ー | AM98: 45674 | AN98: 依頼元都合により、稼働前キャンセル | AO98: - | AS98: (サービス停止) | AT98: 9.対応不要 | AV98: 45785 | AY98: =IF(D98="受託",IF(COUNTA(B98,F98,G98:J98,Z98:AA98)=8,"OK","NG"),"確認対象外") -> NG | AZ98: =ISNUMBER(AJ98) -> FALSE | BA98: =ROW()-7 -> 91 | BB98: e
A99: =IF(Z99="サービス停止",Z99,"") -> サービス停止 | C99: =IF(B99="","-",IF(COUNTIF($B$8:B99,B99)=1,"〇","×")) -> - | D99: 受託 | E99: SN_0058 | G99: KDDI_労務管理 | H99: KDDI_労務管理 | I99: 生麦 | K99: shigeki.ohtake | L99: 無 | M99: 日次 | N99: 依頼なしで、シェアポのメンバー対象リストをチェック | O99: 日々、13時まで1回 | P99: 無 | Q99: Teams、メール | R99: なし | S99: 手動 | T99: Teams | U99: × | V99: × | W99: ARISE | X99: 松村さん（Matsumura, Atsuko） | Z99: サービス停止 | AA99: 44470 | AB99: ー | AC99: FY24以前 | AD99: ー | AI99: ー | AJ99: ー | AK99: ー | AL99: ー | AM99: 45674 | AN99: 依頼元都合により、稼働前キャンセル | AO99: - | AS99: (サービス停止) | AT99: 9.対応不要 | AV99: 45785 | AY99: =IF(D99="受託",IF(COUNTA(B99,F99,G99:J99,Z99:AA99)=8,"OK","NG"),"確認対象外") -> NG | AZ99: =ISNUMBER(AJ99) -> FALSE | BA99: =ROW()-7 -> 92 | BB99: e
A100: =IF(Z100="サービス停止",Z100,"") -> サービス停止 | C100: =IF(B100="","-",IF(COUNTIF($B$8:B100,B100)=1,"〇","×")) -> - | D100: 受託 | E100: ST_0028 | G100: 企業情報調査 | H100: CCJ_小学校設立のプロジェクトに協賛している企業の情報を調査し管理Excelに転記する。 | I100: 立川 | K100: shinichi.fukasawa | L100: 無 | M100: 随時 | N100: 単発依頼 | O100: 2日 | P100: 無 | Q100: メール | R100: 1か月 | S100: 手動 | T100: メール | U100: 〇 | V100: × | W100: CCJ | X100: 立原さん（syuhei.tachihara） | Z100: サービス停止 | AA100: 44470 | AB100: ー | AC100: FY24以前 | AD100: ー | AI100: ー | AJ100: ー | AK100: ー | AL100: ー | AM100: 45674 | AO100: - | AS100: (サービス停止) | AT100: 9.対応不要 | AV100: 45785 | AY100: =IF(D100="受託",IF(COUNTA(B100,F100,G100:J100,Z100:AA100)=8,"OK","NG"),"確認対象外") -> NG | AZ100: =ISNUMBER(AJ100) -> FALSE | BA100: =ROW()-7 -> 93 | BB100: e
...

Sheet プルダウンリスト
B1: ***Highly Confidential. Not To Be Distributed Further Without Authorization of the Sender. *** Copyright © 2026 Accenture. All rights reserved.
B2: PJT・サテライトのみ共有可
B4: 案件ステータス | C4: タスクステータス
B5: タスク進行中 | C5: 未着手
B6: デリバリ完了 | C6: 実行作業中
B7: 取消 | C7: ピアレビュー中
B8: 内部完了 | C8: ピアレビューFB反映中
C9: SVレビュー中
C10: SVレビューFB反映中
C11: 依頼元レビュー中
C12: 依頼元レビューFB反映中
C13: 依頼元/内部レビュー完了
C14: タスク取消

Sheet Work-->

Sheet OrderList案件登録情報一覧_生麦X_0608
B1: ***Highly Confidential. Not To Be Distributed Further Without Authorization of the Sender. *** Copyright © 2026 Accenture. All rights reserved.
B2: PJT・サテライトのみ共有可
A4: フロー番号 | B4: サービス番号 | C4: サービス名 | D4: 案件番号 | E4: 案件名 | F4: チーム(案件) | G4: 案件ステータス | H4: タスク番号 | I4: タスク名 | J4: タスクステータス | K4: 実行作業担当者 | L4: ピアレビュー担当者 | M4: SVレビュー担当者 | N4: 実行作業開始予定日 | O4: ピアレビュー開始予定日 | P4: SVレビュー開始予定日 | Q4: タスク完了予定日
A5: F009536-01 | B5: A0098 | C5: HR_myTIM/OTデータ作成(Google) | D5: A0098-0032 | E5: 【OT】HR_myTIM/OTデータ作成(Google) 12月度 | F5: 生麦X | G5: デリバリ完了 | H5: A0098-0032-01 | I5: 【OT】HR_myTIM/OTデータ作成(Google) 12月度 調査依頼メール | J5: 集計完了 | K5: rintaro.watanabe | L5: shunsuke.taniguchi | M5: ryusei.inaba | N5: 46000 | O5: 46000 | P5: 46000 | Q5: 46000
A6: F009536-01 | B6: A0098 | C6: HR_myTIM/OTデータ作成(Google) | D6: A0098-0032 | E6: 【OT】HR_myTIM/OTデータ作成(Google) 12月度 | F6: 生麦X | G6: デリバリ完了 | H6: A0098-0032-02 | I6: 【OT】HR_myTIM/OTデータ作成(Google) 12月度 リマインド➀ | J6: 集計完了 | K6: rintaro.watanabe | L6: shunsuke.taniguchi | M6: ryusei.inaba | N6: 46002 | O6: 46002 | P6: 46002 | Q6: 46002
A7: F009536-01 | B7: A0098 | C7: HR_myTIM/OTデータ作成(Google) | D7: A0098-0032 | E7: 【OT】HR_myTIM/OTデータ作成(Google) 12月度 | F7: 生麦X | G7: デリバリ完了 | H7: A0098-0032-03 | I7: 【OT】HR_myTIM/OTデータ作成(Google) 12月度 リマインド② | J7: 集計完了 | K7: rintaro.watanabe | L7: shunsuke.taniguchi | M7: ryusei.inaba | N7: 46003 | O7: 46003 | P7: 46003 | Q7: 46003
A8: F009536-01 | B8: A0098 | C8: HR_myTIM/OTデータ作成(Google) | D8: A0098-0032 | E8: 【OT】HR_myTIM/OTデータ作成(Google) 12月度 | F8: 生麦X | G8: デリバリ完了 | H8: A0098-0032-04 | I8: 【OT】HR_myTIM/OTデータ作成(Google) 12月度 完了報告 | J8: 集計完了 | K8: rintaro.watanabe | L8: shunsuke.taniguchi | M8: ryusei.inaba | N8: 46006 | O8: 46006 | P8: 46006 | Q8: 46006
B9: P1999 | C9: テスト運用サービス(SN) | D9: P1999-0073 | E9: 【テスト運用】HPS_JPiT月次基盤資料作成 | F9: 生麦X | G9: デリバリ完了 | H9: P1999-0073-01 | I9: 【テスト運用】HPS_JPiT月次基盤資料作成 | J9: 集計完了 | K9: kazuma.motoyama | L9: kazuma.motoyama | M9: kazuma.motoyama | N9: 45356 | O9: 45356 | P9: 45373 | Q9: 45373
A10: F011644-01 | B10: P3999 | C10: テスト運用サービス・データ計測不可(共通) | D10: P3999-1986 | E10: 【杉山さん】ツール練習 | F10: 生麦X | G10: デリバリ完了 | H10: P3999-1986-01 | I10: 【杉山さん】ツール練習 | J10: 集計完了 | K10: joi.sugiyama | L10: manami.nanbu | M10: shingo.a.maeda | N10: 46149 | O10: 46149 | P10: 46149 | Q10: 46149
A11: F011686-01 | B11: A1031 | C11: I&D_Women's stories記事配信 | D11: A1031-0279 | E11: I&D_Women's stories記事配信 英訳追加① No1～7 | F11: 生麦X | G11: タスク進行中 | H11: A1031-0279-01 | I11: I&D_Women's stories記事配信 英訳追加① No1～7 | J11: ピアレビュー | K11: riamu.daikusu | L11: rintaro.watanabe | M11: ryota.nozawa | N11: 46153 | O11: 46153 | P11: 46185 | Q11: 46185
A12: F011687-1 | B12: A1031 | C12: I&D_Women's stories記事配信 | D12: A1031-0280 | E12: I&D_Women's stories記事配信 英訳追加② No8～13 | F12: 生麦X | G12: 内部完了 | H12: A1031-0280-01 | I12: I&D_Women's stories記事配信 英訳追加② No8～13 | J12: 集計完了 | K12: rintaro.watanabe | L12: riamu.daikusu | M12: ryota.nozawa | N12: 46153 | O12: 46153 | P12: 46185 | Q12: 46185
B13: P1999 | C13: テスト運用サービス(SN) | D13: P1999-0011 | E13: IC-Energy_石油3社のプレスリリース__日経News情報11/24週テスト運用① | F13: 生麦X | G13: デリバリ完了 | H13: P1999-0011-01 | I13: IC-Energy_石油3社のプレスリリース__日経News情報11/24週テスト運用① | J13: 集計完了 | K13: ayumi.wada | L13: takuma.fukazawa | M13: takashi.muramatsu | N13: 44889.375 | O13: 44889.375 | P13: 44889.375 | Q13: 44889.375
A14: F009113-01 | B14: A1025 | C14: 人事異動・組織改編情報チェック(自動化) | D14: A1025-0880 | E14: Nトレーニング人事異動（佐藤さん）⑦ | F14: 生麦X | G14: デリバリ完了 | H14: A1025-0880-01 | I14: Nトレーニング人事異動（佐藤さん）⑦ | J14: 集計完了 | K14: takao.hattori | M14: takao.hattori | N14: 45974 | P14: 45974 | Q14: 45974
A15: F009116-01 | B15: A1025 | C15: 人事異動・組織改編情報チェック(自動化) | D15: A1025-0881 | E15: Nトレーニング人事異動（佐藤さん）⑦ | F15: 生麦X | G15: デリバリ完了 | H15: A1025-0881-01 | I15: Nトレーニング人事異動（佐藤さん）⑦ | J15: 集計完了 | K15: yuya.tanigaki | L15: yuya.tanigaki | N15: 45974 | O15: 45974 | Q15: 45974
A16: F009117-01 | B16: P3999 | C16: テスト運用サービス・データ計測不可(共通) | D16: P3999-1701 | E16: Nトレーニング人事異動（佐藤さん）⑦ | F16: 生麦X | G16: デリバリ完了 | H16: P3999-1701-01 | I16: Nトレーニング人事異動（佐藤さん）⑦ | J16: 集計完了 | K16: yuya.tanigaki | L16: yuya.tanigaki | N16: 45974 | O16: 45974 | Q16: 45975
A17: F009122-1 | B17: P3999 | C17: テスト運用サービス・データ計測不可(共通) | D17: P3999-1705 | E17: Nトレーニング人事異動（佐藤さん）⑦ | F17: 生麦X | G17: デリバリ完了 | H17: P3999-1705-01 | I17: Nトレーニング人事異動（佐藤さん）⑦ | J17: 集計完了 | K17: yuya.tanigaki | L17: yuya.tanigaki | N17: 45974 | O17: 45974 | Q17: 45974
A18: F009118-1 | B18: P3999 | C18: テスト運用サービス・データ計測不可(共通) | D18: P3999-1702 | E18: Nトレーニング人事異動（山岸さん）⑦ | F18: 生麦X | G18: デリバリ完了 | H18: P3999-1702-01 | I18: Nトレーニング人事異動（山岸さん）⑦ | J18: 集計完了 | K18: yuya.tanigaki | L18: yuya.tanigaki | N18: 45974 | O18: 45974 | Q18: 45975
A19: F009121-1 | B19: P3999 | C19: テスト運用サービス・データ計測不可(共通) | D19: P3999-1704 | E19: Nトレーニング人事異動（山岸さん）⑦ | F19: 生麦X | G19: デリバリ完了 | H19: P3999-1704-01 | I19: Nトレーニング人事異動（山岸さん）⑦ | J19: 集計完了 | K19: yuya.tanigaki | L19: yuya.tanigaki | N19: 45974 | O19: 45974 | Q19: 45974
B20: A1072 | C20: Technology_アクセンチュア健保_chatbot運用保守 | D20: A1072-0036 | E20: Technology_アクセンチュア健保_chatbot運用保守2/3・6 | F20: 生麦X | G20: デリバリ完了 | H20: A1072-0036-01 | I20: Technology_アクセンチュア健保_chatbot運用保守2/3・6 | J20: 集計完了 | K20: takuma.fukazawa | L20: ryota.nozawa | M20: ryota.nozawa | N20: 44960.375 | O20: 44963.375 | P20: 44963.375 | Q20: 44963.375
B21: A1025 | C21: 人事異動・組織改編情報チェック(自動化) | D21: A1025-0409 | E21: (追加)(PRD_人事異動・組織改編情報チェック(日経転記)⑥(3/4週) | F21: 生麦X | G21: デリバリ完了 | H21: A1025-0409-01 | I21: (追加)(PRD_人事異動・組織改編情報チェック(日経転記)⑥(3/4週) | J21: 集計完了 | K21: kazuma.motoyama | L21: ayumi.wada | M21: kazuma.motoyama | N21: 45355 | O21: 45359 | P21: 45359 | Q21: 45359
B22: A1025 | C22: 人事異動・組織改編情報チェック(自動化) | D22: A1025-0408 | E22: (追加)PRD_人事異動・組織改編情報チェック(日経転記)⑤(3/4週) | F22: 生麦X | G22: デリバリ完了 | H22: A1025-0408-01 | I22: (追加)PRD_人事異動・組織改編情報チェック(日経転記)⑤(3/4週) | J22: 集計完了 | K22: ayumi.wada | L22: kazuma.motoyama | M22: kazuma.motoyama | N22: 45355 | O22: 45359 | P22: 45359 | Q22: 45359
B23: P1000 | C23: 共通(SN) | D23: P1000-0130 | E23: [A1024]Digital_マイナポWeb問合せ回答_マニュアル修正 | F23: 生麦X | G23: デリバリ完了 | H23: P1000-0130-01 | I23: [A1024]Digital_マイナポWeb問合せ回答_マニュアル修正 | J23: 集計完了 | K23: yuichi.kimura | L23: ryota.nozawa | M23: shigeki.ohtake | N23: 44950.375 | O23: 44953.375 | P23: 44953.375 | Q23: 44953.375
B24: P1000 | C24: 共通(SN) | D24: P1000-0137 | E24: [A1046]CMT_クライアントのメディアリリース情報確認_マニュアル修正 | F24: 生麦X | G24: デリバリ完了 | H24: P1000-0137-01 | I24: [A1046]CMT_クライアントのメディアリリース情報確認_マニュアル修正 | J24: 集計完了 | K24: yumi.terui | L24: takuma.fukazawa | M24: ayumi.wada | N24: 44970.375 | O24: 44970.375 | P24: 44985.375 | Q24: 44985.375
A25: F006714-01 | B25: P3999 | C25: テスト運用サービス・データ計測不可(共通) | D25: P3999-1523 | E25: _HR_安全衛生委員会データ作成【横田さん】 | F25: 生麦X | G25: デリバリ完了 | H25: P3999-1523-01 | I25: HR_安全衛生委員会データ作成【横田さん】 | J25: 集計完了 | K25: shinji.yokota | M25: shingo.a.maeda | N25: 45861 | P25: 45861 | Q25: 45861
A26: F009549-01 | B26: P3999 | C26: テスト運用サービス・データ計測不可(共通) | D26: P3999-1742 | E26: 【〆野さん】NトレーニングSupplier | F26: 生麦X | G26: デリバリ完了 | H26: P3999-1742-01 | I26: 【〆野さん】NトレーニングSupplier ① | J26: 集計完了 | K26: kasumi.shimeno | L26: takao.hattori | M26: keita.anzai | N26: 46000 | O26: 46000 | P26: 46000 | Q26: 46014
A27: F009549-01 | B27: P3999 | C27: テスト運用サービス・データ計測不可(共通) | D27: P3999-1742 | E27: 【〆野さん】NトレーニングSupplier | F27: 生麦X | G27: デリバリ完了 | H27: P3999-1742-02 | I27: 【〆野さん】NトレーニングSupplier ② | J27: 集計完了 | K27: kasumi.shimeno | L27: minoru.fujita | M27: keita.anzai | N27: 46001 | O27: 46001 | P27: 46001 | Q27: 46001
A28: F009549-01 | B28: P3999 | C28: テスト運用サービス・データ計測不可(共通) | D28: P3999-1742 | E28: 【〆野さん】NトレーニングSupplier | F28: 生麦X | G28: デリバリ完了 | H28: P3999-1742-03 | I28: 【〆野さん】NトレーニングSupplier ③ | J28: 集計完了 | K28: kasumi.shimeno | L28: minoru.fujita | M28: keita.anzai | N28: 46003 | O28: 46003 | P28: 46003 | Q28: 46017
A29: F009698-01 | B29: P3999 | C29: テスト運用サービス・データ計測不可(共通) | D29: P3999-1757 | E29: 【〆野さん】サーバールームTRG | F29: 生麦X | G29: デリバリ完了 | H29: P3999-1757-01 | I29: 【〆野さん】サーバールームTRG(7月分)【Excel工程】 | J29: 集計完了 | K29: kasumi.shimeno | L29: shinra.sakaki | M29: takao.hattori | N29: 46010 | O29: 46010 | P29: 46010 | Q29: 46010
A30: F009698-01 | B30: P3999 | C30: テスト運用サービス・データ計測不可(共通) | D30: P3999-1757 | E30: 【〆野さん】サーバールームTRG | F30: 生麦X | G30: デリバリ完了 | H30: P3999-1757-02 | I30: 【〆野さん】サーバールームTRG(7月分)【メール工程】 | J30: 集計完了 | K30: kasumi.shimeno | L30: shinra.sakaki | M30: takao.hattori | N30: 46010 | O30: 46010 | P30: 46010 | Q30: 46010
A31: F009717-01 | B31: P3999 | C31: テスト運用サービス・データ計測不可(共通) | D31: P3999-1766 | E31: 【〆野さん】サーバールームTRG 8月分 | F31: 生麦X | G31: デリバリ完了 | H31: P3999-1766-01 | I31: 【〆野さん】サーバールームTRG 8月分 Excel作成工程 | J31: 集計完了 | K31: kasumi.shimeno | L31: shinra.sakaki | M31: takao.hattori | N31: 46013 | O31: 46013 | P31: 46013 | Q31: 46017
A32: F009717-01 | B32: P3999 | C32: テスト運用サービス・データ計測不可(共通) | D32: P3999-1766 | E32: 【〆野さん】サーバールームTRG 8月分 | F32: 生麦X | G32: デリバリ完了 | H32: P3999-1766-02 | I32: 【〆野さん】サーバールームTRG 8月分 メール作成工程 | J32: 集計完了 | K32: kasumi.shimeno | L32: shinra.sakaki | M32: takao.hattori | N32: 46013 | O32: 46013 | P32: 46013 | Q32: 46017
A33: F006857-01 | B33: P3999 | C33: テスト運用サービス・データ計測不可(共通) | D33: P3999-1542 | E33: 【〇〇さん】HR_myTIM（Google）Excelデータ作成 | F33: 生麦X | G33: デリバリ完了 | H33: P3999-1542-01 | I33: 【〇〇さん】HR_myTIM（Google）Excel①工程 | J33: 集計完了 | K33: takao.hattori | M33: shingo.a.maeda | N33: 45868 | P33: 45868 | Q33: 45868
A34: F006857-01 | B34: P3999 | C34: テスト運用サービス・データ計測不可(共通) | D34: P3999-1542 | E34: 【〇〇さん】HR_myTIM（Google）Excelデータ作成 | F34: 生麦X | G34: デリバリ完了 | H34: P3999-1542-02 | I34: 【〇〇さん】HR_myTIM（Google）Excel②工程 | J34: 集計完了 | K34: takao.hattori | M34: shingo.a.maeda | N34: 45868 | P34: 45868 | Q34: 45868
A35: F000553-1 | B35: P3998 | C35: テスト運用サービス(共通) | D35: P3998-0048 | E35: 【3週目】テスト案件_PRD_中計・決算発表チェック&レポート作成(優先50社） | F35: 生麦X | G35: デリバリ完了 | H35: P3998-0048-01 | I35: 【3週目】テスト案件_PRD_中計・決算発表チェック&レポート作成(優先50社） | J35: 集計完了 | K35: takumi.kurematsu | L35: takashi.muramatsu | M35: kazuma.motoyama | N35: 45454 | O35: 45457 | P35: 45457 | Q35: 45457
B36: P1000 | C36: 共通(SN) | D36: P1000-0101 | E36: 【A0003】IC-Energy_石油3社のプレスリリース_日経News情報 マニュアル修正 | F36: 生麦X | G36: デリバリ完了 | H36: P1000-0101-01 | I36: 【A0003】IC-Energy_石油3社のプレスリリース_日経News情報 マニュアル修正 | J36: SVレビュー | K36: ayumi.wada | L36: takuma.fukazawa | M36: takashi.muramatsu | N36: 44890.375 | O36: 44893.375 | P36: 44893.375 | Q36: 44895.375
B37: P1000 | C37: 共通(SN) | D37: P1000-0192 | E37: 【A0065】Procurement_在宅勤務サポートプログラム メールテンプレート追加 | F37: 生麦X | G37: デリバリ完了 | H37: P1000-0192-01 | I37: 【A1065】Procurement_在宅勤務サポートプログラム メールテンプレート追記 | J37: 集計完了 | K37: ayumi.wada | L37: kazuma.motoyama | M37: takashi.muramatsu | N37: 45075.375 | O37: 45075.375 | P37: 45075.375 | Q37: 45075.375
B38: P1000 | C38: 共通(SN) | D38: P1000-0270 | E38: 【A1025】PRD_人事異動・組織改編情報チェック(自動化)マニュアル_レビューチェックシート修正 | F38: 生麦X | G38: デリバリ完了 | H38: P1000-0270-01 | I38: 【A1025】PRD_人事異動・組織改編情報チェック(自動化)マニュアル_レビューチェックシート修正 | J38: 集計完了 | K38: ayumi.wada | L38: kazuma.motoyama | M38: shigeki.ohtake | N38: 45174.375 | O38: 45174.375 | P38: 45174.375 | Q38: 45184.375
B39: P1000 | C39: 共通(SN) | D39: P1000-0207 | E39: 【A1025】PRD_人事異動・組織改編情報チェック(自動化)マニュアル修正 | F39: 生麦X | G39: デリバリ完了 | H39: P1000-0207-01 | I39: 【A1025】PRD_人事異動・組織改編情報チェック(自動化)マニュアル修正 | J39: 集計完了 | K39: takashi.muramatsu | M39: shigeki.ohtake | N39: 45082.375 | P39: 45086.375 | Q39: 45086.375
B40: P1000 | C40: 共通(SN) | D40: P1000-0182 | E40: 【A1025】PRD_人事異動・組織改編情報チェック(自動化)マニュアル精査 | F40: 生麦X | G40: デリバリ完了 | H40: P1000-0182-01 | I40: 【A1025】PRD_人事異動・組織改編情報チェック(自動化)マニュアル精査 | J40: 集計完了 | K40: shinsuke.eto | L40: ayumi.wada | M40: takashi.muramatsu | N40: 45040.375 | O40: 45058.375 | P40: 45058.375 | Q40: 45058.375
B41: P1999 | C41: テスト運用サービス(SN) | D41: P1999-0084 | E41: 【A1025】人事異動マニュアル修正 | F41: 生麦X | G41: デリバリ完了 | H41: P1999-0084-01 | I41: 【A1025】人事異動マニュアル修正 | J41: 集計完了 | K41: shingo.a.maeda | M41: ayumi.wada | N41: 45379 | P41: 45379 | Q41: 45385
B42: P1000 | C42: 共通(SN) | D42: P1000-0385 | E42: 【A1025】人事異動マニュアル更新 | F42: 生麦X | G42: デリバリ完了 | H42: P1000-0385-01 | I42: 【A1025】人事異動マニュアル更新 | J42: 集計完了 | K42: shingo.a.maeda | L42: ayumi.wada | M42: shigeki.ohtake | N42: 45387 | O42: 45387 | P42: 45387 | Q42: 45387
B43: P1000 | C43: 共通(SN) | D43: P1000-0191 | E43: 【A1031】I&D_Women's stories記事配信 マニュアル修正 | F43: 生麦X | G43: デリバリ完了 | H43: P1000-0191-01 | I43: 【A1031】I&D_Women's stories記事配信 マニュアル修正 | J43: 集計完了 | K43: yuichi.kimura | L43: riamu.daikusu | M43: ryota.nozawa | N43: 45070.375 | O43: 45071.375 | P43: 45077.375 | Q43: 45077.375
B44: P1000 | C44: 共通(SN) | D44: P1000-0276 | E44: 【A1046】CMT_クライアントのメディアリリース情報確認_マニュアル修正 | F44: 生麦X | G44: デリバリ完了 | H44: P1000-0276-01 | I44: 【A1046】CMT_クライアントのメディアリリース情報確認_マニュアル修正 | J44: 集計完了 | K44: ayumi.wada | L44: takashi.muramatsu | M44: shigeki.ohtake | N44: 45180.375 | O44: 45180.375 | P44: 45180.375 | Q44: 45184.375
B45: P1000 | C45: 共通(SN) | D45: P1000-0180 | E45: 【A1054】Security_脆弱性情報マニュアル・納品テンプレート更新 | F45: 生麦X | G45: デリバリ完了 | H45: P1000-0180-01 | I45: 【A1054】Security_脆弱性情報マニュアル・納品テンプレート更新 | J45: 集計完了 | K45: takuma.fukazawa | M45: takashi.muramatsu | N45: 45033.375 | P45: 45033.375 | Q45: 45035.375
B46: P1999 | C46: テスト運用サービス(SN) | D46: P1999-0027 | E46: 【A1065】在宅勤務サポートプログラムテスト運用メール送付① | F46: 生麦X | G46: デリバリ完了 | H46: P1999-0027-01 | I46: 【A1065】在宅勤務サポートプログラムテスト運用メール送付① | J46: 集計完了 | K46: takuma.fukazawa | L46: yuichi.kimura | M46: ayumi.wada | N46: 44972.375 | O46: 44973.375 | P46: 44974.375 | Q46: 44974.375
B47: P1999 | C47: テスト運用サービス(SN) | D47: P1999-0028 | E47: 【A1065】在宅勤務サポートプログラムテスト運用メール送付② | F47: 生麦X | G47: デリバリ完了 | H47: P1999-0028-01 | I47: 【A1065】在宅勤務サポートプログラムテスト運用メール送付② | J47: 集計完了 | K47: yumi.terui | L47: koji.fukui | M47: ayumi.wada | N47: 44972.375 | O47: 44973.375 | P47: 44974.375 | Q47: 44974.375
B48: P1999 | C48: テスト運用サービス(SN) | D48: P1999-0029 | E48: 【A1065】在宅勤務サポートプログラムテスト運用メール送付② | F48: 生麦X | G48: デリバリ完了 | H48: P1999-0029-01 | I48: 【A1065】在宅勤務サポートプログラムテスト運用メール送付③ | J48: 集計完了 | K48: yuichi.kimura | L48: takuma.fukazawa | M48: takashi.muramatsu | N48: 44972.375 | O48: 44973.375 | P48: 44974.375 | Q48: 44974.375
B49: P1999 | C49: テスト運用サービス(SN) | D49: P1999-0030 | E49: 【A1065】在宅勤務サポートプログラムテスト運用メール送付④ | F49: 生麦X | G49: デリバリ完了 | H49: P1999-0030-01 | I49: 【A1065】在宅勤務サポートプログラムテスト運用メール送付④ | J49: 集計完了 | K49: koji.fukui | L49: yumi.terui | M49: takashi.muramatsu | N49: 44972.375 | O49: 44973.375 | P49: 44974.375 | Q49: 44974.375
B50: P1999 | C50: テスト運用サービス(SN) | D50: P1999-0031 | E50: 【A1065】在宅勤務サポートプログラムテスト運用メール送付④ | F50: 生麦X | G50: デリバリ完了 | H50: P1999-0031-01 | I50: 【A1065】在宅勤務サポートプログラムテスト運用メール送付⑤ | J50: 集計完了 | K50: kazuma.motoyama | L50: rei.hasegawa | M50: ayumi.wada | N50: 44972.375 | O50: 44973.375 | P50: 44974.375 | Q50: 44974.375
B51: P1999 | C51: テスト運用サービス(SN) | D51: P1999-0032 | E51: 【A1065】在宅勤務サポートプログラムテスト運用メール送付⑥ | F51: 生麦X | G51: デリバリ完了 | H51: P1999-0032-01 | I51: 【A1065】在宅勤務サポートプログラムテスト運用メール送付⑥ | J51: 集計完了 | K51: rei.hasegawa | L51: kazuma.motoyama | M51: takashi.muramatsu | N51: 44972.375 | O51: 44973.375 | P51: 44974.375 | Q51: 44974.375
B52: P1999 | C52: テスト運用サービス(SN) | D52: P1999-0033 | E52: 【A1065】在宅勤務サポートプログラムテスト運用管理担当① | F52: 生麦X | G52: デリバリ完了 | H52: P1999-0033-01 | I52: 【A1065】在宅勤務サポートプログラムテスト運用管理担当① | J52: 集計完了 | K52: kazuma.motoyama | L52: ayumi.wada | M52: takashi.muramatsu | N52: 44971.375 | O52: 44972.375 | P52: 44973.375 | Q52: 44974.375
B53: P1999 | C53: テスト運用サービス(SN) | D53: P1999-0034 | E53: 【A1065】在宅勤務サポートプログラムテスト運用管理担当② | F53: 生麦X | G53: デリバリ完了 | H53: P1999-0034-01 | I53: 【A1065】在宅勤務サポートプログラムテスト運用管理担当② | J53: 集計完了 | K53: rei.hasegawa | L53: ayumi.wada | M53: takashi.muramatsu | N53: 44971.375 | O53: 44972.375 | P53: 44973.375 | Q53: 44974.375
B54: P1999 | C54: テスト運用サービス(SN) | D54: P1999-0015 | E54: 【A1072】Technology_アクセンチュア健保_chatbot運用保守12/2/5① | F54: 生麦X | G54: デリバリ完了 | H54: P1999-0015-01 | I54: 【A1072】Technology_アクセンチュア健保_chatbot運用保守12/2/5① | J54: 集計完了 | K54: ayumi.wada | L54: rei.hasegawa | M54: takashi.muramatsu | N54: 44897.375 | O54: 44900.375 | P54: 44900.375 | Q54: 44900.375
B55: P1999 | C55: テスト運用サービス(SN) | D55: P1999-0016 | E55: 【A1072】Technology_アクセンチュア健保_chatbot運用保守12/2/5① | F55: 生麦X | G55: デリバリ完了 | H55: P1999-0016-01 | I55: 【A1072】Technology_アクセンチュア健保_chatbot運用保守12/2/5② | J55: 集計完了 | K55: yumi.terui | L55: takuma.fukazawa | M55: takashi.muramatsu | N55: 44897.375 | O55: 44900.375 | P55: 44900.375 | Q55: 44900.375
B56: P1999 | C56: テスト運用サービス(SN) | D56: P1999-0019 | E56: 【A1072】Technology_アクセンチュア健保_chatbot運用保守12/2/5①(Aチーム） | F56: 生麦X | G56: デリバリ完了 | H56: P1999-0019-01 | I56: 【A1072】Technology_アクセンチュア健保_chatbot運用保守12/2/5①(Aチーム） | J56: 集計完了 | K56: yuichi.kimura | L56: riamu.daikusu | M56: ryota.nozawa | N56: 44897.375 | O56: 44897.375 | P56: 44897.375 | Q56: 44900.375
B57: P1999 | C57: テスト運用サービス(SN) | D57: P1999-0019 | E57: 【A1072】Technology_アクセンチュア健保_chatbot運用保守12/2/5①(Aチーム） | F57: 生麦X | G57: デリバリ完了 | H57: P1999-0019-02 | I57: 【A1072】Technology_アクセンチュア健保_chatbot運用保守12/8/12①(Aチーム） | J57: 集計完了 | K57: yuichi.kimura | L57: riamu.daikusu | M57: ryota.nozawa | N57: 44904.375 | O57: 44904.375 | P57: 44904.375 | Q57: 44907.375
... B69: P1999 | C69: テスト運用サービス(SN) | D69: P1999-0026 | E69: 【A1072】Technology_アクセンチュア健保_chatbot運用保守12/9/12④ | F69: 生麦X | G69: デリバリ完了 | H69: P1999-0026-01 | I69: 【A1072】Technology_アクセンチュア健保_chatbot運用保守12/9/12④ | J69: 集計完了 | K69: takuma.fukazawa | L69: ayumi.wada | M69: takashi.muramatsu | N69: 44904.375 | O69: 44907.375 | P69: 44907.375 | Q69: 44907.375
B70: P1000 | C70: 共通(SN) | D70: P1000-0042 | E70: 【A1073】S&C_購買レポートリスト更新_マニュアル更新 | F70: 生麦X | G70: デリバリ完了 | H70: P1000-0042-01 | I70: 【A1073】S&C_購買レポートリスト更新_マニュアル更新 | J70: 内部レビュー完了 | K70: kotaro.honma | L70: kotaro.honma | N70: 44826.375 | O70: 44840.375 | P70: 44840.375 | Q70: 44841.375
A71: F001199-1 | B71: P3999 | C71: テスト運用サービス(共通) | D71: P3999-0227 | E71: 【IC-Energy】Nグループ練習（谷口さん） | F71: 生麦X | G71: デリバリ完了 | H71: P3999-0227-01 | I71: 【IC-Energy】Nグループ練習（谷口さん） | J71: 集計完了 | K71: shunsuke.taniguchi | L71: eri.wakabayashi | M71: takashi.muramatsu | N71: 45505 | O71: 45505 | P71: 45505 | Q71: 45505
A72: F001197-1 | B72: P3999 | C72: テスト運用サービス(共通) | D72: P3999-0226 | E72: 【IC-Energy】Nグループ練習（谷川さん） | F72: 生麦X | G72: デリバリ完了 | H72: P3999-0226-01 | I72: 【IC-Energy】Nグループ練習（谷川さん） | J72: 集計完了 | K72: hironori.tanikawa | L72: eri.wakabayashi | M72: takashi.muramatsu | N72: 45505 | O72: 45505 | P72: 45505 | Q72: 45505
A73: F001201-1 | B73: P3999 | C73: テスト運用サービス(共通) | D73: P3999-0228 | E73: 【IC-Energy】Nグループ練習8/5週（谷口さん） | F73: 生麦X | G73: デリバリ完了 | H73: P3999-0228-01 | I73: 【IC-Energy】Nグループ練習8/5週（谷口さん） | J73: 集計完了 | K73: shunsuke.taniguchi | L73: eri.wakabayashi | M73: takashi.muramatsu | N73: 45512 | O73: 45512 | P73: 45512 | Q73: 45512
A74: F001202-1 | B74: P3999 | C74: テスト運用サービス(共通) | D74: P3999-0229 | E74: 【IC-Energy】Nグループ練習8/5週（谷川さん） | F74: 生麦X | G74: デリバリ完了 | H74: P3999-0229-01 | I74: 【IC-Energy】Nグループ練習8/5週（谷川さん） | J74: 集計完了 | K74: hironori.tanikawa | L74: eri.wakabayashi | M74: takashi.muramatsu | N74: 45512 | O74: 45512 | P74: 45512 | Q74: 45512
A75: F005791-1 | B75: P3999 | C75: テスト運用サービス・データ計測不可(共通) | D75: P3999-1407 | E75: 【myTIM】HR_myTIM/OTデータ作成(Google) 6/9週 | F75: 生麦X | G75: デリバリ完了 | H75: P3999-1407-01 | I75: 【myTIM】HR_myTIM/OTデータ作成(Google) 6/9週 Excel作業 | J75: 集計完了 | K75: riamu.daikusu | L75: shinra.sakaki | M75: ryota.nozawa | N75: 45817 | O75: 45817 | P75: 45821 | Q75: 45821
A76: F005791-1 | B76: P3999 | C76: テスト運用サービス・データ計測不可(共通) | D76: P3999-1407 | E76: 【myTIM】HR_myTIM/OTデータ作成(Google) 6/9週 | F76: 生麦X | G76: デリバリ完了 | H76: P3999-1407-02 | I76: 【myTIM】HR_myTIM/OTデータ作成(Google) 6/9週 メール作業 | J76: 集計完了 | K76: riamu.daikusu | L76: shinra.sakaki | M76: ryota.nozawa | N76: 45817 | O76: 45817 | P76: 45821 | Q76: 45821
A77: F007900-1 | B77: A0098 | C77: HR_myTIM/OTデータ作成(Google) | D77: A0098-0022 | E77: 【myTIM】HR_myTIM/OTデータ作成(Google) 10/13週 | F77: 生麦X | G77: デリバリ完了 | H77: A0098-0022-01 | I77: 【myTIM】HR_myTIM/OTデータ作成(Google) 10/13週 Excel作業 | J77: 集計完了 | K77: shinsuke.eto | L77: naoto.maejima | M77: ryusei.inaba | N77: 45944 | O77: 45947 | P77: 45947 | Q77: 45947
A78: F007900-1 | B78: A0098 | C78: HR_myTIM/OTデータ作成(Google) | D78: A0098-0022 | E78: 【myTIM】HR_myTIM/OTデータ作成(Google) 10/13週 | F78: 生麦X | G78: デリバリ完了 | H78: A0098-0022-02 | I78: 【myTIM】HR_myTIM/OTデータ作成(Google) 10/13週 メール作業 | J78: 集計完了 | K78: shinsuke.eto | L78: naoto.maejima | M78: ryusei.inaba | N78: 45944 | O78: 45947 | P78: 45947 | Q78: 45947
A79: F007996-1 | B79: A0098 | C79: HR_myTIM/OTデータ作成(Google) | D79: A0098-0023 | E79: 【myTIM】HR_myTIM/OTデータ作成(Google) 10/20週 | F79: 生麦X | G79: デリバリ完了 | H79: A0098-0023-01 | I79: 【myTIM】HR_myTIM/OTデータ作成(Google) 10/20週 Excel作業 | J79: 集計完了 | K79: naoto.maejima | L79: rintaro.watanabe | M79: ryusei.inaba | N79: 45950 | O79: 45954 | P79: 45954 | Q79: 45954
A80: F007996-1 | B80: A0098 | C80: HR_myTIM/OTデータ作成(Google) | D80: A0098-0023 | E80: 【myTIM】HR_myTIM/OTデータ作成(Google) 10/20週 | F80: 生麦X | G80: デリバリ完了 | H80: A0098-0023-02 | I80: 【myTIM】HR_myTIM/OTデータ作成(Google) 10/20週 メール作業 | J80: 集計完了 | K80: naoto.maejima | L80: rintaro.watanabe | M80: ryusei.inaba | N80: 45950 | O80: 45954 | P80: 45954 | Q80: 45954
A81: F008105-01 | B81: A0098 | C81: HR_myTIM/OTデータ作成(Google) | D81: A0098-0024 | E81: 【myTIM】HR_myTIM/OTデータ作成(Google) 10/27週 | F81: 生麦X | G81: デリバリ完了 | H81: A0098-0024-01 | I81: 【myTIM】HR_myTIM/OTデータ作成(Google) 10/27週 Excel作業 | J81: 内部レビュー完了 | K81: naoto.maejima | L81: shunsuke.taniguchi | M81: ryusei.inaba | N81: 45957 | O81: 45961 | P81: 45961 | Q81: 45961
A82: F008105-01 | B82: A0098 | C82: HR_myTIM/OTデータ作成(Google) | D82: A0098-0024 | E82: 【myTIM】HR_myTIM/OTデータ作成(Google) 10/27週 | F82: 生麦X | G82: デリバリ完了 | H82: A0098-0024-02 | I82: 【myTIM】HR_myTIM/OTデータ作成(Google) 10/27週 メール作業 | J82: 内部レビュー完了 | K82: naoto.maejima | L82: shunsuke.taniguchi | M82: ryusei.inaba | N82: 45957 | O82: 45961 | P82: 45961 | Q82: 45961
... A110: F006660-1 | B110: A0098 | C110: HR_myTIM/OTデータ作成(Google) | D110: A0098-0006 | E110: 【myTIM】HR_myTIM/OTデータ作成(Google) 7/22週 | F110: 生麦X | G110: デリバリ完了 | H110: A0098-0006-02 | I110: 【myTIM】HR_myTIM/OTデータ作成(Google) 7/22週 メール作業 | J110: 集計完了 | K110: rintaro.watanabe | L110: shinsuke.eto | M110: ryusei.inaba | N110: 45860 | O110: 45860 | P110: 45863 | Q110: 45863
A111: F006661-1 | B111: A0098 | C111: HR_myTIM/OTデータ作成(Google) | D111: A0098-0007 | E111: 【myTIM】HR_myTIM/OTデータ作成(Google) 7/22週 Excel作業 | F111: 生麦X | G111: デリバリ完了 | H111: A0098-0007-01 | I111: 【myTIM】HR_myTIM/OTデータ作成(Google) 7/28週 Excel作業 | J111: 集計完了 | K111: shingo.a.maeda | L111: shingo.a.maeda | N111: 45856 | O111: 45856 | Q111: 45856
A112: F006662-1 | B112: A0098 | C112: HR_myTIM/OTデータ作成(Google) | D112: A0098-0008 | E112: 【myTIM】HR_myTIM/OTデータ作成(Google) 7/22週 メール作業 | F112: 生麦X | G112: デリバリ完了 | H112: A0098-0008-01 | I112: 【myTIM】HR_myTIM/OTデータ作成(Google) 8/4週 Excel作業 | J112: 集計完了 | K112: shingo.a.maeda | L112: shingo.a.maeda | N112: 45856 | O112: 45856 | Q112: 45856
A113: F006810-1 | B113: A0098 | C113: HR_myTIM/OTデータ作成(Google) | D113: A0098-0009 | E113: 【myTIM】HR_myTIM/OTデータ作成(Google) 7/28週 | F113: 生麦X | G113: デリバリ完了 | H113: A0098-0009-01 | I113: 【myTIM】HR_myTIM/OTデータ作成(Google) 7/28週 Excel工程 | J113: 内部レビュー完了 | K113: shunsuke.taniguchi | L113: shinsuke.eto | M113: ryusei.inaba | N113: 45866 | O113: 45870 | P113: 45870 | Q113: 45870
A114: F006810-1 | B114: A0098 | C114: HR_myTIM/OTデータ作成(Google) | D114: A0098-0009 | E114: 【myTIM】HR_myTIM/OTデータ作成(Google) 7/28週 | F114: 生麦X | G114: デリバリ完了 | H114: A0098-0009-02 | I114: 【myTIM】HR_myTIM/OTデータ作成(Google) 7/28週 メール工程 | J114: 内部レビュー完了 | K114: shunsuke.taniguchi | L114: shinsuke.eto | M114: ryusei.inaba | N114: 45866 | O114: 45870 | P114: 45870 | Q114: 45870
A115: F006351-01 | B115: A0098 | C115: HR_myTIM/OTデータ作成(Google) | D115: A0098-0004 | E115: 【myTIM】HR_myTIM/OTデータ作成(Google) 7/7週 | F115: 生麦X | G115: デリバリ完了 | H115: A0098-0004-01 | I115: 【myTIM】HR_myTIM/OTデータ作成(Google) 7/7週 Excel作業 | J115: 集計完了 | K115: shunsuke.taniguchi | L115: riamu.daikusu | M115: ryusei.inaba | N115: 45845 | O115: 45849 | P115: 45849 | Q115: 45849
A116: F006351-01 | B116: A0098 | C116: HR_myTIM/OTデータ作成(Google) | D116: A0098-0004 | E116: 【myTIM】HR_myTIM/OTデータ作成(Google) 7/7週 | F116: 生麦X | G116: デリバリ完了 | H116: A0098-0004-02 | I116: 【myTIM】HR_myTIM/OTデータ作成(Google) 7/7週 メール作業 | J116: 集計完了 | K116: shunsuke.taniguchi | L116: riamu.daikusu | M116: ryusei.inaba | N116: 45845 | O116: 45849 | P116: 45849 | Q116: 45849
A117: F007073-1 | B117: A0098 | C117: HR_myTIM/OTデータ作成(Google) | D117: A0098-0012 | E117: 【myTIM】HR_myTIM/OTデータ作成(Google) 8/18週 | F117: 生麦X | G117: デリバリ完了 | H117: A0098-0012-01 | I117: 【myTIM】HR_myTIM/OTデータ作成(Google) 8/18週 Excel工程 | J117: 集計完了 | K117: shinra.sakaki | L117: rintaro.watanabe | M117: ryusei.inaba | N117: 45887 | O117: 45891 | P117: 45891 | Q117: 45891
A118: F007073-1 | B118: A0098 | C118: HR_myTIM/OTデータ作成(Google) | D118: A0098-0012 | E118: 【myTIM】HR_myTIM/OTデータ作成(Google) 8/18週 | F118: 生麦X | G118: デリバリ完了 | H118: A0098-0012-02 | I118: 【myTIM】HR_myTIM/OTデータ作成(Google) 8/18週 メール工程 | J118: 集計完了 | K118: shinra.sakaki | L118: rintaro.watanabe | M118: ryusei.inaba | N118: 45887 | O118: 45891 | P118: 45891 | Q118: 45891
A119: F007172-1 | B119: A0098 | C119: HR_myTIM/OTデータ作成(Google) | D119: A0098-0013 | E119: 【myTIM】HR_myTIM/OTデータ作成(Google) 8/18週 | F119: 生麦X | G119: デリバリ完了 | H119: A0098-0013-01 | I119: 【myTIM】HR_myTIM/OTデータ作成(Google) 8/25週 Excel作業 | J119: 集計完了 | K119: riamu.daikusu | L119: shinsuke.eto | M119: ryusei.inaba | N119: 45894 | O119: 45898 | P119: 45898 | Q119: 45898
A120: F007172-1 | B120: A0098 | C120: HR_myTIM/OTデータ作成(Google) | D120: A0098-0013 | E120: 【myTIM】HR_myTIM/OTデータ作成(Google) 8/18週 | F120: 生麦X | G120: デリバリ完了 | H120: A0098-0013-02 | I120: 【myTIM】HR_myTIM/OTデータ作成(Google) 8/25週 メール作業 | J120: 集計完了 | K120: riamu.daikusu | L120: shinsuke.eto | M120: ryusei.inaba | N120: 45894 | O120: 45898 | P120: 45898 | Q120: 45898
A121: F006919-1 | B121: A0098 | C121: HR_myTIM/OTデータ作成(Google) | D121: A0098-0010 | E121: 【myTIM】HR_myTIM/OTデータ作成(Google) 8/4週 | F121: 生麦X | G121: デリバリ完了 | H121: A0098-0010-01 | I121: 【myTIM】HR_myTIM/OTデータ作成(Google) 8/4週 Excel作業 | J121: 集計完了 | K121: rintaro.watanabe | L121: shunsuke.taniguchi | M121: ryusei.inaba | N121: 45873 | O121: 45873 | P121: 45877 | Q121: 45877
A122: F006919-1 | B122: A0098 | C122: HR_myTIM/OTデータ作成(Google) | D122: A0098-0010 | E122: 【myTIM】HR_myTIM/OTデータ作成(Google) 8/4週 | F122: 生麦X | G122: デリバリ完了 | H122: A0098-0010-02 | I122: 【myTIM】HR_myTIM/OTデータ作成(Google) 8/4週 メール作業 | J122: 集計完了 | K122: rintaro.watanabe | L122: shunsuke.taniguchi | M122: ryusei.inaba | N122: 45873 | O122: 45873 | P122: 45877 | Q122: 45877
A123: F007514-1 | B123: A0098 | C123: HR_myTIM/OTデータ作成(Google) | D123: A0098-0017 | E123: 【myTIM】HR_myTIM/OTデータ作成(Google) 9/15週 | F123: 生麦X | G123: デリバリ完了 | H123: A0098-0017-01 | I123: 【myTIM】HR_myTIM/OTデータ作成(Google) 9/15週 Excel作業 | J123: 集計完了 | K123: shinsuke.eto | L123: shinra.sakaki | M123: ryusei.inaba | N123: 45916 | O123: 45919 | P123: 45919 | Q123: 45919
A124: F007514-1 | B124: A0098 | C124: HR_myTIM/OTデータ作成(Google) | D124: A0098-0017 | E124: 【myTIM】HR_myTIM/OTデータ作成(Google) 9/15週 | F124: 生麦X | G124: デリバリ完了 | H124: A0098-0017-02 | I124: 【myTIM】HR_myTIM/OTデータ作成(Google) 9/15週 メール作業 | J124: 集計完了 | K124: shinsuke.eto | L124: shinra.sakaki | M124: ryusei.inaba | N124: 45916 | O124: 45919 | P124: 45919 | Q124: 45919
... A132: F007410-1 | B132: A0098 | C132: HR_myTIM/OTデータ作成(Google) | D132: A0098-0015 | E132: 【myTIM】HR_myTIM/OTデータ作成(Google) 9/8週 | F132: 生麦X | G132: デリバリ完了 | H132: A0098-0015-02 | I132: 【myTIM】HR_myTIM/OTデータ作成(Google) 9/8週 メール工程 | J132: 集計完了 | K132: shunsuke.taniguchi | L132: riamu.daikusu | M132: ryusei.inaba | N132: 45908 | O132: 45912 | P132: 45912 | Q132: 45912
A133: F006638-01 | B133: P3000 | C133: 改善案件(共通) | D133: P3000-0658 | E133: 【myTIM】HR_myTIM/OTデータ作成(Google) マニュアル修正 | F133: 生麦X | G133: デリバリ完了 | H133: P3000-0658-01 | I133: 【myTIM】HR_myTIM/OTデータ作成(Google) マニュアル修正 | J133: 集計完了 | K133: shinra.sakaki | M133: yuichi.kimura | N133: 45856 | P133: 45856 | Q133: 45856
A134: F009224-01 | B134: P3000 | C134: 改善案件(共通) | D134: P3000-0838 | E134: 【myTIM】HR_myTIM/OTデータ作成(Google) マニュアル修正 | F134: 生麦X | G134: デリバリ完了 | H134: P3000-0838-01 | I134: 【myTIM】HR_myTIM/OTデータ作成(Google) マニュアル修正 | J134: 集計完了 | K134: naoto.maejima | L134: ryota.nozawa | M134: ryusei.inaba | N134: 45979 | O134: 45989 | P134: 45989 | Q134: 45989
A135: F007225-01 | B135: P3000 | C135: 改善案件(共通) | D135: P3000-0714 | E135: 【myTIM】HR_myTIM/OTデータ作成(Google) マニュアル改定 | F135: 生麦X | G135: デリバリ完了 | H135: P3000-0714-01 | I135: 【myTIM】HR_myTIM/OTデータ作成(Google) マニュアル改定 | J135: 集計完了 | K135: shinra.sakaki | L135: ryota.nozawa | M135: ryusei.inaba | N135: 45895 | O135: 45895 | P135: 45895 | Q135: 45898
A136: F004029-01 | B136: P3000 | C136: 改善案件(共通) | D136: P3000-0415 | E136: 【myTIM】マニュアル見直し | F136: 生麦X | G136: デリバリ完了 | H136: P3000-0415-01 | I136: 【myTIM】マニュアル見直し | J136: 集計完了 | K136: shinra.sakaki | L136: rintaro.watanabe | M136: yuichi.kimura | N136: 45708 | O136: 45716 | P136: 45716 | Q136: 45716
A137: F002153-1 | B137: P3999 | C137: テスト運用サービス(共通) | D137: P3999-0432 | E137: 【Nグループ】Supplier_榊さん | F137: 生麦X | G137: デリバリ完了 | H137: P3999-0432-01 | I137: 【Nグループ】Supplier_榊さん | J137: 集計完了 | K137: shinra.sakaki | L137: hironori.tanikawa | M137: takashi.muramatsu | N137: 45580 | O137: 45580 | P137: 45580 | Q137: 45590
A138: F002264-01 | B138: P3998 | C138: テスト運用サービス(共通) | D138: P3998-0096 | E138: 【Nグループ】中計1週目 榊さん | F138: 生麦X | G138: デリバリ完了 | H138: P3998-0096-01 | I138: 【Nグループ】中計1週目 榊さん | J138: 集計完了 | K138: shinra.sakaki | L138: eri.wakabayashi | M138: takashi.muramatsu | N138: 45588 | O138: 45588 | P138: 45588 | Q138: 45597
A139: F002360-1 | B139: P3998 | C139: テスト運用サービス(共通) | D139: P3998-0097 | E139: 【Nグループ】中計2週目 榊さん | F139: 生麦X | G139: デリバリ完了 | H139: P3998-0097-01 | I139: 【Nグループ】中計2週目 榊さん | J139: 集計完了 | K139: shinra.sakaki | L139: eri.wakabayashi | M139: takashi.muramatsu | N139: 45594 | O139: 45594 | P139: 45594 | Q139: 45597
A140: F002366-1 | B140: P3998 | C140: テスト運用サービス(共通) | D140: P3998-0098 | E140: 【Nグループ】中計3週目 榊さん | F140: 生麦X | G140: デリバリ完了 | H140: P3998-0098-01 | I140: 【Nグループ】中計3週目 榊さん | J140: 集計完了 | K140: shinra.sakaki | M140: takashi.muramatsu | N140: 45594 | P140: 45594 | Q140: 45597
A141: F001673-1 | B141: P3998 | C141: テスト運用サービス(共通) | D141: P3998-0072 | E141: 【Nグループ】中計一週目【安齋さん】 | F141: 生麦X | G141: デリバリ完了 | H141: P3998-0072-01 | I141: 【Nグループ】中計一週目【安齋さん】 | J141: 集計完了 | K141: keita.anzai | L141: eri.wakabayashi | M141: takashi.muramatsu | N141: 45545 | O141: 45545 | P141: 45545 | Q141: 45555
A142: F001674-1 | B142: P3998 | C142: テスト運用サービス(共通) | D142: P3998-0073 | E142: 【Nグループ】中計一週目【稲葉さん】 | F142: 生麦X | G142: デリバリ完了 | H142: P3998-0073-01 | I142: 【Nグループ】中計一週目【稲葉さん】 | J142: 集計完了 | K142: ryusei.inaba | L142: shingo.a.maeda | M142: takashi.muramatsu | N142: 45545 | O142: 45545 | P142: 45545 | Q142: 45555
A143: F001886-01 | B143: P3998 | C143: テスト運用サービス(共通) | D143: P3998-0093 | E143: 【Nグループ】中計三週目【安齋さん】 | F143: 生麦X | G143: デリバリ完了 | H143: P3998-0093-01 | I143: 【Nグループ】中計三週目【安齋さん】 | J143: 集計完了 | K143: keita.anzai | L143: eri.wakabayashi | M143: takashi.muramatsu | N143: 45562 | O143: 45562 | P143: 45562 | Q143: 45569
A144: F001737-1 | B144: P3998 | C144: テスト運用サービス(共通) | D144: P3998-0087 | E144: 【Nグループ】中計三週目【稲葉さん】 | F144: 生麦X | G144: デリバリ完了 | H144: P3998-0087-01 | I144: 【Nグループ】中計三週目【稲葉さん】 | J144: 集計完了 | K144: ryusei.inaba | L144: shingo.a.maeda | M144: takashi.muramatsu | N144: 45548 | O144: 45548 | P144: 45548 | Q144: 45555
B145: P3998 | C145: テスト運用サービス(共通) | D145: P3998-0089 | E145: 【Nグループ】中計二週目【安齋さん】 | F145: 生麦X | G145: デリバリ完了 | H145: P3998-0089-01 | I145: 【Nグループ】中計二週目【安齋さん】 | J145: 集計完了 | K145: keita.anzai | L145: eri.wakabayashi | M145: takashi.muramatsu | N145: 45554 | O145: 45554 | P145: 45554 | Q145: 45554
A146: F001701-1 | B146: P3998 | C146: テスト運用サービス(共通) | D146: P3998-0074 | E146: 【Nグループ】中計二週目【稲葉さん】 | F146: 生麦X | G146: デリバリ完了 | H146: P3998-0074-01 | I146: 【Nグループ】中計二週目【稲葉さん】 | J146: 集計完了 | K146: ryusei.inaba | L146: shingo.a.maeda | M146: takashi.muramatsu | N146: 45548 | O146: 45548 | P146: 45548 | Q146: 45555
...
